Workbook

Sheet Tabelas Auxiliares
A1: Município | B1: Regional | C1: Valor coffee break
A2: Abatiá | B2: Cornélio Procópio | C2: =IF(B2="Apucarana",22.64,(IF(B2="Campo Mourão",22.64,IF(B2="Cascavel",22.64,IF(B2="Cianorte",22.64,IF(B2="Cornélio Procópio",22.64,IF(B2="Curitiba",22.64,IF(B2="Dois Vizinhos",22.64,IF(B2="Francisco Beltrão",21.33,IF(B2="Guarapuava",22.64,IF(B2="Irati",22.64,IF(B2="Ivaiporã",19.95,IF(B2="Laranjeiras do Sul",22.64,IF(B2="Londrina",22.64,IF(B2="Maringá",22.64,IF(B2="Paranaguá",20.63,IF(B2="Paranavaí",22.64,IF(B2="Pato Branco",22,IF(B2="Ponta Grossa",22.64,IF(B2="Santo Antônio da Platina",21.58,IF(B2="Toledo",22.64,IF(B2="Umuarama",22.64,IF(B2="União da Vitória",22.64,0))))))))))))))))))))))) -> 22.64
A3: Adrianópolis | B3: Curitiba | C3: =IF(B3="Apucarana",22.64,(IF(B3="Campo Mourão",22.64,IF(B3="Cascavel",22.64,IF(B3="Cianorte",22.64,IF(B3="Cornélio Procópio",22.64,IF(B3="Curitiba",22.64,IF(B3="Dois Vizinhos",22.64,IF(B3="Francisco Beltrão",21.33,IF(B3="Guarapuava",22.64,IF(B3="Irati",22.64,IF(B3="Ivaiporã",19.95,IF(B3="Laranjeiras do Sul",22.64,IF(B3="Londrina",22.64,IF(B3="Maringá",22.64,IF(B3="Paranaguá",20.63,IF(B3="Paranavaí",22.64,IF(B3="Pato Branco",22,IF(B3="Ponta Grossa",22.64,IF(B3="Santo Antônio da Platina",21.58,IF(B3="Toledo",22.64,IF(B3="Umuarama",22.64,IF(B3="União da Vitória",22.64,0))))))))))))))))))))))) -> 22.64
A4: Agudos do Sul | B4: Curitiba | C4: =IF(B4="Apucarana",22.64,(IF(B4="Campo Mourão",22.64,IF(B4="Cascavel",22.64,IF(B4="Cianorte",22.64,IF(B4="Cornélio Procópio",22.64,IF(B4="Curitiba",22.64,IF(B4="Dois Vizinhos",22.64,IF(B4="Francisco Beltrão",21.33,IF(B4="Guarapuava",22.64,IF(B4="Irati",22.64,IF(B4="Ivaiporã",19.95,IF(B4="Laranjeiras do Sul",22.64,IF(B4="Londrina",22.64,IF(B4="Maringá",22.64,IF(B4="Paranaguá",20.63,IF(B4="Paranavaí",22.64,IF(B4="Pato Branco",22,IF(B4="Ponta Grossa",22.64,IF(B4="Santo Antônio da Platina",21.58,IF(B4="Toledo",22.64,IF(B4="Umuarama",22.64,IF(B4="União da Vitória",22.64,0))))))))))))))))))))))) -> 22.64
A5: Almirante Tamandaré | B5: Curitiba | C5: =IF(B5="Apucarana",22.64,(IF(B5="Campo Mourão",22.64,IF(B5="Cascavel",22.64,IF(B5="Cianorte",22.64,IF(B5="Cornélio Procópio",22.64,IF(B5="Curitiba",22.64,IF(B5="Dois Vizinhos",22.64,IF(B5="Francisco Beltrão",21.33,IF(B5="Guarapuava",22.64,IF(B5="Irati",22.64,IF(B5="Ivaiporã",19.95,IF(B5="Laranjeiras do Sul",22.64,IF(B5="Londrina",22.64,IF(B5="Maringá",22.64,IF(B5="Paranaguá",20.63,IF(B5="Paranavaí",22.64,IF(B5="Pato Branco",22,IF(B5="Ponta Grossa",22.64,IF(B5="Santo Antônio da Platina",21.58,IF(B5="Toledo",22.64,IF(B5="Umuarama",22.64,IF(B5="União da Vitória",22.64,0))))))))))))))))))))))) -> 22.64
A6: Altamira do Paraná | B6: Campo Mourão | C6: =IF(B6="Apucarana",22.64,(IF(B6="Campo Mourão",22.64,IF(B6="Cascavel",22.64,IF(B6="Cianorte",22.64,IF(B6="Cornélio Procópio",22.64,IF(B6="Curitiba",22.64,IF(B6="Dois Vizinhos",22.64,IF(B6="Francisco Beltrão",21.33,IF(B6="Guarapuava",22.64,IF(B6="Irati",22.64,IF(B6="Ivaiporã",19.95,IF(B6="Laranjeiras do Sul",22.64,IF(B6="Londrina",22.64,IF(B6="Maringá",22.64,IF(B6="Paranaguá",20.63,IF(B6="Paranavaí",22.64,IF(B6="Pato Branco",22,IF(B6="Ponta Grossa",22.64,IF(B6="Santo Antônio da Platina",21.58,IF(B6="Toledo",22.64,IF(B6="Umuarama",22.64,IF(B6="União da Vitória",22.64,0))))))))))))))))))))))) -> 22.64
A7: Alto Paraíso | B7: Umuarama | C7: =IF(B7="Apucarana",22.64,(IF(B7="Campo Mourão",22.64,IF(B7="Cascavel",22.64,IF(B7="Cianorte",22.64,IF(B7="Cornélio Procópio",22.64,IF(B7="Curitiba",22.64,IF(B7="Dois Vizinhos",22.64,IF(B7="Francisco Beltrão",21.33,IF(B7="Guarapuava",22.64,IF(B7="Irati",22.64,IF(B7="Ivaiporã",19.95,IF(B7="Laranjeiras do Sul",22.64,IF(B7="Londrina",22.64,IF(B7="Maringá",22.64,IF(B7="Paranaguá",20.63,IF(B7="Paranavaí",22.64,IF(B7="Pato Branco",22,IF(B7="Ponta Grossa",22.64,IF(B7="Santo Antônio da Platina",21.58,IF(B7="Toledo",22.64,IF(B7="Umuarama",22.64,IF(B7="União da Vitória",22.64,0))))))))))))))))))))))) -> 22.64
A8: Alto Paraná | B8: Paranavaí | C8: =IF(B8="Apucarana",22.64,(IF(B8="Campo Mourão",22.64,IF(B8="Cascavel",22.64,IF(B8="Cianorte",22.64,IF(B8="Cornélio Procópio",22.64,IF(B8="Curitiba",22.64,IF(B8="Dois Vizinhos",22.64,IF(B8="Francisco Beltrão",21.33,IF(B8="Guarapuava",22.64,IF(B8="Irati",22.64,IF(B8="Ivaiporã",19.95,IF(B8="Laranjeiras do Sul",22.64,IF(B8="Londrina",22.64,IF(B8="Maringá",22.64,IF(B8="Paranaguá",20.63,IF(B8="Paranavaí",22.64,IF(B8="Pato Branco",22,IF(B8="Ponta Grossa",22.64,IF(B8="Santo Antônio da Platina",21.58,IF(B8="Toledo",22.64,IF(B8="Umuarama",22.64,IF(B8="União da Vitória",22.64,0))))))))))))))))))))))) -> 22.64
A9: Alto Piquiri | B9: Umuarama | C9: =IF(B9="Apucarana",22.64,(IF(B9="Campo Mourão",22.64,IF(B9="Cascavel",22.64,IF(B9="Cianorte",22.64,IF(B9="Cornélio Procópio",22.64,IF(B9="Curitiba",22.64,IF(B9="Dois Vizinhos",22.64,IF(B9="Francisco Beltrão",21.33,IF(B9="Guarapuava",22.64,IF(B9="Irati",22.64,IF(B9="Ivaiporã",19.95,IF(B9="Laranjeiras do Sul",22.64,IF(B9="Londrina",22.64,IF(B9="Maringá",22.64,IF(B9="Paranaguá",20.63,IF(B9="Paranavaí",22.64,IF(B9="Pato Branco",22,IF(B9="Ponta Grossa",22.64,IF(B9="Santo Antônio da Platina",21.58,IF(B9="Toledo",22.64,IF(B9="Umuarama",22.64,IF(B9="União da Vitória",22.64,0))))))))))))))))))))))) -> 22.64
A10: Altônia | B10: Umuarama | C10: =IF(B10="Apucarana",22.64,(IF(B10="Campo Mourão",22.64,IF(B10="Cascavel",22.64,IF(B10="Cianorte",22.64,IF(B10="Cornélio Procópio",22.64,IF(B10="Curitiba",22.64,IF(B10="Dois Vizinhos",22.64,IF(B10="Francisco Beltrão",21.33,IF(B10="Guarapuava",22.64,IF(B10="Irati",22.64,IF(B10="Ivaiporã",19.95,IF(B10="Laranjeiras do Sul",22.64,IF(B10="Londrina",22.64,IF(B10="Maringá",22.64,IF(B10="Paranaguá",20.63,IF(B10="Paranavaí",22.64,IF(B10="Pato Branco",22,IF(B10="Ponta Grossa",22.64,IF(B10="Santo Antônio da Platina",21.58,IF(B10="Toledo",22.64,IF(B10="Umuarama",22.64,IF(B10="União da Vitória",22.64,0))))))))))))))))))))))) -> 22.64
A11: Alvorada do Sul | B11: Londrina | C11: =IF(B11="Apucarana",22.64,(IF(B11="Campo Mourão",22.64,IF(B11="Cascavel",22.64,IF(B11="Cianorte",22.64,IF(B11="Cornélio Procópio",22.64,IF(B11="Curitiba",22.64,IF(B11="Dois Vizinhos",22.64,IF(B11="Francisco Beltrão",21.33,IF(B11="Guarapuava",22.64,IF(B11="Irati",22.64,IF(B11="Ivaiporã",19.95,IF(B11="Laranjeiras do Sul",22.64,IF(B11="Londrina",22.64,IF(B11="Maringá",22.64,IF(B11="Paranaguá",20.63,IF(B11="Paranavaí",22.64,IF(B11="Pato Branco",22,IF(B11="Ponta Grossa",22.64,IF(B11="Santo Antônio da Platina",21.58,IF(B11="Toledo",22.64,IF(B11="Umuarama",22.64,IF(B11="União da Vitória",22.64,0))))))))))))))))))))))) -> 22.64
A12: Amaporã | B12: Paranavaí | C12: =IF(B12="Apucarana",22.64,(IF(B12="Campo Mourão",22.64,IF(B12="Cascavel",22.64,IF(B12="Cianorte",22.64,IF(B12="Cornélio Procópio",22.64,IF(B12="Curitiba",22.64,IF(B12="Dois Vizinhos",22.64,IF(B12="Francisco Beltrão",21.33,IF(B12="Guarapuava",22.64,IF(B12="Irati",22.64,IF(B12="Ivaiporã",19.95,IF(B12="Laranjeiras do Sul",22.64,IF(B12="Londrina",22.64,IF(B12="Maringá",22.64,IF(B12="Paranaguá",20.63,IF(B12="Paranavaí",22.64,IF(B12="Pato Branco",22,IF(B12="Ponta Grossa",22.64,IF(B12="Santo Antônio da Platina",21.58,IF(B12="Toledo",22.64,IF(B12="Umuarama",22.64,IF(B12="União da Vitória",22.64,0))))))))))))))))))))))) -> 22.64
A13: Ampére | B13: Francisco Beltrão | C13: =IF(B13="Apucarana",22.64,(IF(B13="Campo Mourão",22.64,IF(B13="Cascavel",22.64,IF(B13="Cianorte",22.64,IF(B13="Cornélio Procópio",22.64,IF(B13="Curitiba",22.64,IF(B13="Dois Vizinhos",22.64,IF(B13="Francisco Beltrão",21.33,IF(B13="Guarapuava",22.64,IF(B13="Irati",22.64,IF(B13="Ivaiporã",19.95,IF(B13="Laranjeiras do Sul",22.64,IF(B13="Londrina",22.64,IF(B13="Maringá",22.64,IF(B13="Paranaguá",20.63,IF(B13="Paranavaí",22.64,IF(B13="Pato Branco",22,IF(B13="Ponta Grossa",22.64,IF(B13="Santo Antônio da Platina",21.58,IF(B13="Toledo",22.64,IF(B13="Umuarama",22.64,IF(B13="União da Vitória",22.64,0))))))))))))))))))))))) -> 21.33
... A400: Xambrê | B400: Umuarama | C400: =IF(B400="Apucarana",22.64,(IF(B400="Campo Mourão",22.64,IF(B400="Cascavel",22.64,IF(B400="Cianorte",22.64,IF(B400="Cornélio Procópio",22.64,IF(B400="Curitiba",22.64,IF(B400="Dois Vizinhos",22.64,IF(B400="Francisco Beltrão",21.33,IF(B400="Guarapuava",22.64,IF(B400="Irati",22.64,IF(B400="Ivaiporã",19.95,IF(B400="Laranjeiras do Sul",22.64,IF(B400="Londrina",22.64,IF(B400="Maringá",22.64,IF(B400="Paranaguá",20.63,IF(B400="Paranavaí",22.64,IF(B400="Pato Branco",22,IF(B400="Ponta Grossa",22.64,IF(B400="Santo Antônio da Platina",21.58,IF(B400="Toledo",22.64,IF(B400="Umuarama",22.64,IF(B400="União da Vitória",22.64,0))))))))))))))))))))))) -> 22.64

Sheet Respostas ao formulário 1
A1: n° | B1: Carimbo de data/hora | C1: Endereço de e-mail | D1: Status | E1: Diretoria | F1: Departamento | G1: Informe a Assessoria/Regional/Polo/Estação Responsável | H1: N° SAF | I1: Informar título da Capacitação | J1: Metodologia da Capacitação | K1: N° de participantes do IDR-Paraná | L1: Informar nome dos participantes (se houver) | M1: Instituição parceira | N1: N° participantes externos | O1: Informe o Estado onde ocorrerá a capacitação | P1: Informar município onde ocorrerá a capacitação | Q1: Data de Início | R1: Data de Término | S1: A data informada é definitiva? | T1: Modalidade | U1: Temática Básica | V1: Justificativa | W1: Informar quantidade de refeição (n°) | X1: Informar quantidade de pernoite (n°) | Y1: Taxa de Inscrição (R$) | Z1: Material Gráfico (R$) | AA1: Passagem aérea (R$) | AB1: Passagem terrestre/ônibus | AC1: Táxi (R$) | AD1: Pedágio (R$) | AE1: Van (R$) | AF1: Coffee Break | AG1: Total KM (Veículo oficial) | AH1: Integração | AI1: Valor Coffee break (R$) | AJ1: Valor Total Combustível (R$) | AK1: Valor Total Diárias (R$) | AL1: Valor Total IDR-Paraná (R$) | AM1: Parecer do Departamento | AN1: Parecer da Diretoria
A2: =ROW(A2)-1 -> 1 | B2: 45999.677 | C2: tpellini@idr.pr.gov.br | D2: A aprovar | E2: =VLOOKUP(G2,DiretoriaDepart.Coord.!$A$1:$C$72,2,FALSE) -> Pesquisa e Inovação | F2: =VLOOKUP(G2,DiretoriaDepart.Coord.!$A$1:$C$72,3,FALSE) -> Pesquisa e Capacitação | G2: Socioeconomia e Métodos Quantitativos (Pesquisa) | I2: XVI Encontro Nacional da Sociedade Brasileira de Economia Ecológica (ECOECO) | J2: Encontro | K2: 1 | L2: Tiago Santos Telles | M2: Sociedade Brasileira de Economia Ecológica – ECOECO. | N2: 150 | O2: Alagoas | P2: Maceió | Q2: 45998.333 | R2: 46003.75 | S2: Não | T2: Presencial | U2: Economia ecológica. | V2: A participação é essencial para aprofundar conhecimentos e fortalecer pesquisas voltadas à integração entre economia e ecologia, áreas estratégicas para o desenvolvimento sustentável da agropecuária. O evento possibilita atualização científica sobre abordagens inovadoras em economia ecológica, análise de serviços ecossistêmicos e políticas públicas ambientais, além de promover a troca de experiências com pesquisadores nacionais e internacionais. Essa interação contribui para aprimorar metodologias aplicadas em estudos sobre sustentabilidade, uso eficiente de recursos naturais e impactos socioeconômicos, alinhando-se às metas institucionais de geração de conhecimento e suporte à tomada de decisão para sistemas produtivos mais resilientes. | W2: 12 | X2: 6 | Y2: 350 | Z2: 0 | AA2: 1650 | AB2: 0 | AC2: 300 | AD2: 0 | AE2: 0 | AF2: Não | AG2: 0 | AH2: Não | AI2: =IF(AF2="Sim",INT((R2-Q2+1))*K2*VLOOKUP(P2,'Tabelas Auxiliares'!$A$1:$C$400,3,FALSE),0) -> 0 | AJ2: =(AG2/10)*7 -> 0 | AK2: =IFS( O2="Acre",((W2*0.15)+(X2*0.7))*VLOOKUP(P2,'MunicípiosEstados'!$A$2:$B$23,2,FALSE), O2="Alagoas",((W2*0.15)+(X2*0.7))*VLOOKUP(P2,'MunicípiosEstados'!$C$2:$D$103,2,FALSE), O2="Amapá",((W2*0.15)+(X2*0.7))*VLOOKUP(P2,'MunicípiosEstados'!$E$2:$F$17,2,FALSE), O2="Amazonas",((W2*0.15)+(X2*0.7))*VLOOKUP(P2,'MunicípiosEstados'!$G$2:$H$63,2,FALSE), O2="Bahia",((W2*0.15)+(X2*0.7))*VLOOKUP(P2,'MunicípiosEstados'!$I$2:$J$418,2,FALSE), O2="Ceará",((W2*0.15)+(X2*0.7))*VLOOKUP(P2,'MunicípiosEstados'!$K$2:$L$185,2,FALSE), O2="Distrito Federal",((W2*0.15)+(X2*0.7))*VLOOKUP(P2,'MunicípiosEstados'!$M$2:$N$2,2,FALSE), O2="Espírito Santo",((W2*0.15)+(X2*0.7))*VLOOKUP(P2,'MunicípiosEstados'!$O$2:$P$79,2,FALSE), O2="Goiás",((W2*0.15)+(X2*0.7))*VLOOKUP(P2,'MunicípiosEstados'!$Q$2:$R$247,2,FALSE), O2="Maranhão",((W2*0.15)+(X2*0.7))*VLOOKUP(P2,'MunicípiosEstados'!$S$2:$T$218,2,FALSE), O2="Mato Grosso",((W2*0.15)+(X2*0.7))*VLOOKUP(P2,'MunicípiosEstados'!$U$2:$V$143,2,FALSE), O2="Mato Grosso do Sul",((W2*0.15)+(X2*0.7))*VLOOKUP(P2,'MunicípiosEstados'!$W$2:$X$80,2,FALSE), O2="Minas Gerais",((W2*0.15)+(X2*0.7))*VLOOKUP(P2,'MunicípiosEstados'!$Y$2:$Z$854,2,FALSE), O2="Pará",((W2*0.15)+(X2*0.7))*VLOOKUP(P2,'MunicípiosEstados'!$AA$2:$AB$145,2,FALSE), O2="Paraíba",((W2*0.15)+(X2*0.7))*VLOOKUP(P2,'MunicípiosEstados'!$AC$2:$AD$224,2,FALSE), O2="Paraná",((W2*0.15)+(X2*0.7))*VLOOKUP(P2,'MunicípiosEstados'!$AE$2:$AF$400,2,FALSE), O2="Pernambuco",((W2*0.15)+(X2*0.7))*VLOOKUP(P2,'MunicípiosEstados'!$AG$2:$AH$186,2,FALSE), O2="Piauí",((W2*0.15)+(X2*0.7))*VLOOKUP(P2,'MunicípiosEstados'!$AI$2:$AJ$225,2,FALSE), O2="Rio Grande do Norte",((W2*0.15)+(X2*0.7))*VLOOKUP(P2,'MunicípiosEstados'!$AK$2:$AL$168,2,FALSE), O2="Rio Grande do Sul",((W2*0.15)+(X2*0.7))*VLOOKUP(P2,'MunicípiosEstados'!$AM$2:$AN$498,2,FALSE), O2="Rio de Janeiro",((W2*0.15)+(X2*0.7))*VLOOKUP(P2,'MunicípiosEstados'!$AO$2:$AP$93,2,FALSE), O2="Rondônia",((W2*0.15)+(X2*0.7))*VLOOKUP(P2,'MunicípiosEstados'!$AQ$2:$AR$53,2,FALSE), O2="Roraima",((W2*0.15)+(X2*0.7))*VLOOKUP(P2,'MunicípiosEstados'!$AS$2:$AT$16,2,FALSE), O2="Santa Catarina",((W2*0.15)+(X2*0.7))*VLOOKUP(P2,'MunicípiosEstados'!$AU$2:$AV$296,2,FALSE), O2="São Paulo",((W2*0.15)+(X2*0.7))*VLOOKUP(P2,'MunicípiosEstados'!$AW$2:$AX$646,2,FALSE), O2="Sergipe",((W2*0.15)+(X2*0.7))*VLOOKUP(P2,'MunicípiosEstados'!$AY$2:$AZ$76,2,FALSE), O2="Tocantins",((W2*0.15)+(X2*0.7))*VLOOKUP(P2,'MunicípiosEstados'!$BA$2:$BB$140,2,FALSE), O2="Exterior",((W2*0.15)+(X2*0.7))*VLOOKUP(P2,'MunicípiosEstados'!$BC$2:$BE$221,3,FALSE),TRUE,0 ) -> 2227.56 | AL2: =AK2+AJ2+AI2+AE2+AD2+AC2+AB2+AA2+Z2+Y2 -> 4527.56
A3: =ROW(A3)-1 -> 2 | B3: 45993.395 | C3: graziela_barbosa@idr.pr.gov.br | D3: Aprovado | E3: =VLOOKUP(G3,DiretoriaDepart.Coord.!$A$1:$C$72,2,FALSE) -> Pesquisa e Inovação | F3: =VLOOKUP(G3,DiretoriaDepart.Coord.!$A$1:$C$72,3,FALSE) -> Inovação e Comunicação Científica | G3: Solos e Meio Ambiente (Pesquisa) | I3: IV Simpósio Brasileiro de Solos Arenosos | J3: Simpósio | K3: 1 | L3: Jonez Fidalski | M3: Não se aplica | N3: 1 | O3: Bahia | P3: Luís Eduardo Magalhães | Q3: 45901.333 | R3: 45903.708 | S3: Sim | T3: Presencial | U3: Sistemas de produção resilientes em solos leves | V3: 01) Atualizações de manejo do solos e da água em solos arenosos no Brasil, participar da Comissão Organizadora; 2) submeter um resumo. | W3: 10 | X3: 5 | Y3: 1000 | Z3: 250 | AA3: 4500 | AB3: 0 | AC3: 500 | AD3: 0 | AE3: 0 | AF3: Não | AG3: 0 | AH3: Não | AI3: =IF(AF3="Sim",INT((R3-Q3+1))*K3*VLOOKUP(P3,'Tabelas Auxiliares'!$A$1:$C$400,3,FALSE),0) -> 0 | AJ3: =(AG3/10)*7 -> 0 | AK3: =IFS( O3="Acre",((W3*0.15)+(X3*0.7))*VLOOKUP(P3,'MunicípiosEstados'!$A$2:$B$23,2,FALSE), O3="Alagoas",((W3*0.15)+(X3*0.7))*VLOOKUP(P3,'MunicípiosEstados'!$C$2:$D$103,2,FALSE), O3="Amapá",((W3*0.15)+(X3*0.7))*VLOOKUP(P3,'MunicípiosEstados'!$E$2:$F$17,2,FALSE), O3="Amazonas",((W3*0.15)+(X3*0.7))*VLOOKUP(P3,'MunicípiosEstados'!$G$2:$H$63,2,FALSE), O3="Bahia",((W3*0.15)+(X3*0.7))*VLOOKUP(P3,'MunicípiosEstados'!$I$2:$J$418,2,FALSE), O3="Ceará",((W3*0.15)+(X3*0.7))*VLOOKUP(P3,'MunicípiosEstados'!$K$2:$L$185,2,FALSE), O3="Distrito Federal",((W3*0.15)+(X3*0.7))*VLOOKUP(P3,'MunicípiosEstados'!$M$2:$N$2,2,FALSE), O3="Espírito Santo",((W3*0.15)+(X3*0.7))*VLOOKUP(P3,'MunicípiosEstados'!$O$2:$P$79,2,FALSE), O3="Goiás",((W3*0.15)+(X3*0.7))*VLOOKUP(P3,'MunicípiosEstados'!$Q$2:$R$247,2,FALSE), O3="Maranhão",((W3*0.15)+(X3*0.7))*VLOOKUP(P3,'MunicípiosEstados'!$S$2:$T$218,2,FALSE), O3="Mato Grosso",((W3*0.15)+(X3*0.7))*VLOOKUP(P3,'MunicípiosEstados'!$U$2:$V$143,2,FALSE), O3="Mato Grosso do Sul",((W3*0.15)+(X3*0.7))*VLOOKUP(P3,'MunicípiosEstados'!$W$2:$X$80,2,FALSE), O3="Minas Gerais",((W3*0.15)+(X3*0.7))*VLOOKUP(P3,'MunicípiosEstados'!$Y$2:$Z$854,2,FALSE), O3="Pará",((W3*0.15)+(X3*0.7))*VLOOKUP(P3,'MunicípiosEstados'!$AA$2:$AB$145,2,FALSE), O3="Paraíba",((W3*0.15)+(X3*0.7))*VLOOKUP(P3,'MunicípiosEstados'!$AC$2:$AD$224,2,FALSE), O3="Paraná",((W3*0.15)+(X3*0.7))*VLOOKUP(P3,'MunicípiosEstados'!$AE$2:$AF$400,2,FALSE), O3="Pernambuco",((W3*0.15)+(X3*0.7))*VLOOKUP(P3,'MunicípiosEstados'!$AG$2:$AH$186,2,FALSE), O3="Piauí",((W3*0.15)+(X3*0.7))*VLOOKUP(P3,'MunicípiosEstados'!$AI$2:$AJ$225,2,FALSE), O3="Rio Grande do Norte",((W3*0.15)+(X3*0.7))*VLOOKUP(P3,'MunicípiosEstados'!$AK$2:$AL$168,2,FALSE), O3="Rio Grande do Sul",((W3*0.15)+(X3*0.7))*VLOOKUP(P3,'MunicípiosEstados'!$AM$2:$AN$498,2,FALSE), O3="Rio de Janeiro",((W3*0.15)+(X3*0.7))*VLOOKUP(P3,'MunicípiosEstados'!$AO$2:$AP$93,2,FALSE), O3="Rondônia",((W3*0.15)+(X3*0.7))*VLOOKUP(P3,'MunicípiosEstados'!$AQ$2:$AR$53,2,FALSE), O3="Roraima",((W3*0.15)+(X3*0.7))*VLOOKUP(P3,'MunicípiosEstados'!$AS$2:$AT$16,2,FALSE), O3="Santa Catarina",((W3*0.15)+(X3*0.7))*VLOOKUP(P3,'MunicípiosEstados'!$AU$2:$AV$296,2,FALSE), O3="São Paulo",((W3*0.15)+(X3*0.7))*VLOOKUP(P3,'MunicípiosEstados'!$AW$2:$AX$646,2,FALSE), O3="Sergipe",((W3*0.15)+(X3*0.7))*VLOOKUP(P3,'MunicípiosEstados'!$AY$2:$AZ$76,2,FALSE), O3="Tocantins",((W3*0.15)+(X3*0.7))*VLOOKUP(P3,'MunicípiosEstados'!$BA$2:$BB$140,2,FALSE), O3="Exterior",((W3*0.15)+(X3*0.7))*VLOOKUP(P3,'MunicípiosEstados'!$BC$2:$BE$221,3,FALSE),TRUE,0 ) -> 1452.75 | AL3: =AK3+AJ3+AI3+AE3+AD3+AC3+AB3+AA3+Z3+Y3 -> 7702.75 | AN3: Aprovado para Jonez Fidalski
A4: =ROW(A4)-1 -> 3 | B4: 45979.577 | C4: santosjb@idr.pr.gov.br | D4: A aprovar | E4: =VLOOKUP(G4,DiretoriaDepart.Coord.!$A$1:$C$72,2,FALSE) -> Pesquisa e Inovação | F4: =VLOOKUP(G4,DiretoriaDepart.Coord.!$A$1:$C$72,3,FALSE) -> Inovação e Comunicação Científica | G4: Solos e Meio Ambiente (Pesquisa) | I4: 20° Encontro Nacional do Sistema Plantio Direto e 3° Encontro Mundial do Sistema Plantio Direto | J4: Encontro | K4: 1 | L4: Josiane Burkner dos Santos | M4: FEBRAPDP | N4: 0 | O4: Distrito Federal | P4: Brasília | Q4: 45845.333 | R4: 45847.708 | S4: Sim | T4: Presencial | U4: Sistema Plantio Direto | V4: Manter a visibilidade do IDR-Paraná como instituição que conduziu e conduz o Paraná como o estado com maior produtividade e sustentabilidade exatamente por essa instituição ter escolhido desde os anos 80 o fomento da prática do SPD, é muito importante para continuarmos sendo reconhecidos como uma empresa que gera pesquisa de qualidade para o mundo. | W4: 10 | X4: 4 | Y4: 800 | Z4: 350 | AA4: 4500 | AB4: 500 | AC4: 1000 | AD4: 0 | AE4: 500 | AF4: Não | AG4: 500 | AH4: Sim | AI4: =IF(AF4="Sim",INT((R4-Q4+1))*K4*VLOOKUP(P4,'Tabelas Auxiliares'!$A$1:$C$400,3,FALSE),0) -> 0 | AJ4: =(AG4/10)*7 -> 350 | AK4: =IFS( O4="Acre",((W4*0.15)+(X4*0.7))*VLOOKUP(P4,'MunicípiosEstados'!$A$2:$B$23,2,FALSE), O4="Alagoas",((W4*0.15)+(X4*0.7))*VLOOKUP(P4,'MunicípiosEstados'!$C$2:$D$103,2,FALSE), O4="Amapá",((W4*0.15)+(X4*0.7))*VLOOKUP(P4,'MunicípiosEstados'!$E$2:$F$17,2,FALSE), O4="Amazonas",((W4*0.15)+(X4*0.7))*VLOOKUP(P4,'MunicípiosEstados'!$G$2:$H$63,2,FALSE), O4="Bahia",((W4*0.15)+(X4*0.7))*VLOOKUP(P4,'MunicípiosEstados'!$I$2:$J$418,2,FALSE), O4="Ceará",((W4*0.15)+(X4*0.7))*VLOOKUP(P4,'MunicípiosEstados'!$K$2:$L$185,2,FALSE), O4="Distrito Federal",((W4*0.15)+(X4*0.7))*VLOOKUP(P4,'MunicípiosEstados'!$M$2:$N$2,2,FALSE), O4="Espírito Santo",((W4*0.15)+(X4*0.7))*VLOOKUP(P4,'MunicípiosEstados'!$O$2:$P$79,2,FALSE), O4="Goiás",((W4*0.15)+(X4*0.7))*VLOOKUP(P4,'MunicípiosEstados'!$Q$2:$R$247,2,FALSE), O4="Maranhão",((W4*0.15)+(X4*0.7))*VLOOKUP(P4,'MunicípiosEstados'!$S$2:$T$218,2,FALSE), O4="Mato Grosso",((W4*0.15)+(X4*0.7))*VLOOKUP(P4,'MunicípiosEstados'!$U$2:$V$143,2,FALSE), O4="Mato Grosso do Sul",((W4*0.15)+(X4*0.7))*VLOOKUP(P4,'MunicípiosEstados'!$W$2:$X$80,2,FALSE), O4="Minas Gerais",((W4*0.15)+(X4*0.7))*VLOOKUP(P4,'MunicípiosEstados'!$Y$2:$Z$854,2,FALSE), O4="Pará",((W4*0.15)+(X4*0.7))*VLOOKUP(P4,'MunicípiosEstados'!$AA$2:$AB$145,2,FALSE), O4="Paraíba",((W4*0.15)+(X4*0.7))*VLOOKUP(P4,'MunicípiosEstados'!$AC$2:$AD$224,2,FALSE), O4="Paraná",((W4*0.15)+(X4*0.7))*VLOOKUP(P4,'MunicípiosEstados'!$AE$2:$AF$400,2,FALSE), O4="Pernambuco",((W4*0.15)+(X4*0.7))*VLOOKUP(P4,'MunicípiosEstados'!$AG$2:$AH$186,2,FALSE), O4="Piauí",((W4*0.15)+(X4*0.7))*VLOOKUP(P4,'MunicípiosEstados'!$AI$2:$AJ$225,2,FALSE), O4="Rio Grande do Norte",((W4*0.15)+(X4*0.7))*VLOOKUP(P4,'MunicípiosEstados'!$AK$2:$AL$168,2,FALSE), O4="Rio Grande do Sul",((W4*0.15)+(X4*0.7))*VLOOKUP(P4,'MunicípiosEstados'!$AM$2:$AN$498,2,FALSE), O4="Rio de Janeiro",((W4*0.15)+(X4*0.7))*VLOOKUP(P4,'MunicípiosEstados'!$AO$2:$AP$93,2,FALSE), O4="Rondônia",((W4*0.15)+(X4*0.7))*VLOOKUP(P4,'MunicípiosEstados'!$AQ$2:$AR$53,2,FALSE), O4="Roraima",((W4*0.15)+(X4*0.7))*VLOOKUP(P4,'MunicípiosEstados'!$AS$2:$AT$16,2,FALSE), O4="Santa Catarina",((W4*0.15)+(X4*0.7))*VLOOKUP(P4,'MunicípiosEstados'!$AU$2:$AV$296,2,FALSE), O4="São Paulo",((W4*0.15)+(X4*0.7))*VLOOKUP(P4,'MunicípiosEstados'!$AW$2:$AX$646,2,FALSE), O4="Sergipe",((W4*0.15)+(X4*0.7))*VLOOKUP(P4,'MunicípiosEstados'!$AY$2:$AZ$76,2,FALSE), O4="Tocantins",((W4*0.15)+(X4*0.7))*VLOOKUP(P4,'MunicípiosEstados'!$BA$2:$BB$140,2,FALSE), O4="Exterior",((W4*0.15)+(X4*0.7))*VLOOKUP(P4,'MunicípiosEstados'!$BC$2:$BE$221,3,FALSE),TRUE,0 ) -> 2012.916 | AL4: =AK4+AJ4+AI4+AE4+AD4+AC4+AB4+AA4+Z4+Y4 -> 10012.916
A5: =ROW(A5)-1 -> 4 | B5: 45987.657 | C5: ronaldo@iapar.br | D5: Aprovado | E5: =VLOOKUP(G5,DiretoriaDepart.Coord.!$A$1:$C$72,2,FALSE) -> Pesquisa e Inovação | F5: =VLOOKUP(G5,DiretoriaDepart.Coord.!$A$1:$C$72,3,FALSE) -> Inovação e Comunicação Científica | G5: Fitotecnia e Fisiologia da Produção (Pesquisa) | I5: Capacitação em sistema Plantio Direto | J5: Encontro | K5: 3 | L5: Ronaldo Hissayuki Hojo Luiz Antonio Odenath Penha Ivan Bordin | M5: FEBRAPDP | N5: 300 | O5: Distrito Federal | P5: Brasília | Q5: 45845.333 | R5: 45847.708 | S5: Sim | T5: Presencial | U5: Produção Sustentavel | V5: Particpipação em evento com afinidade aos projetos de pesquisa em execução. | W5: 5 | X5: 5 | Y5: 500 | Z5: 1100 | AA5: 4000 | AB5: 0 | AC5: 300 | AD5: 0 | AE5: 0 | AF5: Não | AG5: 0 | AH5: Não | AI5: =IF(AF5="Sim",INT((R5-Q5+1))*K5*VLOOKUP(P5,'Tabelas Auxiliares'!$A$1:$C$400,3,FALSE),0) -> 0 | AJ5: =(AG5/10)*7 -> 0 | AK5: =IFS( O5="Acre",((W5*0.15)+(X5*0.7))*VLOOKUP(P5,'MunicípiosEstados'!$A$2:$B$23,2,FALSE), O5="Alagoas",((W5*0.15)+(X5*0.7))*VLOOKUP(P5,'MunicípiosEstados'!$C$2:$D$103,2,FALSE), O5="Amapá",((W5*0.15)+(X5*0.7))*VLOOKUP(P5,'MunicípiosEstados'!$E$2:$F$17,2,FALSE), O5="Amazonas",((W5*0.15)+(X5*0.7))*VLOOKUP(P5,'MunicípiosEstados'!$G$2:$H$63,2,FALSE), O5="Bahia",((W5*0.15)+(X5*0.7))*VLOOKUP(P5,'MunicípiosEstados'!$I$2:$J$418,2,FALSE), O5="Ceará",((W5*0.15)+(X5*0.7))*VLOOKUP(P5,'MunicípiosEstados'!$K$2:$L$185,2,FALSE), O5="Distrito Federal",((W5*0.15)+(X5*0.7))*VLOOKUP(P5,'MunicípiosEstados'!$M$2:$N$2,2,FALSE), O5="Espírito Santo",((W5*0.15)+(X5*0.7))*VLOOKUP(P5,'MunicípiosEstados'!$O$2:$P$79,2,FALSE), O5="Goiás",((W5*0.15)+(X5*0.7))*VLOOKUP(P5,'MunicípiosEstados'!$Q$2:$R$247,2,FALSE), O5="Maranhão",((W5*0.15)+(X5*0.7))*VLOOKUP(P5,'MunicípiosEstados'!$S$2:$T$218,2,FALSE), O5="Mato Grosso",((W5*0.15)+(X5*0.7))*VLOOKUP(P5,'MunicípiosEstados'!$U$2:$V$143,2,FALSE), O5="Mato Grosso do Sul",((W5*0.15)+(X5*0.7))*VLOOKUP(P5,'MunicípiosEstados'!$W$2:$X$80,2,FALSE), O5="Minas Gerais",((W5*0.15)+(X5*0.7))*VLOOKUP(P5,'MunicípiosEstados'!$Y$2:$Z$854,2,FALSE), O5="Pará",((W5*0.15)+(X5*0.7))*VLOOKUP(P5,'MunicípiosEstados'!$AA$2:$AB$145,2,FALSE), O5="Paraíba",((W5*0.15)+(X5*0.7))*VLOOKUP(P5,'MunicípiosEstados'!$AC$2:$AD$224,2,FALSE), O5="Paraná",((W5*0.15)+(X5*0.7))*VLOOKUP(P5,'MunicípiosEstados'!$AE$2:$AF$400,2,FALSE), O5="Pernambuco",((W5*0.15)+(X5*0.7))*VLOOKUP(P5,'MunicípiosEstados'!$AG$2:$AH$186,2,FALSE), O5="Piauí",((W5*0.15)+(X5*0.7))*VLOOKUP(P5,'MunicípiosEstados'!$AI$2:$AJ$225,2,FALSE), O5="Rio Grande do Norte",((W5*0.15)+(X5*0.7))*VLOOKUP(P5,'MunicípiosEstados'!$AK$2:$AL$168,2,FALSE), O5="Rio Grande do Sul",((W5*0.15)+(X5*0.7))*VLOOKUP(P5,'MunicípiosEstados'!$AM$2:$AN$498,2,FALSE), O5="Rio de Janeiro",((W5*0.15)+(X5*0.7))*VLOOKUP(P5,'MunicípiosEstados'!$AO$2:$AP$93,2,FALSE), O5="Rondônia",((W5*0.15)+(X5*0.7))*VLOOKUP(P5,'MunicípiosEstados'!$AQ$2:$AR$53,2,FALSE), O5="Roraima",((W5*0.15)+(X5*0.7))*VLOOKUP(P5,'MunicípiosEstados'!$AS$2:$AT$16,2,FALSE), O5="Santa Catarina",((W5*0.15)+(X5*0.7))*VLOOKUP(P5,'MunicípiosEstados'!$AU$2:$AV$296,2,FALSE), O5="São Paulo",((W5*0.15)+(X5*0.7))*VLOOKUP(P5,'MunicípiosEstados'!$AW$2:$AX$646,2,FALSE), O5="Sergipe",((W5*0.15)+(X5*0.7))*VLOOKUP(P5,'MunicípiosEstados'!$AY$2:$AZ$76,2,FALSE), O5="Tocantins",((W5*0.15)+(X5*0.7))*VLOOKUP(P5,'MunicípiosEstados'!$BA$2:$BB$140,2,FALSE), O5="Exterior",((W5*0.15)+(X5*0.7))*VLOOKUP(P5,'MunicípiosEstados'!$BC$2:$BE$221,3,FALSE),TRUE,0 ) -> 1989.51 | AL5: =AK5+AJ5+AI5+AE5+AD5+AC5+AB5+AA5+Z5+Y5 -> 7889.51 | AN5: Aprovado para dois participantes: Ronaldo Hojo e Ivan Bordin
A6: =ROW(A6)-1 -> 5 | B6: 45993.389 | C6: graziela_barbosa@idr.pr.gov.br | D6: Aprovado | E6: =VLOOKUP(G6,DiretoriaDepart.Coord.!$A$1:$C$72,2,FALSE) -> Pesquisa e Inovação | F6: =VLOOKUP(G6,DiretoriaDepart.Coord.!$A$1:$C$72,3,FALSE) -> Inovação e Comunicação Científica | G6: Solos e Meio Ambiente (Pesquisa) | I6: 20° Encontro Nacional do Sistema Plantio Direto e 3° Encontro Mundial do Sistema Plantio Direto | J6: Encontro | K6: 2 | L6: Graziela Moraes de Cesare Barbosa e Josiane Burkner dos Santos | M6: FEBRAPDP | N6: 0 | O6: Distrito Federal | P6: Brasília | Q6: 45845.333 | R6: 45847.708 | S6: Sim | T6: Presencial | U6: Discussões sobre plantio direto na palha | V6: Manter a visibilidade do IDR-Paraná como instituição que conduziu e conduz o Paraná como o estado com maior produtividade e sustentabilidade exatamente por essa instituição ter escolhido desde os anos 80 o fomento da prática do SPD, é muito importante para continuarmos sendo reconhecidos como uma empresa que gera pesquisa de qualidade para o mundo. | W6: 18 | X6: 8 | Y6: 1600 | Z6: 500 | AA6: 7500 | AB6: 0 | AC6: 2000 | AD6: 0 | AE6: 0 | AF6: Não | AG6: 0 | AH6: Não | AI6: =IF(AF6="Sim",INT((R6-Q6+1))*K6*VLOOKUP(P6,'Tabelas Auxiliares'!$A$1:$C$400,3,FALSE),0) -> 0 | AJ6: =(AG6/10)*7 -> 0 | AK6: =IFS( O6="Acre",((W6*0.15)+(X6*0.7))*VLOOKUP(P6,'MunicípiosEstados'!$A$2:$B$23,2,FALSE), O6="Alagoas",((W6*0.15)+(X6*0.7))*VLOOKUP(P6,'MunicípiosEstados'!$C$2:$D$103,2,FALSE), O6="Amapá",((W6*0.15)+(X6*0.7))*VLOOKUP(P6,'MunicípiosEstados'!$E$2:$F$17,2,FALSE), O6="Amazonas",((W6*0.15)+(X6*0.7))*VLOOKUP(P6,'MunicípiosEstados'!$G$2:$H$63,2,FALSE), O6="Bahia",((W6*0.15)+(X6*0.7))*VLOOKUP(P6,'MunicípiosEstados'!$I$2:$J$418,2,FALSE), O6="Ceará",((W6*0.15)+(X6*0.7))*VLOOKUP(P6,'MunicípiosEstados'!$K$2:$L$185,2,FALSE), O6="Distrito Federal",((W6*0.15)+(X6*0.7))*VLOOKUP(P6,'MunicípiosEstados'!$M$2:$N$2,2,FALSE), O6="Espírito Santo",((W6*0.15)+(X6*0.7))*VLOOKUP(P6,'MunicípiosEstados'!$O$2:$P$79,2,FALSE), O6="Goiás",((W6*0.15)+(X6*0.7))*VLOOKUP(P6,'MunicípiosEstados'!$Q$2:$R$247,2,FALSE), O6="Maranhão",((W6*0.15)+(X6*0.7))*VLOOKUP(P6,'MunicípiosEstados'!$S$2:$T$218,2,FALSE), O6="Mato Grosso",((W6*0.15)+(X6*0.7))*VLOOKUP(P6,'MunicípiosEstados'!$U$2:$V$143,2,FALSE), O6="Mato Grosso do Sul",((W6*0.15)+(X6*0.7))*VLOOKUP(P6,'MunicípiosEstados'!$W$2:$X$80,2,FALSE), O6="Minas Gerais",((W6*0.15)+(X6*0.7))*VLOOKUP(P6,'MunicípiosEstados'!$Y$2:$Z$854,2,FALSE), O6="Pará",((W6*0.15)+(X6*0.7))*VLOOKUP(P6,'MunicípiosEstados'!$AA$2:$AB$145,2,FALSE), O6="Paraíba",((W6*0.15)+(X6*0.7))*VLOOKUP(P6,'MunicípiosEstados'!$AC$2:$AD$224,2,FALSE), O6="Paraná",((W6*0.15)+(X6*0.7))*VLOOKUP(P6,'MunicípiosEstados'!$AE$2:$AF$400,2,FALSE), O6="Pernambuco",((W6*0.15)+(X6*0.7))*VLOOKUP(P6,'MunicípiosEstados'!$AG$2:$AH$186,2,FALSE), O6="Piauí",((W6*0.15)+(X6*0.7))*VLOOKUP(P6,'MunicípiosEstados'!$AI$2:$AJ$225,2,FALSE), O6="Rio Grande do Norte",((W6*0.15)+(X6*0.7))*VLOOKUP(P6,'MunicípiosEstados'!$AK$2:$AL$168,2,FALSE), O6="Rio Grande do Sul",((W6*0.15)+(X6*0.7))*VLOOKUP(P6,'MunicípiosEstados'!$AM$2:$AN$498,2,FALSE), O6="Rio de Janeiro",((W6*0.15)+(X6*0.7))*VLOOKUP(P6,'MunicípiosEstados'!$AO$2:$AP$93,2,FALSE), O6="Rondônia",((W6*0.15)+(X6*0.7))*VLOOKUP(P6,'MunicípiosEstados'!$AQ$2:$AR$53,2,FALSE), O6="Roraima",((W6*0.15)+(X6*0.7))*VLOOKUP(P6,'MunicípiosEstados'!$AS$2:$AT$16,2,FALSE), O6="Santa Catarina",((W6*0.15)+(X6*0.7))*VLOOKUP(P6,'MunicípiosEstados'!$AU$2:$AV$296,2,FALSE), O6="São Paulo",((W6*0.15)+(X6*0.7))*VLOOKUP(P6,'MunicípiosEstados'!$AW$2:$AX$646,2,FALSE), O6="Sergipe",((W6*0.15)+(X6*0.7))*VLOOKUP(P6,'MunicípiosEstados'!$AY$2:$AZ$76,2,FALSE), O6="Tocantins",((W6*0.15)+(X6*0.7))*VLOOKUP(P6,'MunicípiosEstados'!$BA$2:$BB$140,2,FALSE), O6="Exterior",((W6*0.15)+(X6*0.7))*VLOOKUP(P6,'MunicípiosEstados'!$BC$2:$BE$221,3,FALSE),TRUE,0 ) -> 3885.396 | AL6: =AK6+AJ6+AI6+AE6+AD6+AC6+AB6+AA6+Z6+Y6 -> 15485.396 | AN6: Aprovado para Graziela Barbosa e Josiane Burkner
A7: =ROW(A7)-1 -> 6 | B7: 45995.431 | C7: joaoreis@idr.pr.gov.br | D7: A aprovar | E7: =VLOOKUP(G7,DiretoriaDepart.Coord.!$A$1:$C$72,2,FALSE) -> Extensão Rural | F7: =VLOOKUP(G7,DiretoriaDepart.Coord.!$A$1:$C$72,3,FALSE) -> Projetos e Cadeias Produtivas | G7: Olericultura (Extensão Rural) | I7: 58º Congresso Brasileiro de Olericultura | J7: Congresso | K7: 10 | M7: ABH | N7: 500 | O7: Distrito Federal | P7: Brasília | Q7: 45859.333 | R7: 45862.708 | S7: Sim | T7: Presencial | U7: Desafios da Agricultura Familiar frente às Mudanças Climáticas | V7: As mudanças climáticas tem provocado grande impacto na produção de hortaliças no Brasil e principalmente no Paraná, dessa forma, participar desse debate permitirá aos nossos profissionais definir estratégia para conviver com essas mudanças permitindo manter a produção e produtividade das hortaliças. | W7: 110 | X7: 50 | Y7: 15000 | Z7: 0 | AA7: 30000 | AB7: 0 | AC7: 2000 | AD7: 0 | AE7: 0 | AF7: Não | AG7: 5000 | AH7: Não | AI7: =IF(AF7="Sim",INT((R7-Q7+1))*K7*VLOOKUP(P7,'Tabelas Auxiliares'!$A$1:$C$400,3,FALSE),0) -> 0 | AJ7: =(AG7/10)*7 -> 3500 | AK7: =IFS( O7="Acre",((W7*0.15)+(X7*0.7))*VLOOKUP(P7,'MunicípiosEstados'!$A$2:$B$23,2,FALSE), O7="Alagoas",((W7*0.15)+(X7*0.7))*VLOOKUP(P7,'MunicípiosEstados'!$C$2:$D$103,2,FALSE), O7="Amapá",((W7*0.15)+(X7*0.7))*VLOOKUP(P7,'MunicípiosEstados'!$E$2:$F$17,2,FALSE), O7="Amazonas",((W7*0.15)+(X7*0.7))*VLOOKUP(P7,'MunicípiosEstados'!$G$2:$H$63,2,FALSE), O7="Bahia",((W7*0.15)+(X7*0.7))*VLOOKUP(P7,'MunicípiosEstados'!$I$2:$J$418,2,FALSE), O7="Ceará",((W7*0.15)+(X7*0.7))*VLOOKUP(P7,'MunicípiosEstados'!$K$2:$L$185,2,FALSE), O7="Distrito Federal",((W7*0.15)+(X7*0.7))*VLOOKUP(P7,'MunicípiosEstados'!$M$2:$N$2,2,FALSE), O7="Espírito Santo",((W7*0.15)+(X7*0.7))*VLOOKUP(P7,'MunicípiosEstados'!$O$2:$P$79,2,FALSE), O7="Goiás",((W7*0.15)+(X7*0.7))*VLOOKUP(P7,'MunicípiosEstados'!$Q$2:$R$247,2,FALSE), O7="Maranhão",((W7*0.15)+(X7*0.7))*VLOOKUP(P7,'MunicípiosEstados'!$S$2:$T$218,2,FALSE), O7="Mato Grosso",((W7*0.15)+(X7*0.7))*VLOOKUP(P7,'MunicípiosEstados'!$U$2:$V$143,2,FALSE), O7="Mato Grosso do Sul",((W7*0.15)+(X7*0.7))*VLOOKUP(P7,'MunicípiosEstados'!$W$2:$X$80,2,FALSE), O7="Minas Gerais",((W7*0.15)+(X7*0.7))*VLOOKUP(P7,'MunicípiosEstados'!$Y$2:$Z$854,2,FALSE), O7="Pará",((W7*0.15)+(X7*0.7))*VLOOKUP(P7,'MunicípiosEstados'!$AA$2:$AB$145,2,FALSE), O7="Paraíba",((W7*0.15)+(X7*0.7))*VLOOKUP(P7,'MunicípiosEstados'!$AC$2:$AD$224,2,FALSE), O7="Paraná",((W7*0.15)+(X7*0.7))*VLOOKUP(P7,'MunicípiosEstados'!$AE$2:$AF$400,2,FALSE), O7="Pernambuco",((W7*0.15)+(X7*0.7))*VLOOKUP(P7,'MunicípiosEstados'!$AG$2:$AH$186,2,FALSE), O7="Piauí",((W7*0.15)+(X7*0.7))*VLOOKUP(P7,'MunicípiosEstados'!$AI$2:$AJ$225,2,FALSE), O7="Rio Grande do Norte",((W7*0.15)+(X7*0.7))*VLOOKUP(P7,'MunicípiosEstados'!$AK$2:$AL$168,2,FALSE), O7="Rio Grande do Sul",((W7*0.15)+(X7*0.7))*VLOOKUP(P7,'MunicípiosEstados'!$AM$2:$AN$498,2,FALSE), O7="Rio de Janeiro",((W7*0.15)+(X7*0.7))*VLOOKUP(P7,'MunicípiosEstados'!$AO$2:$AP$93,2,FALSE), O7="Rondônia",((W7*0.15)+(X7*0.7))*VLOOKUP(P7,'MunicípiosEstados'!$AQ$2:$AR$53,2,FALSE), O7="Roraima",((W7*0.15)+(X7*0.7))*VLOOKUP(P7,'MunicípiosEstados'!$AS$2:$AT$16,2,FALSE), O7="Santa Catarina",((W7*0.15)+(X7*0.7))*VLOOKUP(P7,'MunicípiosEstados'!$AU$2:$AV$296,2,FALSE), O7="São Paulo",((W7*0.15)+(X7*0.7))*VLOOKUP(P7,'MunicípiosEstados'!$AW$2:$AX$646,2,FALSE), O7="Sergipe",((W7*0.15)+(X7*0.7))*VLOOKUP(P7,'MunicípiosEstados'!$AY$2:$AZ$76,2,FALSE), O7="Tocantins",((W7*0.15)+(X7*0.7))*VLOOKUP(P7,'MunicípiosEstados'!$BA$2:$BB$140,2,FALSE), O7="Exterior",((W7*0.15)+(X7*0.7))*VLOOKUP(P7,'MunicípiosEstados'!$BC$2:$BE$221,3,FALSE),TRUE,0 ) -> 24108.18 | AL7: =AK7+AJ7+AI7+AE7+AD7+AC7+AB7+AA7+Z7+Y7 -> 74608.18
A8: =ROW(A8)-1 -> 7 | B8: 45996.65 | C8: joiceassmann@idr.pr.gov.br | D8: A aprovar | E8: =VLOOKUP(G8,DiretoriaDepart.Coord.!$A$1:$C$72,2,FALSE) -> Pesquisa e Inovação | F8: =VLOOKUP(G8,DiretoriaDepart.Coord.!$A$1:$C$72,3,FALSE) -> Inovação e Comunicação Científica | G8: Polo de Pesquisa de Pato Branco | I8: 20° Encontro Nacional do Sistema Plantio Direto e 3° Encontro Mundial do Sistema Plantio Direto | J8: Encontro | K8: 5 | L8: Joice Mari Assmann | M8: FEBRAPDP e ENSPD | N8: 1000 | O8: Distrito Federal | P8: Brasília | Q8: 45845.333 | R8: 45847.708 | S8: Sim | T8: Presencial | U8: "Sistema Plantio Direto: base para a Agricultura Regenerativa" | V8: O Paraná consolidou-se como o berço do Plantio Direto, sendo referência mundial nesse sistema de cultivo. O IDR-Paraná, pioneiro e protagonista nos estudos e avanços relacionados aos seus pilares, rotação de culturas, uso de plantas de cobertura e manejo sustentável do solo, desempenhou papel fundamental na construção desse legado. Diante dessa trajetória, é imprescindível que a instituição esteja representada em âmbito nacional e internacional, fortalecendo sua posição de liderança e credibilidade. Participar desses espaços nos permite não apenas aprimorar conhecimentos e incorporar inovações, mas também compartilhar resultados e experiências que contribuem para o desenvolvimento da agricultura sustentável no Brasil e no mundo. | W8: 8 | X8: 4 | Y8: 800 | Z8: 150 | AA8: 3000 | AB8: 400 | AC8: 200 | AD8: 0 | AE8: 0 | AF8: Não | AG8: 0 | AH8: Sim | AI8: =IF(AF8="Sim",INT((R8-Q8+1))*K8*VLOOKUP(P8,'Tabelas Auxiliares'!$A$1:$C$400,3,FALSE),0) -> 0 | AJ8: =(AG8/10)*7 -> 0 | AK8: =IFS( O8="Acre",((W8*0.15)+(X8*0.7))*VLOOKUP(P8,'MunicípiosEstados'!$A$2:$B$23,2,FALSE), O8="Alagoas",((W8*0.15)+(X8*0.7))*VLOOKUP(P8,'MunicípiosEstados'!$C$2:$D$103,2,FALSE), O8="Amapá",((W8*0.15)+(X8*0.7))*VLOOKUP(P8,'MunicípiosEstados'!$E$2:$F$17,2,FALSE), O8="Amazonas",((W8*0.15)+(X8*0.7))*VLOOKUP(P8,'MunicípiosEstados'!$G$2:$H$63,2,FALSE), O8="Bahia",((W8*0.15)+(X8*0.7))*VLOOKUP(P8,'MunicípiosEstados'!$I$2:$J$418,2,FALSE), O8="Ceará",((W8*0.15)+(X8*0.7))*VLOOKUP(P8,'MunicípiosEstados'!$K$2:$L$185,2,FALSE), O8="Distrito Federal",((W8*0.15)+(X8*0.7))*VLOOKUP(P8,'MunicípiosEstados'!$M$2:$N$2,2,FALSE), O8="Espírito Santo",((W8*0.15)+(X8*0.7))*VLOOKUP(P8,'MunicípiosEstados'!$O$2:$P$79,2,FALSE), O8="Goiás",((W8*0.15)+(X8*0.7))*VLOOKUP(P8,'MunicípiosEstados'!$Q$2:$R$247,2,FALSE), O8="Maranhão",((W8*0.15)+(X8*0.7))*VLOOKUP(P8,'MunicípiosEstados'!$S$2:$T$218,2,FALSE), O8="Mato Grosso",((W8*0.15)+(X8*0.7))*VLOOKUP(P8,'MunicípiosEstados'!$U$2:$V$143,2,FALSE), O8="Mato Grosso do Sul",((W8*0.15)+(X8*0.7))*VLOOKUP(P8,'MunicípiosEstados'!$W$2:$X$80,2,FALSE), O8="Minas Gerais",((W8*0.15)+(X8*0.7))*VLOOKUP(P8,'MunicípiosEstados'!$Y$2:$Z$854,2,FALSE), O8="Pará",((W8*0.15)+(X8*0.7))*VLOOKUP(P8,'MunicípiosEstados'!$AA$2:$AB$145,2,FALSE), O8="Paraíba",((W8*0.15)+(X8*0.7))*VLOOKUP(P8,'MunicípiosEstados'!$AC$2:$AD$224,2,FALSE), O8="Paraná",((W8*0.15)+(X8*0.7))*VLOOKUP(P8,'MunicípiosEstados'!$AE$2:$AF$400,2,FALSE), O8="Pernambuco",((W8*0.15)+(X8*0.7))*VLOOKUP(P8,'MunicípiosEstados'!$AG$2:$AH$186,2,FALSE), O8="Piauí",((W8*0.15)+(X8*0.7))*VLOOKUP(P8,'MunicípiosEstados'!$AI$2:$AJ$225,2,FALSE), O8="Rio Grande do Norte",((W8*0.15)+(X8*0.7))*VLOOKUP(P8,'MunicípiosEstados'!$AK$2:$AL$168,2,FALSE), O8="Rio Grande do Sul",((W8*0.15)+(X8*0.7))*VLOOKUP(P8,'MunicípiosEstados'!$AM$2:$AN$498,2,FALSE), O8="Rio de Janeiro",((W8*0.15)+(X8*0.7))*VLOOKUP(P8,'MunicípiosEstados'!$AO$2:$AP$93,2,FALSE), O8="Rondônia",((W8*0.15)+(X8*0.7))*VLOOKUP(P8,'MunicípiosEstados'!$AQ$2:$AR$53,2,FALSE), O8="Roraima",((W8*0.15)+(X8*0.7))*VLOOKUP(P8,'MunicípiosEstados'!$AS$2:$AT$16,2,FALSE), O8="Santa Catarina",((W8*0.15)+(X8*0.7))*VLOOKUP(P8,'MunicípiosEstados'!$AU$2:$AV$296,2,FALSE), O8="São Paulo",((W8*0.15)+(X8*0.7))*VLOOKUP(P8,'MunicípiosEstados'!$AW$2:$AX$646,2,FALSE), O8="Sergipe",((W8*0.15)+(X8*0.7))*VLOOKUP(P8,'MunicípiosEstados'!$AY$2:$AZ$76,2,FALSE), O8="Tocantins",((W8*0.15)+(X8*0.7))*VLOOKUP(P8,'MunicípiosEstados'!$BA$2:$BB$140,2,FALSE), O8="Exterior",((W8*0.15)+(X8*0.7))*VLOOKUP(P8,'MunicípiosEstados'!$BC$2:$BE$221,3,FALSE),TRUE,0 ) -> 1872.48 | AL8: =AK8+AJ8+AI8+AE8+AD8+AC8+AB8+AA8+Z8+Y8 -> 6422.48
A9: =ROW(A9)-1 -> 8 | B9: 45999.45 | C9: ivanbordin@idr.pr.gov.br | D9: A aprovar | E9: =VLOOKUP(G9,DiretoriaDepart.Coord.!$A$1:$C$72,2,FALSE) -> Pesquisa e Inovação | F9: =VLOOKUP(G9,DiretoriaDepart.Coord.!$A$1:$C$72,3,FALSE) -> Pesquisa e Capacitação | G9: Polo de Pesquisa de Londrina | I9: 20º Encontro Nacional do Sistema Plantio Direto e o 3º Encontro Mundial | J9: Congresso | K9: 1 | L9: Ivan Bordin | M9: Federação Brasileira de Plantio Direto na Palha | N9: 500 | O9: Distrito Federal | P9: Brasília | Q9: 45815.333 | R9: 45817.708 | S9: Sim | T9: Presencial | U9: Sistema Plantio Direto | V9: Sou Assessor do programa grãos: soja e milho. Sou gerente do projeto de produção sustentável de grãos em rotação de culturas, em parceria com a ITAIPÚ (AISA). Pretendo levar resumos científicos para o evento. | W9: 10 | X9: 5 | Y9: 1200 | Z9: 0 | AA9: 4000 | AB9: 0 | AC9: 400 | AD9: 0 | AE9: 0 | AF9: Não | AG9: 0 | AH9: Sim | AI9: =IF(AF9="Sim",INT((R9-Q9+1))*K9*VLOOKUP(P9,'Tabelas Auxiliares'!$A$1:$C$400,3,FALSE),0) -> 0 | AJ9: =(AG9/10)*7 -> 0 | AK9: =IFS( O9="Acre",((W9*0.15)+(X9*0.7))*VLOOKUP(P9,'MunicípiosEstados'!$A$2:$B$23,2,FALSE), O9="Alagoas",((W9*0.15)+(X9*0.7))*VLOOKUP(P9,'MunicípiosEstados'!$C$2:$D$103,2,FALSE), O9="Amapá",((W9*0.15)+(X9*0.7))*VLOOKUP(P9,'MunicípiosEstados'!$E$2:$F$17,2,FALSE), O9="Amazonas",((W9*0.15)+(X9*0.7))*VLOOKUP(P9,'MunicípiosEstados'!$G$2:$H$63,2,FALSE), O9="Bahia",((W9*0.15)+(X9*0.7))*VLOOKUP(P9,'MunicípiosEstados'!$I$2:$J$418,2,FALSE), O9="Ceará",((W9*0.15)+(X9*0.7))*VLOOKUP(P9,'MunicípiosEstados'!$K$2:$L$185,2,FALSE), O9="Distrito Federal",((W9*0.15)+(X9*0.7))*VLOOKUP(P9,'MunicípiosEstados'!$M$2:$N$2,2,FALSE), O9="Espírito Santo",((W9*0.15)+(X9*0.7))*VLOOKUP(P9,'MunicípiosEstados'!$O$2:$P$79,2,FALSE), O9="Goiás",((W9*0.15)+(X9*0.7))*VLOOKUP(P9,'MunicípiosEstados'!$Q$2:$R$247,2,FALSE), O9="Maranhão",((W9*0.15)+(X9*0.7))*VLOOKUP(P9,'MunicípiosEstados'!$S$2:$T$218,2,FALSE), O9="Mato Grosso",((W9*0.15)+(X9*0.7))*VLOOKUP(P9,'MunicípiosEstados'!$U$2:$V$143,2,FALSE), O9="Mato Grosso do Sul",((W9*0.15)+(X9*0.7))*VLOOKUP(P9,'MunicípiosEstados'!$W$2:$X$80,2,FALSE), O9="Minas Gerais",((W9*0.15)+(X9*0.7))*VLOOKUP(P9,'MunicípiosEstados'!$Y$2:$Z$854,2,FALSE), O9="Pará",((W9*0.15)+(X9*0.7))*VLOOKUP(P9,'MunicípiosEstados'!$AA$2:$AB$145,2,FALSE), O9="Paraíba",((W9*0.15)+(X9*0.7))*VLOOKUP(P9,'MunicípiosEstados'!$AC$2:$AD$224,2,FALSE), O9="Paraná",((W9*0.15)+(X9*0.7))*VLOOKUP(P9,'MunicípiosEstados'!$AE$2:$AF$400,2,FALSE), O9="Pernambuco",((W9*0.15)+(X9*0.7))*VLOOKUP(P9,'MunicípiosEstados'!$AG$2:$AH$186,2,FALSE), O9="Piauí",((W9*0.15)+(X9*0.7))*VLOOKUP(P9,'MunicípiosEstados'!$AI$2:$AJ$225,2,FALSE), O9="Rio Grande do Norte",((W9*0.15)+(X9*0.7))*VLOOKUP(P9,'MunicípiosEstados'!$AK$2:$AL$168,2,FALSE), O9="Rio Grande do Sul",((W9*0.15)+(X9*0.7))*VLOOKUP(P9,'MunicípiosEstados'!$AM$2:$AN$498,2,FALSE), O9="Rio de Janeiro",((W9*0.15)+(X9*0.7))*VLOOKUP(P9,'MunicípiosEstados'!$AO$2:$AP$93,2,FALSE), O9="Rondônia",((W9*0.15)+(X9*0.7))*VLOOKUP(P9,'MunicípiosEstados'!$AQ$2:$AR$53,2,FALSE), O9="Roraima",((W9*0.15)+(X9*0.7))*VLOOKUP(P9,'MunicípiosEstados'!$AS$2:$AT$16,2,FALSE), O9="Santa Catarina",((W9*0.15)+(X9*0.7))*VLOOKUP(P9,'MunicípiosEstados'!$AU$2:$AV$296,2,FALSE), O9="São Paulo",((W9*0.15)+(X9*0.7))*VLOOKUP(P9,'MunicípiosEstados'!$AW$2:$AX$646,2,FALSE), O9="Sergipe",((W9*0.15)+(X9*0.7))*VLOOKUP(P9,'MunicípiosEstados'!$AY$2:$AZ$76,2,FALSE), O9="Tocantins",((W9*0.15)+(X9*0.7))*VLOOKUP(P9,'MunicípiosEstados'!$BA$2:$BB$140,2,FALSE), O9="Exterior",((W9*0.15)+(X9*0.7))*VLOOKUP(P9,'MunicípiosEstados'!$BC$2:$BE$221,3,FALSE),TRUE,0 ) -> 2340.6 | AL9: =AK9+AJ9+AI9+AE9+AD9+AC9+AB9+AA9+Z9+Y9 -> 7940.6
A10: =ROW(A10)-1 -> 9 | B10: 45999.629 | C10: patriciasantoro@idr.pr.gov.br | D10: Não Aprovado | E10: =VLOOKUP(G10,DiretoriaDepart.Coord.!$A$1:$C$72,2,FALSE) -> Pesquisa e Inovação | F10: =VLOOKUP(G10,DiretoriaDepart.Coord.!$A$1:$C$72,3,FALSE) -> Inovação e Comunicação Científica | G10: Fitotecnia e Fisiologia da Produção (Pesquisa) | I10: 20° Encontro Nacional do Sistema Plantio Direto e 3° Encontro Mundial do Sistema Plantio Direto | J10: Encontro | K10: 1 | L10: 1 | M10: não há | N10: 0 | O10: Distrito Federal | P10: Brasília | Q10: 45845.333 | R10: 45847.708 | S10: Não | T10: Presencial | U10: O encontro reunirá produtores, pesquisadores e lideranças do setor e simboliza um dos principais fóruns do agronegócio para discussão de técnicas de agricultura sustentável. | V10: Considerando que o Paraná foi o "berço" do Plantio Direto e que o IDR-Paraná foi pioneiro e extremamente relevante nos estudos e avanços relacionados aos pilares deste sistema de cultivo (rotação de culturas, plantas de cobertura e manejo do solo) é de suma importância representarmos a instituição em nivel nacional e mundial, inclusive salientar que em 2026 o projeto de pesquisa mais antigo de Plantio Direto da instituição conduzido em Pato Branco completa 40 anos! | W10: 8 | X10: 5 | Y10: 500 | Z10: 100 | AA10: 2500 | AB10: 0 | AC10: 300 | AD10: 0 | AE10: 0 | AF10: Não | AG10: 0 | AH10: Não | AI10: =IF(AF10="Sim",INT((R10-Q10+1))*K10*VLOOKUP(P10,'Tabelas Auxiliares'!$A$1:$C$400,3,FALSE),0) -> 0 | AJ10: =(AG10/10)*7 -> 0 | AK10: =IFS( O10="Acre",((W10*0.15)+(X10*0.7))*VLOOKUP(P10,'MunicípiosEstados'!$A$2:$B$23,2,FALSE), O10="Alagoas",((W10*0.15)+(X10*0.7))*VLOOKUP(P10,'MunicípiosEstados'!$C$2:$D$103,2,FALSE), O10="Amapá",((W10*0.15)+(X10*0.7))*VLOOKUP(P10,'MunicípiosEstados'!$E$2:$F$17,2,FALSE), O10="Amazonas",((W10*0.15)+(X10*0.7))*VLOOKUP(P10,'MunicípiosEstados'!$G$2:$H$63,2,FALSE), O10="Bahia",((W10*0.15)+(X10*0.7))*VLOOKUP(P10,'MunicípiosEstados'!$I$2:$J$418,2,FALSE), O10="Ceará",((W10*0.15)+(X10*0.7))*VLOOKUP(P10,'MunicípiosEstados'!$K$2:$L$185,2,FALSE), O10="Distrito Federal",((W10*0.15)+(X10*0.7))*VLOOKUP(P10,'MunicípiosEstados'!$M$2:$N$2,2,FALSE), O10="Espírito Santo",((W10*0.15)+(X10*0.7))*VLOOKUP(P10,'MunicípiosEstados'!$O$2:$P$79,2,FALSE), O10="Goiás",((W10*0.15)+(X10*0.7))*VLOOKUP(P10,'MunicípiosEstados'!$Q$2:$R$247,2,FALSE), O10="Maranhão",((W10*0.15)+(X10*0.7))*VLOOKUP(P10,'MunicípiosEstados'!$S$2:$T$218,2,FALSE), O10="Mato Grosso",((W10*0.15)+(X10*0.7))*VLOOKUP(P10,'MunicípiosEstados'!$U$2:$V$143,2,FALSE), O10="Mato Grosso do Sul",((W10*0.15)+(X10*0.7))*VLOOKUP(P10,'MunicípiosEstados'!$W$2:$X$80,2,FALSE), O10="Minas Gerais",((W10*0.15)+(X10*0.7))*VLOOKUP(P10,'MunicípiosEstados'!$Y$2:$Z$854,2,FALSE), O10="Pará",((W10*0.15)+(X10*0.7))*VLOOKUP(P10,'MunicípiosEstados'!$AA$2:$AB$145,2,FALSE), O10="Paraíba",((W10*0.15)+(X10*0.7))*VLOOKUP(P10,'MunicípiosEstados'!$AC$2:$AD$224,2,FALSE), O10="Paraná",((W10*0.15)+(X10*0.7))*VLOOKUP(P10,'MunicípiosEstados'!$AE$2:$AF$400,2,FALSE), O10="Pernambuco",((W10*0.15)+(X10*0.7))*VLOOKUP(P10,'MunicípiosEstados'!$AG$2:$AH$186,2,FALSE), O10="Piauí",((W10*0.15)+(X10*0.7))*VLOOKUP(P10,'MunicípiosEstados'!$AI$2:$AJ$225,2,FALSE), O10="Rio Grande do Norte",((W10*0.15)+(X10*0.7))*VLOOKUP(P10,'MunicípiosEstados'!$AK$2:$AL$168,2,FALSE), O10="Rio Grande do Sul",((W10*0.15)+(X10*0.7))*VLOOKUP(P10,'MunicípiosEstados'!$AM$2:$AN$498,2,FALSE), O10="Rio de Janeiro",((W10*0.15)+(X10*0.7))*VLOOKUP(P10,'MunicípiosEstados'!$AO$2:$AP$93,2,FALSE), O10="Rondônia",((W10*0.15)+(X10*0.7))*VLOOKUP(P10,'MunicípiosEstados'!$AQ$2:$AR$53,2,FALSE), O10="Roraima",((W10*0.15)+(X10*0.7))*VLOOKUP(P10,'MunicípiosEstados'!$AS$2:$AT$16,2,FALSE), O10="Santa Catarina",((W10*0.15)+(X10*0.7))*VLOOKUP(P10,'MunicípiosEstados'!$AU$2:$AV$296,2,FALSE), O10="São Paulo",((W10*0.15)+(X10*0.7))*VLOOKUP(P10,'MunicípiosEstados'!$AW$2:$AX$646,2,FALSE), O10="Sergipe",((W10*0.15)+(X10*0.7))*VLOOKUP(P10,'MunicípiosEstados'!$AY$2:$AZ$76,2,FALSE), O10="Tocantins",((W10*0.15)+(X10*0.7))*VLOOKUP(P10,'MunicípiosEstados'!$BA$2:$BB$140,2,FALSE), O10="Exterior",((W10*0.15)+(X10*0.7))*VLOOKUP(P10,'MunicípiosEstados'!$BC$2:$BE$221,3,FALSE),TRUE,0 ) -> 2200.164 | AL10: =AK10+AJ10+AI10+AE10+AD10+AC10+AB10+AA10+Z10+Y10 -> 5600.164 | AN10: Não aprovado por falta de informações: Nome do participante
A11: =ROW(A11)-1 -> 10 | B11: 45999.785 | C11: sramos@idr.pr.gov.br | D11: A aprovar | E11: =VLOOKUP(G11,DiretoriaDepart.Coord.!$A$1:$C$72,2,FALSE) -> Extensão Rural | F11: =VLOOKUP(G11,DiretoriaDepart.Coord.!$A$1:$C$72,3,FALSE) -> Políticas Públicas | G11: Turismo Rural (Extensão Rural) | I11: MISSÃO TÉCNICA COM O SEBRAE | J11: Excursão | K11: 5 | L11: Sidney Aurelio Valeriano Ramos, Ailton Rojas Poppi, Delma Fabiola Ferreira da Silva, Rogerio da Silva Almeida e Varlei Toller | M11: SEBRAE | N11: 30 | O11: Espírito Santo | P11: Venda Nova do Imigrante | Q11: 45719.333 | R11: 45721.708 | S11: Não | T11: Presencial | U11: TURISMO RURAL | V11: A realização da missão técnica entre o Instituto de Desenvolvimento Rural do Paraná (IDR-Paraná) e o Serviço Brasileiro de Apoio às Micro e Pequenas Empresas (SEBRAE) justifica-se como ação estratégica decorrente do acordo de cooperação vigente entre os dois entes, cujo objetivo é promover o desenvolvimento sustentável, a inovação e a competitividade dos empreendimentos rurais no Estado do Paraná. O acordo de cooperação estabelece a integração de esforços para fortalecimento das cadeias produtivas, difusão de tecnologias, aprimoramento de metodologias de assistência técnica e extensão rural (ATER), além da qualificação de produtores, técnicos e gestores. Nesse contexto, a missão técnica constitui etapa fundamental para o alinhamento de práticas, troca de experiências e identificação de soluções que contribuam para a melhoria contínua dos programas e projetos conjuntos. | W11: 45 | X11: 15 | Y11: 1500 | Z11: 0 | AA11: 7000 | AB11: 0 | AC11: 800 | AD11: 0 | AE11: 0 | AF11: Não | AG11: 1200 | AH11: Não | AI11: =IF(AF11="Sim",INT((R11-Q11+1))*K11*VLOOKUP(P11,'Tabelas Auxiliares'!$A$1:$C$400,3,FALSE),0) -> 0 | AJ11: =(AG11/10)*7 -> 840 | AK11: =IFS( O11="Acre",((W11*0.15)+(X11*0.7))*VLOOKUP(P11,'MunicípiosEstados'!$A$2:$B$23,2,FALSE), O11="Alagoas",((W11*0.15)+(X11*0.7))*VLOOKUP(P11,'MunicípiosEstados'!$C$2:$D$103,2,FALSE), O11="Amapá",((W11*0.15)+(X11*0.7))*VLOOKUP(P11,'MunicípiosEstados'!$E$2:$F$17,2,FALSE), O11="Amazonas",((W11*0.15)+(X11*0.7))*VLOOKUP(P11,'MunicípiosEstados'!$G$2:$H$63,2,FALSE), O11="Bahia",((W11*0.15)+(X11*0.7))*VLOOKUP(P11,'MunicípiosEstados'!$I$2:$J$418,2,FALSE), O11="Ceará",((W11*0.15)+(X11*0.7))*VLOOKUP(P11,'MunicípiosEstados'!$K$2:$L$185,2,FALSE), O11="Distrito Federal",((W11*0.15)+(X11*0.7))*VLOOKUP(P11,'MunicípiosEstados'!$M$2:$N$2,2,FALSE), O11="Espírito Santo",((W11*0.15)+(X11*0.7))*VLOOKUP(P11,'MunicípiosEstados'!$O$2:$P$79,2,FALSE), O11="Goiás",((W11*0.15)+(X11*0.7))*VLOOKUP(P11,'MunicípiosEstados'!$Q$2:$R$247,2,FALSE), O11="Maranhão",((W11*0.15)+(X11*0.7))*VLOOKUP(P11,'MunicípiosEstados'!$S$2:$T$218,2,FALSE), O11="Mato Grosso",((W11*0.15)+(X11*0.7))*VLOOKUP(P11,'MunicípiosEstados'!$U$2:$V$143,2,FALSE), O11="Mato Grosso do Sul",((W11*0.15)+(X11*0.7))*VLOOKUP(P11,'MunicípiosEstados'!$W$2:$X$80,2,FALSE), O11="Minas Gerais",((W11*0.15)+(X11*0.7))*VLOOKUP(P11,'MunicípiosEstados'!$Y$2:$Z$854,2,FALSE), O11="Pará",((W11*0.15)+(X11*0.7))*VLOOKUP(P11,'MunicípiosEstados'!$AA$2:$AB$145,2,FALSE), O11="Paraíba",((W11*0.15)+(X11*0.7))*VLOOKUP(P11,'MunicípiosEstados'!$AC$2:$AD$224,2,FALSE), O11="Paraná",((W11*0.15)+(X11*0.7))*VLOOKUP(P11,'MunicípiosEstados'!$AE$2:$AF$400,2,FALSE), O11="Pernambuco",((W11*0.15)+(X11*0.7))*VLOOKUP(P11,'MunicípiosEstados'!$AG$2:$AH$186,2,FALSE), O11="Piauí",((W11*0.15)+(X11*0.7))*VLOOKUP(P11,'MunicípiosEstados'!$AI$2:$AJ$225,2,FALSE), O11="Rio Grande do Norte",((W11*0.15)+(X11*0.7))*VLOOKUP(P11,'MunicípiosEstados'!$AK$2:$AL$168,2,FALSE), O11="Rio Grande do Sul",((W11*0.15)+(X11*0.7))*VLOOKUP(P11,'MunicípiosEstados'!$AM$2:$AN$498,2,FALSE), O11="Rio de Janeiro",((W11*0.15)+(X11*0.7))*VLOOKUP(P11,'MunicípiosEstados'!$AO$2:$AP$93,2,FALSE), O11="Rondônia",((W11*0.15)+(X11*0.7))*VLOOKUP(P11,'MunicípiosEstados'!$AQ$2:$AR$53,2,FALSE), O11="Roraima",((W11*0.15)+(X11*0.7))*VLOOKUP(P11,'MunicípiosEstados'!$AS$2:$AT$16,2,FALSE), O11="Santa Catarina",((W11*0.15)+(X11*0.7))*VLOOKUP(P11,'MunicípiosEstados'!$AU$2:$AV$296,2,FALSE), O11="São Paulo",((W11*0.15)+(X11*0.7))*VLOOKUP(P11,'MunicípiosEstados'!$AW$2:$AX$646,2,FALSE), O11="Sergipe",((W11*0.15)+(X11*0.7))*VLOOKUP(P11,'MunicípiosEstados'!$AY$2:$AZ$76,2,FALSE), O11="Tocantins",((W11*0.15)+(X11*0.7))*VLOOKUP(P11,'MunicípiosEstados'!$BA$2:$BB$140,2,FALSE), O11="Exterior",((W11*0.15)+(X11*0.7))*VLOOKUP(P11,'MunicípiosEstados'!$BC$2:$BE$221,3,FALSE),TRUE,0 ) -> 5011.9875 | AL11: =AK11+AJ11+AI11+AE11+AD11+AC11+AB11+AA11+Z11+Y11 -> 15151.987
A12: =ROW(A12)-1 -> 11 | B12: 45978.623 | C12: laisepontes@idr.pr.gov.br | D12: A aprovar | E12: =VLOOKUP(G12,DiretoriaDepart.Coord.!$A$1:$C$72,2,FALSE) -> Pesquisa e Inovação | F12: =VLOOKUP(G12,DiretoriaDepart.Coord.!$A$1:$C$72,3,FALSE) -> Pesquisa e Capacitação | G12: Programa de Pecuária de Corte e ILPF (Pesquisa) | I12: EGF 2026 | J12: Congresso | K12: 1 | L12: Laíse da Silveira Pontes | M12: European Grassland Federation | N12: 350 | O12: Exterior | P12: Portugal | Q12: 45759.333 | R12: 45763.75 | S12: Sim | T12: Presencial | U12: Desafios e inovações para a resiliência das pastagens. | V12: O congresso internacional do EGF “Desafios e inovações para a resiliência das pastagens” reunirá pesquisadores de diversos países que atuam na temática da sustentabilidade e resiliência dos sistemas de pastagens, constituindo-se em um espaço privilegiado para trocas de experiências, aprendizado e atualização científica. A participação de pesquisadores do IDR-Paraná em evento desta magnitude é de suma importância, considerando que os desafios enfrentados pelos sistemas de pastagens — como mudanças climáticas, abandono/degradação de áreas rurais, conflitos de uso da terra, riscos crescentes de incêndios, perda de biodiversidade, pressões sobre solo e água, além de transformações na demanda por proteína e nos sistemas de produção animal — também se refletem diretamente na realidade brasileira. Mudanças climáticas e pastagens, manejo do solo e da água • Impactos das mudanças climáticas sobre as pastagens • Capacidade das pastagens de se adaptar às mudanças climáticas • Sequestro de carbono em pastagens para mitigar as mudanças climáticas • Solo, água, práticas de cultivo e manejo do pastoreio para a estabilidade das pastagens • Novas tecnologias para o desenvolvimento e resiliência das pastagens Agroflorestas, pastoralismo e sociedade • O papel das pastagens na sustentabilidade das propriedades agroflorestais • Sinergias entre pastagens, arbustos, árvores e animais em sistemas agroflorestais • Práticas para prevenir a degradação em sistemas agroflorestais • Pastoreio e pastoralismo: atendendo às demandas da sociedade • O papel contemporâneo do pastoralismo • Pastoralismo e tecnologias emergentes • Pastoralismo: equilibrando o bem-estar dos agricultores, expectativas dos consumidores, bem-estar animal e biodiversidade Melhoramento para novos desafios • Incorporação de novas espécies vegetais nos sistemas agrícolas • Estratégias de melhoramento vegetal em resposta às mudanças nos padrões climáticos • Estratégias de melhoramento vegetal para reduzir emissões de metano • Características genéticas das plantas e seu papel na redução das emissões do pastoreio • Aproveitamento da diversidade genética animal para enfrentar novos desafios das pastagens Sistemas sustentáveis de produção pecuária baseados em pastagens: desafios e oportunidades • Manejo adaptado ao local baseado em pastagens • Serviços ecossistêmicos proporcionados pelo uso das pastagens pelo gado • Autossuficiência proteica de sistemas de produção de ruminantes e monogástricos • Pecuária de precisão • Qualidade e rotulagem de produtos animais baseados em pastagens Pastagens e ferramentas de políticas rurais para enfrentar desafios globais • Ferramentas de políticas para adaptação das funções das pastagens • Eco-esquemas e programas de desenvolvimento rural em resposta à perda de pastagens • Enfrentando desafios emergentes por meio de políticas públicas voltadas às pastagens • Construindo resiliência: políticas como proteção diante de crises futuras • Fomentando o papel das pastagens na estabilidade dos sistemas agrícolas A participação neste evento permitirá não apenas a atualização científica, mas também a apresentação de resultados de pesquisas já desenvolvidas no âmbito do IDR-Paraná, cujos trabalhos (2) foram aceitos pela organização do congresso para publicação nos General Meeting Proceedings. Trata-se, portanto, de uma oportunidade estratégica para dar visibilidade internacional às pesquisas realizadas, fortalecer parcerias e trazer subsídios técnicos e científicos que poderão ser aplicados em programas de extensão e políticas públicas voltadas ao setor agropecuário paranaense. A presença neste evento internacional contribuirá significativamente para o fortalecimento da atuação do IDR-Paraná na temática das pastagens e sistemas agropecuários sustentáveis, ampliando a inserção da pesquisa paranaense em debates globais e trazendo benefícios diretos para o desenvolvimento rural e a segurança alimentar. | W12: 12 | X12: 6 | Y12: 4000 | Z12: 200 | AA12: 0 | AB12: 0 | AC12: 100 | AD12: 0 | AE12: 0 | AF12: Não | AG12: 0 | AH12: Não | AI12: =IF(AF12="Sim",INT((R12-Q12+1))*K12*VLOOKUP(P12,'Tabelas Auxiliares'!$A$1:$C$400,3,FALSE),0) -> 0 | AJ12: =(AG12/10)*7 -> 0 | AK12: =IFS( O12="Acre",((W12*0.15)+(X12*0.7))*VLOOKUP(P12,'MunicípiosEstados'!$A$2:$B$23,2,FALSE), O12="Alagoas",((W12*0.15)+(X12*0.7))*VLOOKUP(P12,'MunicípiosEstados'!$C$2:$D$103,2,FALSE), O12="Amapá",((W12*0.15)+(X12*0.7))*VLOOKUP(P12,'MunicípiosEstados'!$E$2:$F$17,2,FALSE), O12="Amazonas",((W12*0.15)+(X12*0.7))*VLOOKUP(P12,'MunicípiosEstados'!$G$2:$H$63,2,FALSE), O12="Bahia",((W12*0.15)+(X12*0.7))*VLOOKUP(P12,'MunicípiosEstados'!$I$2:$J$418,2,FALSE), O12="Ceará",((W12*0.15)+(X12*0.7))*VLOOKUP(P12,'MunicípiosEstados'!$K$2:$L$185,2,FALSE), O12="Distrito Federal",((W12*0.15)+(X12*0.7))*VLOOKUP(P12,'MunicípiosEstados'!$M$2:$N$2,2,FALSE), O12="Espírito Santo",((W12*0.15)+(X12*0.7))*VLOOKUP(P12,'MunicípiosEstados'!$O$2:$P$79,2,FALSE), O12="Goiás",((W12*0.15)+(X12*0.7))*VLOOKUP(P12,'MunicípiosEstados'!$Q$2:$R$247,2,FALSE), O12="Maranhão",((W12*0.15)+(X12*0.7))*VLOOKUP(P12,'MunicípiosEstados'!$S$2:$T$218,2,FALSE), O12="Mato Grosso",((W12*0.15)+(X12*0.7))*VLOOKUP(P12,'MunicípiosEstados'!$U$2:$V$143,2,FALSE), O12="Mato Grosso do Sul",((W12*0.15)+(X12*0.7))*VLOOKUP(P12,'MunicípiosEstados'!$W$2:$X$80,2,FALSE), O12="Minas Gerais",((W12*0.15)+(X12*0.7))*VLOOKUP(P12,'MunicípiosEstados'!$Y$2:$Z$854,2,FALSE), O12="Pará",((W12*0.15)+(X12*0.7))*VLOOKUP(P12,'MunicípiosEstados'!$AA$2:$AB$145,2,FALSE), O12="Paraíba",((W12*0.15)+(X12*0.7))*VLOOKUP(P12,'MunicípiosEstados'!$AC$2:$AD$224,2,FALSE), O12="Paraná",((W12*0.15)+(X12*0.7))*VLOOKUP(P12,'MunicípiosEstados'!$AE$2:$AF$400,2,FALSE), O12="Pernambuco",((W12*0.15)+(X12*0.7))*VLOOKUP(P12,'MunicípiosEstados'!$AG$2:$AH$186,2,FALSE), O12="Piauí",((W12*0.15)+(X12*0.7))*VLOOKUP(P12,'MunicípiosEstados'!$AI$2:$AJ$225,2,FALSE), O12="Rio Grande do Norte",((W12*0.15)+(X12*0.7))*VLOOKUP(P12,'MunicípiosEstados'!$AK$2:$AL$168,2,FALSE), O12="Rio Grande do Sul",((W12*0.15)+(X12*0.7))*VLOOKUP(P12,'MunicípiosEstados'!$AM$2:$AN$498,2,FALSE), O12="Rio de Janeiro",((W12*0.15)+(X12*0.7))*VLOOKUP(P12,'MunicípiosEstados'!$AO$2:$AP$93,2,FALSE), O12="Rondônia",((W12*0.15)+(X12*0.7))*VLOOKUP(P12,'MunicípiosEstados'!$AQ$2:$AR$53,2,FALSE), O12="Roraima",((W12*0.15)+(X12*0.7))*VLOOKUP(P12,'MunicípiosEstados'!$AS$2:$AT$16,2,FALSE), O12="Santa Catarina",((W12*0.15)+(X12*0.7))*VLOOKUP(P12,'MunicípiosEstados'!$AU$2:$AV$296,2,FALSE), O12="São Paulo",((W12*0.15)+(X12*0.7))*VLOOKUP(P12,'MunicípiosEstados'!$AW$2:$AX$646,2,FALSE), O12="Sergipe",((W12*0.15)+(X12*0.7))*VLOOKUP(P12,'MunicípiosEstados'!$AY$2:$AZ$76,2,FALSE), O12="Tocantins",((W12*0.15)+(X12*0.7))*VLOOKUP(P12,'MunicípiosEstados'!$BA$2:$BB$140,2,FALSE), O12="Exterior",((W12*0.15)+(X12*0.7))*VLOOKUP(P12,'MunicípiosEstados'!$BC$2:$BE$221,3,FALSE),TRUE,0 ) -> 13164.03 | AL12: =AK12+AJ12+AI12+AE12+AD12+AC12+AB12+AA12+Z12+Y12 -> 17464.03
A13: =ROW(A13)-1 -> 12 | B13: 45978.67 | C13: kfgobbi@idr.pr.gov.br | D13: A aprovar | E13: =VLOOKUP(G13,DiretoriaDepart.Coord.!$A$1:$C$72,2,FALSE) -> Pesquisa e Inovação | F13: =VLOOKUP(G13,DiretoriaDepart.Coord.!$A$1:$C$72,3,FALSE) -> Pesquisa e Capacitação | G13: Programa de Pecuária de Corte e ILPF (Pesquisa) | I13: 31st EGF (European Grassland Federation) General Meeting | J13: Congresso | K13: 1 | M13: Universidade de Évora, Portugal | N13: 500 | O13: Exterior | P13: Portugal | Q13: 45759.333 | R13: 45763.708 | S13: Sim | T13: Presencial | U13: Forragicultura e pastagens; Sistema silvopastoril (manejo tradicional); Sistema silvopastoril multifuncional - Biodiversidade e sistemas de pastoreio complementares (Bovinos, Ovinos, Caprinos, Suínos); | V13: O Encontro Geral da Federação Europeia de Pastagens é um dos principais eventos mundiais sobre o tema pastagens e forragicultura. Em 2026 terá como foco os desafios e inovações para a resiliência das pastagens, mudanças climáticas e pastagens, manejo do solo e da água; agrofloresta, pastoralismo e sociedade; Melhoramento genético para novos desafios; Sistemas sustentáveis ​​de produção pecuária baseados em pastagens; Ferramentas de política para pastagens e terras rurais para enfrentar desafios globais. | W13: 0 | X13: 0 | Y13: 4500 | Z13: 0 | AA13: 0 | AB13: 0 | AC13: 0 | AD13: 0 | AE13: 0 | AF13: Não | AG13: 0 | AH13: Não | AI13: =IF(AF13="Sim",INT((R13-Q13+1))*K13*VLOOKUP(P13,'Tabelas Auxiliares'!$A$1:$C$400,3,FALSE),0) -> 0 | AJ13: =(AG13/10)*7 -> 0 | AK13: =IFS( O13="Acre",((W13*0.15)+(X13*0.7))*VLOOKUP(P13,'MunicípiosEstados'!$A$2:$B$23,2,FALSE), O13="Alagoas",((W13*0.15)+(X13*0.7))*VLOOKUP(P13,'MunicípiosEstados'!$C$2:$D$103,2,FALSE), O13="Amapá",((W13*0.15)+(X13*0.7))*VLOOKUP(P13,'MunicípiosEstados'!$E$2:$F$17,2,FALSE), O13="Amazonas",((W13*0.15)+(X13*0.7))*VLOOKUP(P13,'MunicípiosEstados'!$G$2:$H$63,2,FALSE), O13="Bahia",((W13*0.15)+(X13*0.7))*VLOOKUP(P13,'MunicípiosEstados'!$I$2:$J$418,2,FALSE), O13="Ceará",((W13*0.15)+(X13*0.7))*VLOOKUP(P13,'MunicípiosEstados'!$K$2:$L$185,2,FALSE), O13="Distrito Federal",((W13*0.15)+(X13*0.7))*VLOOKUP(P13,'MunicípiosEstados'!$M$2:$N$2,2,FALSE), O13="Espírito Santo",((W13*0.15)+(X13*0.7))*VLOOKUP(P13,'MunicípiosEstados'!$O$2:$P$79,2,FALSE), O13="Goiás",((W13*0.15)+(X13*0.7))*VLOOKUP(P13,'MunicípiosEstados'!$Q$2:$R$247,2,FALSE), O13="Maranhão",((W13*0.15)+(X13*0.7))*VLOOKUP(P13,'MunicípiosEstados'!$S$2:$T$218,2,FALSE), O13="Mato Grosso",((W13*0.15)+(X13*0.7))*VLOOKUP(P13,'MunicípiosEstados'!$U$2:$V$143,2,FALSE), O13="Mato Grosso do Sul",((W13*0.15)+(X13*0.7))*VLOOKUP(P13,'MunicípiosEstados'!$W$2:$X$80,2,FALSE), O13="Minas Gerais",((W13*0.15)+(X13*0.7))*VLOOKUP(P13,'MunicípiosEstados'!$Y$2:$Z$854,2,FALSE), O13="Pará",((W13*0.15)+(X13*0.7))*VLOOKUP(P13,'MunicípiosEstados'!$AA$2:$AB$145,2,FALSE), O13="Paraíba",((W13*0.15)+(X13*0.7))*VLOOKUP(P13,'MunicípiosEstados'!$AC$2:$AD$224,2,FALSE), O13="Paraná",((W13*0.15)+(X13*0.7))*VLOOKUP(P13,'MunicípiosEstados'!$AE$2:$AF$400,2,FALSE), O13="Pernambuco",((W13*0.15)+(X13*0.7))*VLOOKUP(P13,'MunicípiosEstados'!$AG$2:$AH$186,2,FALSE), O13="Piauí",((W13*0.15)+(X13*0.7))*VLOOKUP(P13,'MunicípiosEstados'!$AI$2:$AJ$225,2,FALSE), O13="Rio Grande do Norte",((W13*0.15)+(X13*0.7))*VLOOKUP(P13,'MunicípiosEstados'!$AK$2:$AL$168,2,FALSE), O13="Rio Grande do Sul",((W13*0.15)+(X13*0.7))*VLOOKUP(P13,'MunicípiosEstados'!$AM$2:$AN$498,2,FALSE), O13="Rio de Janeiro",((W13*0.15)+(X13*0.7))*VLOOKUP(P13,'MunicípiosEstados'!$AO$2:$AP$93,2,FALSE), O13="Rondônia",((W13*0.15)+(X13*0.7))*VLOOKUP(P13,'MunicípiosEstados'!$AQ$2:$AR$53,2,FALSE), O13="Roraima",((W13*0.15)+(X13*0.7))*VLOOKUP(P13,'MunicípiosEstados'!$AS$2:$AT$16,2,FALSE), O13="Santa Catarina",((W13*0.15)+(X13*0.7))*VLOOKUP(P13,'MunicípiosEstados'!$AU$2:$AV$296,2,FALSE), O13="São Paulo",((W13*0.15)+(X13*0.7))*VLOOKUP(P13,'MunicípiosEstados'!$AW$2:$AX$646,2,FALSE), O13="Sergipe",((W13*0.15)+(X13*0.7))*VLOOKUP(P13,'MunicípiosEstados'!$AY$2:$AZ$76,2,FALSE), O13="Tocantins",((W13*0.15)+(X13*0.7))*VLOOKUP(P13,'MunicípiosEstados'!$BA$2:$BB$140,2,FALSE), O13="Exterior",((W13*0.15)+(X13*0.7))*VLOOKUP(P13,'MunicípiosEstados'!$BC$2:$BE$221,3,FALSE),TRUE,0 ) -> 0 | AL13: =AK13+AJ13+AI13+AE13+AD13+AC13+AB13+AA13+Z13+Y13 -> 4500
A14: =ROW(A14)-1 -> 13 | B14: 45979.49 | C14: josiane@idr.pr.gov.br | D14: A aprovar | E14: =VLOOKUP(G14,DiretoriaDepart.Coord.!$A$1:$C$72,2,FALSE) -> Pesquisa e Inovação | F14: =VLOOKUP(G14,DiretoriaDepart.Coord.!$A$1:$C$72,3,FALSE) -> Inovação e Comunicação Científica | G14: Melhoramento Genético Vegetal e Sementes (Pesquisa) | I14: ISF World Seed Congress 2026 | J14: Congresso | K14: 1 | L14: Josiane Cristina de Assis Aliança | M14: Federação Internacional de Sementes (ISF) | N14: 4000 | O14: Exterior | P14: Portugal | Q14: 45795.333 | R14: 45797.75 | S14: Sim | T14: Presencial | U14: Produção mundial de sementes, desafios e formação de parcerias no setor | V14: O evento tem como objetivo fomentar parcerias estratégicas e discutir os principais temas do setor. Com expositores, mesas de negociação e amplas oportunidades de networking, o IDR-Paraná terá a oportunidade de expor as novas cultivares de aveia forrageira que foram registradas e também alcançar uma visibilidade no público Europeu, que utiliza há muitos anos as cultivares de aveia IAPAR 61 e IPR Cabocla. Será um evento que será possível apresentar as cultivares de aveia branca forrageira, que poderão ser testadas e validadas também para uso internacional. Além da grande absorção de novos conhecimentos, que é essencial a todo pesquisador, principalmente os que trabalham com genética e melhoramento de plantas e sementes, que é exatamente a minha linha de pesquisa no IDR-Paraná. | W14: 5 | X14: 5 | Y14: 6170 | Z14: 180 | AA14: 5772 | AB14: 200 | AC14: 500 | AD14: 0 | AE14: 0 | AF14: Não | AG14: 0 | AH14: Não | AI14: =IF(AF14="Sim",INT((R14-Q14+1))*K14*VLOOKUP(P14,'Tabelas Auxiliares'!$A$1:$C$400,3,FALSE),0) -> 0 | AJ14: =(AG14/10)*7 -> 0 | AK14: =IFS( O14="Acre",((W14*0.15)+(X14*0.7))*VLOOKUP(P14,'MunicípiosEstados'!$A$2:$B$23,2,FALSE), O14="Alagoas",((W14*0.15)+(X14*0.7))*VLOOKUP(P14,'MunicípiosEstados'!$C$2:$D$103,2,FALSE), O14="Amapá",((W14*0.15)+(X14*0.7))*VLOOKUP(P14,'MunicípiosEstados'!$E$2:$F$17,2,FALSE), O14="Amazonas",((W14*0.15)+(X14*0.7))*VLOOKUP(P14,'MunicípiosEstados'!$G$2:$H$63,2,FALSE), O14="Bahia",((W14*0.15)+(X14*0.7))*VLOOKUP(P14,'MunicípiosEstados'!$I$2:$J$418,2,FALSE), O14="Ceará",((W14*0.15)+(X14*0.7))*VLOOKUP(P14,'MunicípiosEstados'!$K$2:$L$185,2,FALSE), O14="Distrito Federal",((W14*0.15)+(X14*0.7))*VLOOKUP(P14,'MunicípiosEstados'!$M$2:$N$2,2,FALSE), O14="Espírito Santo",((W14*0.15)+(X14*0.7))*VLOOKUP(P14,'MunicípiosEstados'!$O$2:$P$79,2,FALSE), O14="Goiás",((W14*0.15)+(X14*0.7))*VLOOKUP(P14,'MunicípiosEstados'!$Q$2:$R$247,2,FALSE), O14="Maranhão",((W14*0.15)+(X14*0.7))*VLOOKUP(P14,'MunicípiosEstados'!$S$2:$T$218,2,FALSE), O14="Mato Grosso",((W14*0.15)+(X14*0.7))*VLOOKUP(P14,'MunicípiosEstados'!$U$2:$V$143,2,FALSE), O14="Mato Grosso do Sul",((W14*0.15)+(X14*0.7))*VLOOKUP(P14,'MunicípiosEstados'!$W$2:$X$80,2,FALSE), O14="Minas Gerais",((W14*0.15)+(X14*0.7))*VLOOKUP(P14,'MunicípiosEstados'!$Y$2:$Z$854,2,FALSE), O14="Pará",((W14*0.15)+(X14*0.7))*VLOOKUP(P14,'MunicípiosEstados'!$AA$2:$AB$145,2,FALSE), O14="Paraíba",((W14*0.15)+(X14*0.7))*VLOOKUP(P14,'MunicípiosEstados'!$AC$2:$AD$224,2,FALSE), O14="Paraná",((W14*0.15)+(X14*0.7))*VLOOKUP(P14,'MunicípiosEstados'!$AE$2:$AF$400,2,FALSE), O14="Pernambuco",((W14*0.15)+(X14*0.7))*VLOOKUP(P14,'MunicípiosEstados'!$AG$2:$AH$186,2,FALSE), O14="Piauí",((W14*0.15)+(X14*0.7))*VLOOKUP(P14,'MunicípiosEstados'!$AI$2:$AJ$225,2,FALSE), O14="Rio Grande do Norte",((W14*0.15)+(X14*0.7))*VLOOKUP(P14,'MunicípiosEstados'!$AK$2:$AL$168,2,FALSE), O14="Rio Grande do Sul",((W14*0.15)+(X14*0.7))*VLOOKUP(P14,'MunicípiosEstados'!$AM$2:$AN$498,2,FALSE), O14="Rio de Janeiro",((W14*0.15)+(X14*0.7))*VLOOKUP(P14,'MunicípiosEstados'!$AO$2:$AP$93,2,FALSE), O14="Rondônia",((W14*0.15)+(X14*0.7))*VLOOKUP(P14,'MunicípiosEstados'!$AQ$2:$AR$53,2,FALSE), O14="Roraima",((W14*0.15)+(X14*0.7))*VLOOKUP(P14,'MunicípiosEstados'!$AS$2:$AT$16,2,FALSE), O14="Santa Catarina",((W14*0.15)+(X14*0.7))*VLOOKUP(P14,'MunicípiosEstados'!$AU$2:$AV$296,2,FALSE), O14="São Paulo",((W14*0.15)+(X14*0.7))*VLOOKUP(P14,'MunicípiosEstados'!$AW$2:$AX$646,2,FALSE), O14="Sergipe",((W14*0.15)+(X14*0.7))*VLOOKUP(P14,'MunicípiosEstados'!$AY$2:$AZ$76,2,FALSE), O14="Tocantins",((W14*0.15)+(X14*0.7))*VLOOKUP(P14,'MunicípiosEstados'!$BA$2:$BB$140,2,FALSE), O14="Exterior",((W14*0.15)+(X14*0.7))*VLOOKUP(P14,'MunicípiosEstados'!$BC$2:$BE$221,3,FALSE),TRUE,0 ) -> 9324.5212 | AL14: =AK14+AJ14+AI14+AE14+AD14+AC14+AB14+AA14+Z14+Y14 -> 22146.521
A15: =ROW(A15)-1 -> 14 | B15: 45987.427 | C15: tomaz@idr.pr.gov.br | D15: A aprovar | E15: =VLOOKUP(G15,DiretoriaDepart.Coord.!$A$1:$C$72,2,FALSE) -> Pesquisa e Inovação | F15: =VLOOKUP(G15,DiretoriaDepart.Coord.!$A$1:$C$72,3,FALSE) -> Inovação e Comunicação Científica | G15: Melhoramento Genético Vegetal e Sementes (Pesquisa) | I15: ICAR2026 - International Conference on Arabidopsis Research | J15: Conferência | K15: 1 | L15: Juarez Pires Tomaz | M15: Não há | N15: 1000 | O15: Exterior | P15: Singapura | Q15: 45830.333 | R15: 45834.833 | S15: Sim | T15: Presencial | U15: Desenvolvimento da ciência básica pelo uso de Arabidopsis como modelo vegetal | V15: A Conferência Internacional sobre Pesquisa em Arabidopsis (ICAR) é o principal encontro anual da comunidade global de cientistas que utilizam Arabidopsis thaliana como sistema modelo. Por quase quatro décadas, a ICAR tem destacado as notáveis ​​contribuições da Arabidopsis para o avanço da biologia vegetal ou até mesmo humana e, a cada ano, reúne mais de 1.000 cientistas de todo o mundo. No IDR-Paraná, a utilização desse organismo modelo já levou à compreensão de defesa hormonal e da percepção das defesas vegetais contra o ataque de nematoides, além de ter sido ferramenta para busca de genes de resistência. Atualmente o IDR-Paraná é o instituto que detém o maior banco de germoplasma de Arabidopsis do Brasil, com 380 ecótipos. Investir na capacitação nesta temática colocaria o IDR-Paraná no cenário mundial para pesquisa básica com plantas modelo, além de proporcionar inúmeras possibilidades de aprendizado e parcerias científicas. | W15: 7 | X15: 6 | Y15: 7500 | Z15: 100 | AA15: 10638 | AB15: 0 | AC15: 1000 | AD15: 0 | AE15: 0 | AF15: Não | AG15: 0 | AH15: Não | AI15: =IF(AF15="Sim",INT((R15-Q15+1))*K15*VLOOKUP(P15,'Tabelas Auxiliares'!$A$1:$C$400,3,FALSE),0) -> 0 | AJ15: =(AG15/10)*7 -> 0 | AK15: =IFS( O15="Acre",((W15*0.15)+(X15*0.7))*VLOOKUP(P15,'MunicípiosEstados'!$A$2:$B$23,2,FALSE), O15="Alagoas",((W15*0.15)+(X15*0.7))*VLOOKUP(P15,'MunicípiosEstados'!$C$2:$D$103,2,FALSE), O15="Amapá",((W15*0.15)+(X15*0.7))*VLOOKUP(P15,'MunicípiosEstados'!$E$2:$F$17,2,FALSE), O15="Amazonas",((W15*0.15)+(X15*0.7))*VLOOKUP(P15,'MunicípiosEstados'!$G$2:$H$63,2,FALSE), O15="Bahia",((W15*0.15)+(X15*0.7))*VLOOKUP(P15,'MunicípiosEstados'!$I$2:$J$418,2,FALSE), O15="Ceará",((W15*0.15)+(X15*0.7))*VLOOKUP(P15,'MunicípiosEstados'!$K$2:$L$185,2,FALSE), O15="Distrito Federal",((W15*0.15)+(X15*0.7))*VLOOKUP(P15,'MunicípiosEstados'!$M$2:$N$2,2,FALSE), O15="Espírito Santo",((W15*0.15)+(X15*0.7))*VLOOKUP(P15,'MunicípiosEstados'!$O$2:$P$79,2,FALSE), O15="Goiás",((W15*0.15)+(X15*0.7))*VLOOKUP(P15,'MunicípiosEstados'!$Q$2:$R$247,2,FALSE), O15="Maranhão",((W15*0.15)+(X15*0.7))*VLOOKUP(P15,'MunicípiosEstados'!$S$2:$T$218,2,FALSE), O15="Mato Grosso",((W15*0.15)+(X15*0.7))*VLOOKUP(P15,'MunicípiosEstados'!$U$2:$V$143,2,FALSE), O15="Mato Grosso do Sul",((W15*0.15)+(X15*0.7))*VLOOKUP(P15,'MunicípiosEstados'!$W$2:$X$80,2,FALSE), O15="Minas Gerais",((W15*0.15)+(X15*0.7))*VLOOKUP(P15,'MunicípiosEstados'!$Y$2:$Z$854,2,FALSE), O15="Pará",((W15*0.15)+(X15*0.7))*VLOOKUP(P15,'MunicípiosEstados'!$AA$2:$AB$145,2,FALSE), O15="Paraíba",((W15*0.15)+(X15*0.7))*VLOOKUP(P15,'MunicípiosEstados'!$AC$2:$AD$224,2,FALSE), O15="Paraná",((W15*0.15)+(X15*0.7))*VLOOKUP(P15,'MunicípiosEstados'!$AE$2:$AF$400,2,FALSE), O15="Pernambuco",((W15*0.15)+(X15*0.7))*VLOOKUP(P15,'MunicípiosEstados'!$AG$2:$AH$186,2,FALSE), O15="Piauí",((W15*0.15)+(X15*0.7))*VLOOKUP(P15,'MunicípiosEstados'!$AI$2:$AJ$225,2,FALSE), O15="Rio Grande do Norte",((W15*0.15)+(X15*0.7))*VLOOKUP(P15,'MunicípiosEstados'!$AK$2:$AL$168,2,FALSE), O15="Rio Grande do Sul",((W15*0.15)+(X15*0.7))*VLOOKUP(P15,'MunicípiosEstados'!$AM$2:$AN$498,2,FALSE), O15="Rio de Janeiro",((W15*0.15)+(X15*0.7))*VLOOKUP(P15,'MunicípiosEstados'!$AO$2:$AP$93,2,FALSE), O15="Rondônia",((W15*0.15)+(X15*0.7))*VLOOKUP(P15,'MunicípiosEstados'!$AQ$2:$AR$53,2,FALSE), O15="Roraima",((W15*0.15)+(X15*0.7))*VLOOKUP(P15,'MunicípiosEstados'!$AS$2:$AT$16,2,FALSE), O15="Santa Catarina",((W15*0.15)+(X15*0.7))*VLOOKUP(P15,'MunicípiosEstados'!$AU$2:$AV$296,2,FALSE), O15="São Paulo",((W15*0.15)+(X15*0.7))*VLOOKUP(P15,'MunicípiosEstados'!$AW$2:$AX$646,2,FALSE), O15="Sergipe",((W15*0.15)+(X15*0.7))*VLOOKUP(P15,'MunicípiosEstados'!$AY$2:$AZ$76,2,FALSE), O15="Tocantins",((W15*0.15)+(X15*0.7))*VLOOKUP(P15,'MunicípiosEstados'!$BA$2:$BB$140,2,FALSE), O15="Exterior",((W15*0.15)+(X15*0.7))*VLOOKUP(P15,'MunicípiosEstados'!$BC$2:$BE$221,3,FALSE),TRUE,0 ) -> 13175.663 | AL15: =AK15+AJ15+AI15+AE15+AD15+AC15+AB15+AA15+Z15+Y15 -> 32413.662
A16: =ROW(A16)-1 -> 15 | B16: 45987.478 | C16: heverly@idr.pr.gov.br | D16: Não Aprovado | E16: =VLOOKUP(G16,DiretoriaDepart.Coord.!$A$1:$C$72,2,FALSE) -> Pesquisa e Inovação | F16: =VLOOKUP(G16,DiretoriaDepart.Coord.!$A$1:$C$72,3,FALSE) -> Inovação e Comunicação Científica | G16: Agrometereologia (Pesquisa) | I16: Congresso de Sistemas Agroflorestais | J16: Congresso | K16: 2 | M16: Não se aplica | N16: 0 | O16: Exterior | P16: Costa Rica | Q16: 45844.333 | R16: 45848.75 | S16: Não | T16: Presencial | U16: Produção Regenerativa e Adaptação às Mudanças Climáticas | V16: A pesquisadora Dra. Heverly Morais desenvolve suas atividades com Mudanças Climáticas e Sistemas Agroflorestais (SAFs), tendo participado de inúmeros projetos. Coordena atualmente projetos de pesquisa, experimentos de campo e atividades nesses temas. A mesma possui inúmeras publicações em revistas científicas especializadas, congressos, livros e circulares. Sua participação neste evento terá como fim interação com a comunidade científica e atualização dos seus conhecimentos sobre quais as inovações, expectativas e avanços dos SAFs e Mudanças Climáticas. Além disso, através desse evento poderão ser formados contatos e parcerias entre o IDR-Paraná e universidades e institutos de pesquisa. | W16: 26 | X16: 14 | Y16: 700 | Z16: 100 | AA16: 5200 | AB16: 0 | AC16: 400 | AD16: 0 | AE16: 0 | AF16: Não | AG16: 0 | AH16: Não | AI16: =IF(AF16="Sim",INT((R16-Q16+1))*K16*VLOOKUP(P16,'Tabelas Auxiliares'!$A$1:$C$400,3,FALSE),0) -> 0 | AJ16: =(AG16/10)*7 -> 0 | AK16: =IFS( O16="Acre",((W16*0.15)+(X16*0.7))*VLOOKUP(P16,'MunicípiosEstados'!$A$2:$B$23,2,FALSE), O16="Alagoas",((W16*0.15)+(X16*0.7))*VLOOKUP(P16,'MunicípiosEstados'!$C$2:$D$103,2,FALSE), O16="Amapá",((W16*0.15)+(X16*0.7))*VLOOKUP(P16,'MunicípiosEstados'!$E$2:$F$17,2,FALSE), O16="Amazonas",((W16*0.15)+(X16*0.7))*VLOOKUP(P16,'MunicípiosEstados'!$G$2:$H$63,2,FALSE), O16="Bahia",((W16*0.15)+(X16*0.7))*VLOOKUP(P16,'MunicípiosEstados'!$I$2:$J$418,2,FALSE), O16="Ceará",((W16*0.15)+(X16*0.7))*VLOOKUP(P16,'MunicípiosEstados'!$K$2:$L$185,2,FALSE), O16="Distrito Federal",((W16*0.15)+(X16*0.7))*VLOOKUP(P16,'MunicípiosEstados'!$M$2:$N$2,2,FALSE), O16="Espírito Santo",((W16*0.15)+(X16*0.7))*VLOOKUP(P16,'MunicípiosEstados'!$O$2:$P$79,2,FALSE), O16="Goiás",((W16*0.15)+(X16*0.7))*VLOOKUP(P16,'MunicípiosEstados'!$Q$2:$R$247,2,FALSE), O16="Maranhão",((W16*0.15)+(X16*0.7))*VLOOKUP(P16,'MunicípiosEstados'!$S$2:$T$218,2,FALSE), O16="Mato Grosso",((W16*0.15)+(X16*0.7))*VLOOKUP(P16,'MunicípiosEstados'!$U$2:$V$143,2,FALSE), O16="Mato Grosso do Sul",((W16*0.15)+(X16*0.7))*VLOOKUP(P16,'MunicípiosEstados'!$W$2:$X$80,2,FALSE), O16="Minas Gerais",((W16*0.15)+(X16*0.7))*VLOOKUP(P16,'MunicípiosEstados'!$Y$2:$Z$854,2,FALSE), O16="Pará",((W16*0.15)+(X16*0.7))*VLOOKUP(P16,'MunicípiosEstados'!$AA$2:$AB$145,2,FALSE), O16="Paraíba",((W16*0.15)+(X16*0.7))*VLOOKUP(P16,'MunicípiosEstados'!$AC$2:$AD$224,2,FALSE), O16="Paraná",((W16*0.15)+(X16*0.7))*VLOOKUP(P16,'MunicípiosEstados'!$AE$2:$AF$400,2,FALSE), O16="Pernambuco",((W16*0.15)+(X16*0.7))*VLOOKUP(P16,'MunicípiosEstados'!$AG$2:$AH$186,2,FALSE), O16="Piauí",((W16*0.15)+(X16*0.7))*VLOOKUP(P16,'MunicípiosEstados'!$AI$2:$AJ$225,2,FALSE), O16="Rio Grande do Norte",((W16*0.15)+(X16*0.7))*VLOOKUP(P16,'MunicípiosEstados'!$AK$2:$AL$168,2,FALSE), O16="Rio Grande do Sul",((W16*0.15)+(X16*0.7))*VLOOKUP(P16,'MunicípiosEstados'!$AM$2:$AN$498,2,FALSE), O16="Rio de Janeiro",((W16*0.15)+(X16*0.7))*VLOOKUP(P16,'MunicípiosEstados'!$AO$2:$AP$93,2,FALSE), O16="Rondônia",((W16*0.15)+(X16*0.7))*VLOOKUP(P16,'MunicípiosEstados'!$AQ$2:$AR$53,2,FALSE), O16="Roraima",((W16*0.15)+(X16*0.7))*VLOOKUP(P16,'MunicípiosEstados'!$AS$2:$AT$16,2,FALSE), O16="Santa Catarina",((W16*0.15)+(X16*0.7))*VLOOKUP(P16,'MunicípiosEstados'!$AU$2:$AV$296,2,FALSE), O16="São Paulo",((W16*0.15)+(X16*0.7))*VLOOKUP(P16,'MunicípiosEstados'!$AW$2:$AX$646,2,FALSE), O16="Sergipe",((W16*0.15)+(X16*0.7))*VLOOKUP(P16,'MunicípiosEstados'!$AY$2:$AZ$76,2,FALSE), O16="Tocantins",((W16*0.15)+(X16*0.7))*VLOOKUP(P16,'MunicípiosEstados'!$BA$2:$BB$140,2,FALSE), O16="Exterior",((W16*0.15)+(X16*0.7))*VLOOKUP(P16,'MunicípiosEstados'!$BC$2:$BE$221,3,FALSE),TRUE,0 ) -> 22235.032 | AL16: =AK16+AJ16+AI16+AE16+AD16+AC16+AB16+AA16+Z16+Y16 -> 28635.032 | AN16: Indeferido. A pesquisadora realizou capacitação no exterior no ano de 2025.
A17: =ROW(A17)-1 -> 16 | B17: 45990.056 | C17: maristelacarvalho@idr.pr.gov.br | D17: Não Aprovado | E17: =VLOOKUP(G17,DiretoriaDepart.Coord.!$A$1:$C$72,2,FALSE) -> Pesquisa e Inovação | F17: =VLOOKUP(G17,DiretoriaDepart.Coord.!$A$1:$C$72,3,FALSE) -> Inovação e Comunicação Científica | G17: Fitotecnia e Fisiologia da Produção (Pesquisa) | I17: Soils for Europe: Healthy Soils for a Sustainable Future | J17: Congresso | K17: 1 | L17: Maristela Pereira Carvalho Zanão | M17: Não se aplica | N17: 0 | O17: Exterior | P17: Portugal | Q17: 45907.333 | R17: 45911.708 | S17: Sim | T17: Presencial | U17: Sustentabilidade, Fitotecnia | V17: Evento científico ligado á sustentabilidade, a participação será importante para conhecimento e atualização. Será apresentado em pôster resultados de pesquisa do IDR-Paraná, bem como, participação em palestras, conferências e dialogar com cientistas da área. A experiência adquirida será importante para o desenvolvimento da pesquisa pelo IDR no Paraná. | W17: 16 | X17: 8 | Y17: 1500 | Z17: 0 | AA17: 10000 | AB17: 0 | AC17: 0 | AD17: 0 | AE17: 0 | AF17: Não | AG17: 0 | AH17: Não | AI17: =IF(AF17="Sim",INT((R17-Q17+1))*K17*VLOOKUP(P17,'Tabelas Auxiliares'!$A$1:$C$400,3,FALSE),0) -> 0 | AJ17: =(AG17/10)*7 -> 0 | AK17: =IFS( O17="Acre",((W17*0.15)+(X17*0.7))*VLOOKUP(P17,'MunicípiosEstados'!$A$2:$B$23,2,FALSE), O17="Alagoas",((W17*0.15)+(X17*0.7))*VLOOKUP(P17,'MunicípiosEstados'!$C$2:$D$103,2,FALSE), O17="Amapá",((W17*0.15)+(X17*0.7))*VLOOKUP(P17,'MunicípiosEstados'!$E$2:$F$17,2,FALSE), O17="Amazonas",((W17*0.15)+(X17*0.7))*VLOOKUP(P17,'MunicípiosEstados'!$G$2:$H$63,2,FALSE), O17="Bahia",((W17*0.15)+(X17*0.7))*VLOOKUP(P17,'MunicípiosEstados'!$I$2:$J$418,2,FALSE), O17="Ceará",((W17*0.15)+(X17*0.7))*VLOOKUP(P17,'MunicípiosEstados'!$K$2:$L$185,2,FALSE), O17="Distrito Federal",((W17*0.15)+(X17*0.7))*VLOOKUP(P17,'MunicípiosEstados'!$M$2:$N$2,2,FALSE), O17="Espírito Santo",((W17*0.15)+(X17*0.7))*VLOOKUP(P17,'MunicípiosEstados'!$O$2:$P$79,2,FALSE), O17="Goiás",((W17*0.15)+(X17*0.7))*VLOOKUP(P17,'MunicípiosEstados'!$Q$2:$R$247,2,FALSE), O17="Maranhão",((W17*0.15)+(X17*0.7))*VLOOKUP(P17,'MunicípiosEstados'!$S$2:$T$218,2,FALSE), O17="Mato Grosso",((W17*0.15)+(X17*0.7))*VLOOKUP(P17,'MunicípiosEstados'!$U$2:$V$143,2,FALSE), O17="Mato Grosso do Sul",((W17*0.15)+(X17*0.7))*VLOOKUP(P17,'MunicípiosEstados'!$W$2:$X$80,2,FALSE), O17="Minas Gerais",((W17*0.15)+(X17*0.7))*VLOOKUP(P17,'MunicípiosEstados'!$Y$2:$Z$854,2,FALSE), O17="Pará",((W17*0.15)+(X17*0.7))*VLOOKUP(P17,'MunicípiosEstados'!$AA$2:$AB$145,2,FALSE), O17="Paraíba",((W17*0.15)+(X17*0.7))*VLOOKUP(P17,'MunicípiosEstados'!$AC$2:$AD$224,2,FALSE), O17="Paraná",((W17*0.15)+(X17*0.7))*VLOOKUP(P17,'MunicípiosEstados'!$AE$2:$AF$400,2,FALSE), O17="Pernambuco",((W17*0.15)+(X17*0.7))*VLOOKUP(P17,'MunicípiosEstados'!$AG$2:$AH$186,2,FALSE), O17="Piauí",((W17*0.15)+(X17*0.7))*VLOOKUP(P17,'MunicípiosEstados'!$AI$2:$AJ$225,2,FALSE), O17="Rio Grande do Norte",((W17*0.15)+(X17*0.7))*VLOOKUP(P17,'MunicípiosEstados'!$AK$2:$AL$168,2,FALSE), O17="Rio Grande do Sul",((W17*0.15)+(X17*0.7))*VLOOKUP(P17,'MunicípiosEstados'!$AM$2:$AN$498,2,FALSE), O17="Rio de Janeiro",((W17*0.15)+(X17*0.7))*VLOOKUP(P17,'MunicípiosEstados'!$AO$2:$AP$93,2,FALSE), O17="Rondônia",((W17*0.15)+(X17*0.7))*VLOOKUP(P17,'MunicípiosEstados'!$AQ$2:$AR$53,2,FALSE), O17="Roraima",((W17*0.15)+(X17*0.7))*VLOOKUP(P17,'MunicípiosEstados'!$AS$2:$AT$16,2,FALSE), O17="Santa Catarina",((W17*0.15)+(X17*0.7))*VLOOKUP(P17,'MunicípiosEstados'!$AU$2:$AV$296,2,FALSE), O17="São Paulo",((W17*0.15)+(X17*0.7))*VLOOKUP(P17,'MunicípiosEstados'!$AW$2:$AX$646,2,FALSE), O17="Sergipe",((W17*0.15)+(X17*0.7))*VLOOKUP(P17,'MunicípiosEstados'!$AY$2:$AZ$76,2,FALSE), O17="Tocantins",((W17*0.15)+(X17*0.7))*VLOOKUP(P17,'MunicípiosEstados'!$BA$2:$BB$140,2,FALSE), O17="Exterior",((W17*0.15)+(X17*0.7))*VLOOKUP(P17,'MunicípiosEstados'!$BC$2:$BE$221,3,FALSE),TRUE,0 ) -> 17552.04 | AL17: =AK17+AJ17+AI17+AE17+AD17+AC17+AB17+AA17+Z17+Y17 -> 29052.04 | AN17: Não aprovado
A18: =ROW(A18)-1 -> 17 | B18: 45993.403 | C18: graziela_barbosa@idr.pr.gov.br | D18: Não Aprovado | E18: =VLOOKUP(G18,DiretoriaDepart.Coord.!$A$1:$C$72,2,FALSE) -> Pesquisa e Inovação | F18: =VLOOKUP(G18,DiretoriaDepart.Coord.!$A$1:$C$72,3,FALSE) -> Inovação e Comunicação Científica | G18: Solos e Meio Ambiente (Pesquisa) | I18: Soils for Europe: Healthy Soils for a Sustainable Future | J18: Congresso | K18: 1 | L18: Luiz Antônio Zanão Júnior | M18: Não se aplica | N18: 0 | O18: Exterior | P18: Portugal | Q18: 45907.333 | R18: 45911.708 | S18: Sim | T18: Presencial | U18: Saúde do Solo | V18: Evento científico ligado à ciência do solo, a participação será importante para conhecimento e atualização das novas linhas de pesquisas em solos, será apresentado em pôster resultados de pesquisa do IDR-Paraná, bem como, participação em palestras, conferências e dialogar com cientistas da área. A experiência adquirida será importante para o desenvolvimento da pesquisa na área do solo pelo IDR no Paraná. | W18: 16 | X18: 7 | Y18: 1000 | Z18: 0 | AA18: 10000 | AB18: 0 | AC18: 500 | AD18: 0 | AE18: 0 | AF18: Não | AG18: 0 | AH18: Não | AI18: =IF(AF18="Sim",INT((R18-Q18+1))*K18*VLOOKUP(P18,'Tabelas Auxiliares'!$A$1:$C$400,3,FALSE),0) -> 0 | AJ18: =(AG18/10)*7 -> 0 | AK18: =IFS( O18="Acre",((W18*0.15)+(X18*0.7))*VLOOKUP(P18,'MunicípiosEstados'!$A$2:$B$23,2,FALSE), O18="Alagoas",((W18*0.15)+(X18*0.7))*VLOOKUP(P18,'MunicípiosEstados'!$C$2:$D$103,2,FALSE), O18="Amapá",((W18*0.15)+(X18*0.7))*VLOOKUP(P18,'MunicípiosEstados'!$E$2:$F$17,2,FALSE), O18="Amazonas",((W18*0.15)+(X18*0.7))*VLOOKUP(P18,'MunicípiosEstados'!$G$2:$H$63,2,FALSE), O18="Bahia",((W18*0.15)+(X18*0.7))*VLOOKUP(P18,'MunicípiosEstados'!$I$2:$J$418,2,FALSE), O18="Ceará",((W18*0.15)+(X18*0.7))*VLOOKUP(P18,'MunicípiosEstados'!$K$2:$L$185,2,FALSE), O18="Distrito Federal",((W18*0.15)+(X18*0.7))*VLOOKUP(P18,'MunicípiosEstados'!$M$2:$N$2,2,FALSE), O18="Espírito Santo",((W18*0.15)+(X18*0.7))*VLOOKUP(P18,'MunicípiosEstados'!$O$2:$P$79,2,FALSE), O18="Goiás",((W18*0.15)+(X18*0.7))*VLOOKUP(P18,'MunicípiosEstados'!$Q$2:$R$247,2,FALSE), O18="Maranhão",((W18*0.15)+(X18*0.7))*VLOOKUP(P18,'MunicípiosEstados'!$S$2:$T$218,2,FALSE), O18="Mato Grosso",((W18*0.15)+(X18*0.7))*VLOOKUP(P18,'MunicípiosEstados'!$U$2:$V$143,2,FALSE), O18="Mato Grosso do Sul",((W18*0.15)+(X18*0.7))*VLOOKUP(P18,'MunicípiosEstados'!$W$2:$X$80,2,FALSE), O18="Minas Gerais",((W18*0.15)+(X18*0.7))*VLOOKUP(P18,'MunicípiosEstados'!$Y$2:$Z$854,2,FALSE), O18="Pará",((W18*0.15)+(X18*0.7))*VLOOKUP(P18,'MunicípiosEstados'!$AA$2:$AB$145,2,FALSE), O18="Paraíba",((W18*0.15)+(X18*0.7))*VLOOKUP(P18,'MunicípiosEstados'!$AC$2:$AD$224,2,FALSE), O18="Paraná",((W18*0.15)+(X18*0.7))*VLOOKUP(P18,'MunicípiosEstados'!$AE$2:$AF$400,2,FALSE), O18="Pernambuco",((W18*0.15)+(X18*0.7))*VLOOKUP(P18,'MunicípiosEstados'!$AG$2:$AH$186,2,FALSE), O18="Piauí",((W18*0.15)+(X18*0.7))*VLOOKUP(P18,'MunicípiosEstados'!$AI$2:$AJ$225,2,FALSE), O18="Rio Grande do Norte",((W18*0.15)+(X18*0.7))*VLOOKUP(P18,'MunicípiosEstados'!$AK$2:$AL$168,2,FALSE), O18="Rio Grande do Sul",((W18*0.15)+(X18*0.7))*VLOOKUP(P18,'MunicípiosEstados'!$AM$2:$AN$498,2,FALSE), O18="Rio de Janeiro",((W18*0.15)+(X18*0.7))*VLOOKUP(P18,'MunicípiosEstados'!$AO$2:$AP$93,2,FALSE), O18="Rondônia",((W18*0.15)+(X18*0.7))*VLOOKUP(P18,'MunicípiosEstados'!$AQ$2:$AR$53,2,FALSE), O18="Roraima",((W18*0.15)+(X18*0.7))*VLOOKUP(P18,'MunicípiosEstados'!$AS$2:$AT$16,2,FALSE), O18="Santa Catarina",((W18*0.15)+(X18*0.7))*VLOOKUP(P18,'MunicípiosEstados'!$AU$2:$AV$296,2,FALSE), O18="São Paulo",((W18*0.15)+(X18*0.7))*VLOOKUP(P18,'MunicípiosEstados'!$AW$2:$AX$646,2,FALSE), O18="Sergipe",((W18*0.15)+(X18*0.7))*VLOOKUP(P18,'MunicípiosEstados'!$AY$2:$AZ$76,2,FALSE), O18="Tocantins",((W18*0.15)+(X18*0.7))*VLOOKUP(P18,'MunicípiosEstados'!$BA$2:$BB$140,2,FALSE), O18="Exterior",((W18*0.15)+(X18*0.7))*VLOOKUP(P18,'MunicípiosEstados'!$BC$2:$BE$221,3,FALSE),TRUE,0 ) -> 16016.237 | AL18: =AK18+AJ18+AI18+AE18+AD18+AC18+AB18+AA18+Z18+Y18 -> 27516.236 | AN18: Não aprovado com recursos do IDR
A19: =ROW(A19)-1 -> 18 | B19: 45993.411 | C19: graziela_barbosa@idr.pr.gov.br | D19: Aprovado | E19: =VLOOKUP(G19,DiretoriaDepart.Coord.!$A$1:$C$72,2,FALSE) -> Pesquisa e Inovação | F19: =VLOOKUP(G19,DiretoriaDepart.Coord.!$A$1:$C$72,3,FALSE) -> Inovação e Comunicação Científica | G19: Solos e Meio Ambiente (Pesquisa) | I19: Canvas (Crop, Agronomic, Environmental, & Soil Sciences) | J19: Congresso | K19: 1 | L19: Luciano Grillo Gil | M19: Não se aplica | N19: 0 | O19: Exterior | P19: Estados Unidos | Q19: 45961.333 | R19: 45966.708 | S19: Sim | T19: Presencial | U19: Congresso que aborda ciência do solo com culturas | V19: Evento científico internacional ligado á ciência do solo, a participação será importante para conhecimento e atualização das novas linhas de pesquisas em solos, será apresentado em pôster resultados de pesquisa do IDR-Paraná, bem como, participação em palestras, conferências e dialogar com cientistas da área. A experiência adquirida será importante para o desenvolvimento da pesquisa na área do solo pelo IDR no Paraná. | W19: 0 | X19: 0 | Y19: 0 | Z19: 0 | AA19: 0 | AB19: 0 | AC19: 0 | AD19: 0 | AE19: 0 | AF19: Não | AG19: 0 | AH19: Não | AI19: =IF(AF19="Sim",INT((R19-Q19+1))*K19*VLOOKUP(P19,'Tabelas Auxiliares'!$A$1:$C$400,3,FALSE),0) -> 0 | AJ19: =(AG19/10)*7 -> 0 | AK19: =IFS( O19="Acre",((W19*0.15)+(X19*0.7))*VLOOKUP(P19,'MunicípiosEstados'!$A$2:$B$23,2,FALSE), O19="Alagoas",((W19*0.15)+(X19*0.7))*VLOOKUP(P19,'MunicípiosEstados'!$C$2:$D$103,2,FALSE), O19="Amapá",((W19*0.15)+(X19*0.7))*VLOOKUP(P19,'MunicípiosEstados'!$E$2:$F$17,2,FALSE), O19="Amazonas",((W19*0.15)+(X19*0.7))*VLOOKUP(P19,'MunicípiosEstados'!$G$2:$H$63,2,FALSE), O19="Bahia",((W19*0.15)+(X19*0.7))*VLOOKUP(P19,'MunicípiosEstados'!$I$2:$J$418,2,FALSE), O19="Ceará",((W19*0.15)+(X19*0.7))*VLOOKUP(P19,'MunicípiosEstados'!$K$2:$L$185,2,FALSE), O19="Distrito Federal",((W19*0.15)+(X19*0.7))*VLOOKUP(P19,'MunicípiosEstados'!$M$2:$N$2,2,FALSE), O19="Espírito Santo",((W19*0.15)+(X19*0.7))*VLOOKUP(P19,'MunicípiosEstados'!$O$2:$P$79,2,FALSE), O19="Goiás",((W19*0.15)+(X19*0.7))*VLOOKUP(P19,'MunicípiosEstados'!$Q$2:$R$247,2,FALSE), O19="Maranhão",((W19*0.15)+(X19*0.7))*VLOOKUP(P19,'MunicípiosEstados'!$S$2:$T$218,2,FALSE), O19="Mato Grosso",((W19*0.15)+(X19*0.7))*VLOOKUP(P19,'MunicípiosEstados'!$U$2:$V$143,2,FALSE), O19="Mato Grosso do Sul",((W19*0.15)+(X19*0.7))*VLOOKUP(P19,'MunicípiosEstados'!$W$2:$X$80,2,FALSE), O19="Minas Gerais",((W19*0.15)+(X19*0.7))*VLOOKUP(P19,'MunicípiosEstados'!$Y$2:$Z$854,2,FALSE), O19="Pará",((W19*0.15)+(X19*0.7))*VLOOKUP(P19,'MunicípiosEstados'!$AA$2:$AB$145,2,FALSE), O19="Paraíba",((W19*0.15)+(X19*0.7))*VLOOKUP(P19,'MunicípiosEstados'!$AC$2:$AD$224,2,FALSE), O19="Paraná",((W19*0.15)+(X19*0.7))*VLOOKUP(P19,'MunicípiosEstados'!$AE$2:$AF$400,2,FALSE), O19="Pernambuco",((W19*0.15)+(X19*0.7))*VLOOKUP(P19,'MunicípiosEstados'!$AG$2:$AH$186,2,FALSE), O19="Piauí",((W19*0.15)+(X19*0.7))*VLOOKUP(P19,'MunicípiosEstados'!$AI$2:$AJ$225,2,FALSE), O19="Rio Grande do Norte",((W19*0.15)+(X19*0.7))*VLOOKUP(P19,'MunicípiosEstados'!$AK$2:$AL$168,2,FALSE), O19="Rio Grande do Sul",((W19*0.15)+(X19*0.7))*VLOOKUP(P19,'MunicípiosEstados'!$AM$2:$AN$498,2,FALSE), O19="Rio de Janeiro",((W19*0.15)+(X19*0.7))*VLOOKUP(P19,'MunicípiosEstados'!$AO$2:$AP$93,2,FALSE), O19="Rondônia",((W19*0.15)+(X19*0.7))*VLOOKUP(P19,'MunicípiosEstados'!$AQ$2:$AR$53,2,FALSE), O19="Roraima",((W19*0.15)+(X19*0.7))*VLOOKUP(P19,'MunicípiosEstados'!$AS$2:$AT$16,2,FALSE), O19="Santa Catarina",((W19*0.15)+(X19*0.7))*VLOOKUP(P19,'MunicípiosEstados'!$AU$2:$AV$296,2,FALSE), O19="São Paulo",((W19*0.15)+(X19*0.7))*VLOOKUP(P19,'MunicípiosEstados'!$AW$2:$AX$646,2,FALSE), O19="Sergipe",((W19*0.15)+(X19*0.7))*VLOOKUP(P19,'MunicípiosEstados'!$AY$2:$AZ$76,2,FALSE), O19="Tocantins",((W19*0.15)+(X19*0.7))*VLOOKUP(P19,'MunicípiosEstados'!$BA$2:$BB$140,2,FALSE), O19="Exterior",((W19*0.15)+(X19*0.7))*VLOOKUP(P19,'MunicípiosEstados'!$BC$2:$BE$221,3,FALSE),TRUE,0 ) -> 0 | AL19: =AK19+AJ19+AI19+AE19+AD19+AC19+AB19+AA19+Z19+Y19 -> 0 | AN19: Aprovado com utilização de recursos externos.
A20: =ROW(A20)-1 -> 19 | B20: 45994.666 | C20: aledetoni@idr.pr.gov.br | D20: A aprovar | E20: =VLOOKUP(G20,DiretoriaDepart.Coord.!$A$1:$C$72,2,FALSE) -> Pesquisa e Inovação | F20: =VLOOKUP(G20,DiretoriaDepart.Coord.!$A$1:$C$72,3,FALSE) -> Inovação e Comunicação Científica | G20: Fitotecnia e Fisiologia da Produção (Pesquisa) | I20: Visita técnica para Itália | J20: Visita Técnica | K20: 2 | M20: Fundação Araucária | N20: 5 | O20: Exterior | P20: Itália | Q20: 45793.333 | R20: 45807.75 | S20: Não | T20: Presencial | U20: Interconexão em CT&I entre o NAPI Inova Vitis e a Università degli Studi di Milano, Itália | V20: A visita técnica está alinhada com as diretrizes do Programa Interconexões Paraná – Chamada Pública 03/2025, promovendo a integração entre ciência, tecnologia, inovação e o setor produtivo, uma vez que a Itália é um dos principais e mais tradicionais países produtoras de uvas no mundo, sobretudo sob o sistema de cultivo protegido. A cooperação internacional com a Università degli Studi di Milano, por meio da parceria com a Profa. Dra. Cássia da Silva Linge, representa uma oportunidade singular para o intercâmbio de conhecimento técnico-científico e a transferência de tecnologias agrícolas sustentáveis já consolidadas na Europa. Através da visita técnica será possível promover a capacitação técnica das pesquisadoras do IDR-Paraná, a construção de redes colaborativas duradouras e a incorporação de soluções tecnológicas adaptadas à realidade regional. Além de estreitar os laços de CT&I entre as Instituições. Ao promover a formação de recursos humanos qualificados e a articulação internacional, a proposta contribui diretamente para o fortalecimento do ecossistema de inovação agrícola do Paraná, elevando o estado a uma posição de referência em viticultura sustentável e tecnologicamente avançada. | W20: 0 | X20: 0 | Y20: 0 | Z20: 0 | AA20: 0 | AB20: 0 | AC20: 0 | AD20: 0 | AE20: 0 | AF20: Não | AG20: 00 | AH20: Não | AI20: =IF(AF20="Sim",INT((R20-Q20+1))*K20*VLOOKUP(P20,'Tabelas Auxiliares'!$A$1:$C$400,3,FALSE),0) -> 0 | AJ20: =(AG20/10)*7 -> 0 | AK20: =IFS( O20="Acre",((W20*0.15)+(X20*0.7))*VLOOKUP(P20,'MunicípiosEstados'!$A$2:$B$23,2,FALSE), O20="Alagoas",((W20*0.15)+(X20*0.7))*VLOOKUP(P20,'MunicípiosEstados'!$C$2:$D$103,2,FALSE), O20="Amapá",((W20*0.15)+(X20*0.7))*VLOOKUP(P20,'MunicípiosEstados'!$E$2:$F$17,2,FALSE), O20="Amazonas",((W20*0.15)+(X20*0.7))*VLOOKUP(P20,'MunicípiosEstados'!$G$2:$H$63,2,FALSE), O20="Bahia",((W20*0.15)+(X20*0.7))*VLOOKUP(P20,'MunicípiosEstados'!$I$2:$J$418,2,FALSE), O20="Ceará",((W20*0.15)+(X20*0.7))*VLOOKUP(P20,'MunicípiosEstados'!$K$2:$L$185,2,FALSE), O20="Distrito Federal",((W20*0.15)+(X20*0.7))*VLOOKUP(P20,'MunicípiosEstados'!$M$2:$N$2,2,FALSE), O20="Espírito Santo",((W20*0.15)+(X20*0.7))*VLOOKUP(P20,'MunicípiosEstados'!$O$2:$P$79,2,FALSE), O20="Goiás",((W20*0.15)+(X20*0.7))*VLOOKUP(P20,'MunicípiosEstados'!$Q$2:$R$247,2,FALSE), O20="Maranhão",((W20*0.15)+(X20*0.7))*VLOOKUP(P20,'MunicípiosEstados'!$S$2:$T$218,2,FALSE), O20="Mato Grosso",((W20*0.15)+(X20*0.7))*VLOOKUP(P20,'MunicípiosEstados'!$U$2:$V$143,2,FALSE), O20="Mato Grosso do Sul",((W20*0.15)+(X20*0.7))*VLOOKUP(P20,'MunicípiosEstados'!$W$2:$X$80,2,FALSE), O20="Minas Gerais",((W20*0.15)+(X20*0.7))*VLOOKUP(P20,'MunicípiosEstados'!$Y$2:$Z$854,2,FALSE), O20="Pará",((W20*0.15)+(X20*0.7))*VLOOKUP(P20,'MunicípiosEstados'!$AA$2:$AB$145,2,FALSE), O20="Paraíba",((W20*0.15)+(X20*0.7))*VLOOKUP(P20,'MunicípiosEstados'!$AC$2:$AD$224,2,FALSE), O20="Paraná",((W20*0.15)+(X20*0.7))*VLOOKUP(P20,'MunicípiosEstados'!$AE$2:$AF$400,2,FALSE), O20="Pernambuco",((W20*0.15)+(X20*0.7))*VLOOKUP(P20,'MunicípiosEstados'!$AG$2:$AH$186,2,FALSE), O20="Piauí",((W20*0.15)+(X20*0.7))*VLOOKUP(P20,'MunicípiosEstados'!$AI$2:$AJ$225,2,FALSE), O20="Rio Grande do Norte",((W20*0.15)+(X20*0.7))*VLOOKUP(P20,'MunicípiosEstados'!$AK$2:$AL$168,2,FALSE), O20="Rio Grande do Sul",((W20*0.15)+(X20*0.7))*VLOOKUP(P20,'MunicípiosEstados'!$AM$2:$AN$498,2,FALSE), O20="Rio de Janeiro",((W20*0.15)+(X20*0.7))*VLOOKUP(P20,'MunicípiosEstados'!$AO$2:$AP$93,2,FALSE), O20="Rondônia",((W20*0.15)+(X20*0.7))*VLOOKUP(P20,'MunicípiosEstados'!$AQ$2:$AR$53,2,FALSE), O20="Roraima",((W20*0.15)+(X20*0.7))*VLOOKUP(P20,'MunicípiosEstados'!$AS$2:$AT$16,2,FALSE), O20="Santa Catarina",((W20*0.15)+(X20*0.7))*VLOOKUP(P20,'MunicípiosEstados'!$AU$2:$AV$296,2,FALSE), O20="São Paulo",((W20*0.15)+(X20*0.7))*VLOOKUP(P20,'MunicípiosEstados'!$AW$2:$AX$646,2,FALSE), O20="Sergipe",((W20*0.15)+(X20*0.7))*VLOOKUP(P20,'MunicípiosEstados'!$AY$2:$AZ$76,2,FALSE), O20="Tocantins",((W20*0.15)+(X20*0.7))*VLOOKUP(P20,'MunicípiosEstados'!$BA$2:$BB$140,2,FALSE), O20="Exterior",((W20*0.15)+(X20*0.7))*VLOOKUP(P20,'MunicípiosEstados'!$BC$2:$BE$221,3,FALSE),TRUE,0 ) -> 0 | AL20: =AK20+AJ20+AI20+AE20+AD20+AC20+AB20+AA20+Z20+Y20 -> 0
A21: =ROW(A21)-1 -> 20 | B21: 45999.659 | C21: tpellini@idr.pr.gov.br | D21: A aprovar | E21: =VLOOKUP(G21,DiretoriaDepart.Coord.!$A$1:$C$72,2,FALSE) -> Pesquisa e Inovação | F21: =VLOOKUP(G21,DiretoriaDepart.Coord.!$A$1:$C$72,3,FALSE) -> Pesquisa e Capacitação | G21: Socioeconomia e Métodos Quantitativos (Pesquisa) | I21: Missão técnica aos Laboratórios Vivos projeto GRANULAR do International Centre for Advanced Mediterranean Agronomic Studies (CIHEAM). | J21: Visita Técnica | K21: 3 | L21: Simone Grisa, Norma Kiyota e Moacir Roberto Darolt. | M21: International Centre for Advanced Mediterranean Agronomic Studies (CIHEAM). | N21: 1 | O21: Exterior | P21: França | Q21: 45795.333 | R21: 45802.708 | S21: Não | T21: Presencial | U21: Laboratórios vivos (Living Labs) aplicados ao meio rural. | V21: O objetivo da missão ao CIHEAM é conhecer concepção, operação e experiência de 'Living Labs" consolidados para contribuir no desenvolvimento das atividades realizadas nas diferentes vitrines tecnológicas de agroecologia do IDR-Paraná para que estas possam ampliar sua função como "laboratórios vivos". A capacitação depende da aprovação de apoio da Itaipu Binacional para os gastos de transporte e translado dos participantes através de convênio já existente. | W21: 21 | X21: 7 | Y21: 0 | Z21: 0 | AA21: 27000 | AB21: 2250 | AC21: 1500 | AD21: 0 | AE21: 0 | AF21: Não | AG21: 0 | AH21: Sim | AI21: =IF(AF21="Sim",INT((R21-Q21+1))*K21*VLOOKUP(P21,'Tabelas Auxiliares'!$A$1:$C$400,3,FALSE),0) -> 0 | AJ21: =(AG21/10)*7 -> 0 | AK21: =IFS( O21="Acre",((W21*0.15)+(X21*0.7))*VLOOKUP(P21,'MunicípiosEstados'!$A$2:$B$23,2,FALSE), O21="Alagoas",((W21*0.15)+(X21*0.7))*VLOOKUP(P21,'MunicípiosEstados'!$C$2:$D$103,2,FALSE), O21="Amapá",((W21*0.15)+(X21*0.7))*VLOOKUP(P21,'MunicípiosEstados'!$E$2:$F$17,2,FALSE), O21="Amazonas",((W21*0.15)+(X21*0.7))*VLOOKUP(P21,'MunicípiosEstados'!$G$2:$H$63,2,FALSE), O21="Bahia",((W21*0.15)+(X21*0.7))*VLOOKUP(P21,'MunicípiosEstados'!$I$2:$J$418,2,FALSE), O21="Ceará",((W21*0.15)+(X21*0.7))*VLOOKUP(P21,'MunicípiosEstados'!$K$2:$L$185,2,FALSE), O21="Distrito Federal",((W21*0.15)+(X21*0.7))*VLOOKUP(P21,'MunicípiosEstados'!$M$2:$N$2,2,FALSE), O21="Espírito Santo",((W21*0.15)+(X21*0.7))*VLOOKUP(P21,'MunicípiosEstados'!$O$2:$P$79,2,FALSE), O21="Goiás",((W21*0.15)+(X21*0.7))*VLOOKUP(P21,'MunicípiosEstados'!$Q$2:$R$247,2,FALSE), O21="Maranhão",((W21*0.15)+(X21*0.7))*VLOOKUP(P21,'MunicípiosEstados'!$S$2:$T$218,2,FALSE), O21="Mato Grosso",((W21*0.15)+(X21*0.7))*VLOOKUP(P21,'MunicípiosEstados'!$U$2:$V$143,2,FALSE), O21="Mato Grosso do Sul",((W21*0.15)+(X21*0.7))*VLOOKUP(P21,'MunicípiosEstados'!$W$2:$X$80,2,FALSE), O21="Minas Gerais",((W21*0.15)+(X21*0.7))*VLOOKUP(P21,'MunicípiosEstados'!$Y$2:$Z$854,2,FALSE), O21="Pará",((W21*0.15)+(X21*0.7))*VLOOKUP(P21,'MunicípiosEstados'!$AA$2:$AB$145,2,FALSE), O21="Paraíba",((W21*0.15)+(X21*0.7))*VLOOKUP(P21,'MunicípiosEstados'!$AC$2:$AD$224,2,FALSE), O21="Paraná",((W21*0.15)+(X21*0.7))*VLOOKUP(P21,'MunicípiosEstados'!$AE$2:$AF$400,2,FALSE), O21="Pernambuco",((W21*0.15)+(X21*0.7))*VLOOKUP(P21,'MunicípiosEstados'!$AG$2:$AH$186,2,FALSE), O21="Piauí",((W21*0.15)+(X21*0.7))*VLOOKUP(P21,'MunicípiosEstados'!$AI$2:$AJ$225,2,FALSE), O21="Rio Grande do Norte",((W21*0.15)+(X21*0.7))*VLOOKUP(P21,'MunicípiosEstados'!$AK$2:$AL$168,2,FALSE), O21="Rio Grande do Sul",((W21*0.15)+(X21*0.7))*VLOOKUP(P21,'MunicípiosEstados'!$AM$2:$AN$498,2,FALSE), O21="Rio de Janeiro",((W21*0.15)+(X21*0.7))*VLOOKUP(P21,'MunicípiosEstados'!$AO$2:$AP$93,2,FALSE), O21="Rondônia",((W21*0.15)+(X21*0.7))*VLOOKUP(P21,'MunicípiosEstados'!$AQ$2:$AR$53,2,FALSE), O21="Roraima",((W21*0.15)+(X21*0.7))*VLOOKUP(P21,'MunicípiosEstados'!$AS$2:$AT$16,2,FALSE), O21="Santa Catarina",((W21*0.15)+(X21*0.7))*VLOOKUP(P21,'MunicípiosEstados'!$AU$2:$AV$296,2,FALSE), O21="São Paulo",((W21*0.15)+(X21*0.7))*VLOOKUP(P21,'MunicípiosEstados'!$AW$2:$AX$646,2,FALSE), O21="Sergipe",((W21*0.15)+(X21*0.7))*VLOOKUP(P21,'MunicípiosEstados'!$AY$2:$AZ$76,2,FALSE), O21="Tocantins",((W21*0.15)+(X21*0.7))*VLOOKUP(P21,'MunicípiosEstados'!$BA$2:$BB$140,2,FALSE), O21="Exterior",((W21*0.15)+(X21*0.7))*VLOOKUP(P21,'MunicípiosEstados'!$BC$2:$BE$221,3,FALSE),TRUE,0 ) -> 17661.74 | AL21: =AK21+AJ21+AI21+AE21+AD21+AC21+AB21+AA21+Z21+Y21 -> 48411.74
A22: =ROW(A22)-1 -> 21 | B22: 45999.669 | C22: tpellini@idr.pr.gov.br | D22: A aprovar | E22: =VLOOKUP(G22,DiretoriaDepart.Coord.!$A$1:$C$72,2,FALSE) -> Pesquisa e Inovação | F22: =VLOOKUP(G22,DiretoriaDepart.Coord.!$A$1:$C$72,3,FALSE) -> Pesquisa e Capacitação | G22: Socioeconomia e Métodos Quantitativos (Pesquisa) | I22: XI Congresso Latinoamericano de Agroecologia. | J22: Congresso | K22: 1 | L22: Moacir Roberto Darolt | M22: Sociedad Científica Latinoamericana de Agroecologia (SOCLA) | N22: 400 | O22: Exterior | P22: Chile | Q22: 45986.333 | R22: 45988.75 | S22: Sim | T22: Presencial | U22: Agroecologia. | V22: Apresentar trabalhos realizados na temática da Agroecologia no IDR-Paraná, obter atualização sobre o tema e estabelecer rede de intercâmbio técnico. | W22: 8 | X22: 4 | Y22: 600 | Z22: 0 | AA22: 2000 | AB22: 0 | AC22: 500 | AD22: 0 | AE22: 0 | AF22: Não | AG22: 0 | AH22: Não | AI22: =IF(AF22="Sim",INT((R22-Q22+1))*K22*VLOOKUP(P22,'Tabelas Auxiliares'!$A$1:$C$400,3,FALSE),0) -> 0 | AJ22: =(AG22/10)*7 -> 0 | AK22: =IFS( O22="Acre",((W22*0.15)+(X22*0.7))*VLOOKUP(P22,'MunicípiosEstados'!$A$2:$B$23,2,FALSE), O22="Alagoas",((W22*0.15)+(X22*0.7))*VLOOKUP(P22,'MunicípiosEstados'!$C$2:$D$103,2,FALSE), O22="Amapá",((W22*0.15)+(X22*0.7))*VLOOKUP(P22,'MunicípiosEstados'!$E$2:$F$17,2,FALSE), O22="Amazonas",((W22*0.15)+(X22*0.7))*VLOOKUP(P22,'MunicípiosEstados'!$G$2:$H$63,2,FALSE), O22="Bahia",((W22*0.15)+(X22*0.7))*VLOOKUP(P22,'MunicípiosEstados'!$I$2:$J$418,2,FALSE), O22="Ceará",((W22*0.15)+(X22*0.7))*VLOOKUP(P22,'MunicípiosEstados'!$K$2:$L$185,2,FALSE), O22="Distrito Federal",((W22*0.15)+(X22*0.7))*VLOOKUP(P22,'MunicípiosEstados'!$M$2:$N$2,2,FALSE), O22="Espírito Santo",((W22*0.15)+(X22*0.7))*VLOOKUP(P22,'MunicípiosEstados'!$O$2:$P$79,2,FALSE), O22="Goiás",((W22*0.15)+(X22*0.7))*VLOOKUP(P22,'MunicípiosEstados'!$Q$2:$R$247,2,FALSE), O22="Maranhão",((W22*0.15)+(X22*0.7))*VLOOKUP(P22,'MunicípiosEstados'!$S$2:$T$218,2,FALSE), O22="Mato Grosso",((W22*0.15)+(X22*0.7))*VLOOKUP(P22,'MunicípiosEstados'!$U$2:$V$143,2,FALSE), O22="Mato Grosso do Sul",((W22*0.15)+(X22*0.7))*VLOOKUP(P22,'MunicípiosEstados'!$W$2:$X$80,2,FALSE), O22="Minas Gerais",((W22*0.15)+(X22*0.7))*VLOOKUP(P22,'MunicípiosEstados'!$Y$2:$Z$854,2,FALSE), O22="Pará",((W22*0.15)+(X22*0.7))*VLOOKUP(P22,'MunicípiosEstados'!$AA$2:$AB$145,2,FALSE), O22="Paraíba",((W22*0.15)+(X22*0.7))*VLOOKUP(P22,'MunicípiosEstados'!$AC$2:$AD$224,2,FALSE), O22="Paraná",((W22*0.15)+(X22*0.7))*VLOOKUP(P22,'MunicípiosEstados'!$AE$2:$AF$400,2,FALSE), O22="Pernambuco",((W22*0.15)+(X22*0.7))*VLOOKUP(P22,'MunicípiosEstados'!$AG$2:$AH$186,2,FALSE), O22="Piauí",((W22*0.15)+(X22*0.7))*VLOOKUP(P22,'MunicípiosEstados'!$AI$2:$AJ$225,2,FALSE), O22="Rio Grande do Norte",((W22*0.15)+(X22*0.7))*VLOOKUP(P22,'MunicípiosEstados'!$AK$2:$AL$168,2,FALSE), O22="Rio Grande do Sul",((W22*0.15)+(X22*0.7))*VLOOKUP(P22,'MunicípiosEstados'!$AM$2:$AN$498,2,FALSE), O22="Rio de Janeiro",((W22*0.15)+(X22*0.7))*VLOOKUP(P22,'MunicípiosEstados'!$AO$2:$AP$93,2,FALSE), O22="Rondônia",((W22*0.15)+(X22*0.7))*VLOOKUP(P22,'MunicípiosEstados'!$AQ$2:$AR$53,2,FALSE), O22="Roraima",((W22*0.15)+(X22*0.7))*VLOOKUP(P22,'MunicípiosEstados'!$AS$2:$AT$16,2,FALSE), O22="Santa Catarina",((W22*0.15)+(X22*0.7))*VLOOKUP(P22,'MunicípiosEstados'!$AU$2:$AV$296,2,FALSE), O22="São Paulo",((W22*0.15)+(X22*0.7))*VLOOKUP(P22,'MunicípiosEstados'!$AW$2:$AX$646,2,FALSE), O22="Sergipe",((W22*0.15)+(X22*0.7))*VLOOKUP(P22,'MunicípiosEstados'!$AY$2:$AZ$76,2,FALSE), O22="Tocantins",((W22*0.15)+(X22*0.7))*VLOOKUP(P22,'MunicípiosEstados'!$BA$2:$BB$140,2,FALSE), O22="Exterior",((W22*0.15)+(X22*0.7))*VLOOKUP(P22,'MunicípiosEstados'!$BC$2:$BE$221,3,FALSE),TRUE,0 ) -> 6491.98 | AL22: =AK22+AJ22+AI22+AE22+AD22+AC22+AB22+AA22+Z22+Y22 -> 9591.98
A23: =ROW(A23)-1 -> 22 | B23: 45999.687 | C23: soler@idr.pr.gov.br | D23: A aprovar | E23: =VLOOKUP(G23,DiretoriaDepart.Coord.!$A$1:$C$72,2,FALSE) -> Pesquisa e Inovação | F23: =VLOOKUP(G23,DiretoriaDepart.Coord.!$A$1:$C$72,3,FALSE) -> Inovação e Comunicação Científica | G23: Agrometereologia (Pesquisa) | I23: The AI Developer Conference | J23: Conferência | K23: 1 | L23: Luciano Soler | M23: Não se aplica | N23: 1000 | O23: Exterior | P23: Estados Unidos | Q23: 45775.333 | R23: 45776.833 | S23: Sim | T23: Presencial | U23: Conferência para desenvolvedores de sistemas de Inteligência Artificial | V23: Essa conferência reúne os maiores nomes do desenvolvimento em Inteligência Artificial do mundo, participar desta capacitação é uma ação estratégica para garantir que o IDR-Paraná permaneça protagonista na inovação agrícola. O conhecimento em IA Generativa e Agêntica permitirá ao Instituto desenvolver soluções internas, reduzir dependência tecnológica e aumentar a eficiência da extensão rural sem ampliar custos operacionais. Trata-se de um investimento direto na soberania digital da Instituição, na proteção da nossa propriedade intelectual e na modernização dos serviços oferecidos ao produtor. Não acompanhar esse movimento coloca o Instituto em desvantagem competitiva frente às soluções privadas que já estão se consolidando. | W23: 8 | X23: 5 | Y23: 7500 | Z23: 100 | AA23: 10000 | AB23: 0 | AC23: 1000 | AD23: 0 | AE23: 0 | AF23: Não | AG23: 0 | AH23: Não | AI23: =IF(AF23="Sim",INT((R23-Q23+1))*K23*VLOOKUP(P23,'Tabelas Auxiliares'!$A$1:$C$400,3,FALSE),0) -> 0 | AJ23: =(AG23/10)*7 -> 0 | AK23: =IFS( O23="Acre",((W23*0.15)+(X23*0.7))*VLOOKUP(P23,'MunicípiosEstados'!$A$2:$B$23,2,FALSE), O23="Alagoas",((W23*0.15)+(X23*0.7))*VLOOKUP(P23,'MunicípiosEstados'!$C$2:$D$103,2,FALSE), O23="Amapá",((W23*0.15)+(X23*0.7))*VLOOKUP(P23,'MunicípiosEstados'!$E$2:$F$17,2,FALSE), O23="Amazonas",((W23*0.15)+(X23*0.7))*VLOOKUP(P23,'MunicípiosEstados'!$G$2:$H$63,2,FALSE), O23="Bahia",((W23*0.15)+(X23*0.7))*VLOOKUP(P23,'MunicípiosEstados'!$I$2:$J$418,2,FALSE), O23="Ceará",((W23*0.15)+(X23*0.7))*VLOOKUP(P23,'MunicípiosEstados'!$K$2:$L$185,2,FALSE), O23="Distrito Federal",((W23*0.15)+(X23*0.7))*VLOOKUP(P23,'MunicípiosEstados'!$M$2:$N$2,2,FALSE), O23="Espírito Santo",((W23*0.15)+(X23*0.7))*VLOOKUP(P23,'MunicípiosEstados'!$O$2:$P$79,2,FALSE), O23="Goiás",((W23*0.15)+(X23*0.7))*VLOOKUP(P23,'MunicípiosEstados'!$Q$2:$R$247,2,FALSE), O23="Maranhão",((W23*0.15)+(X23*0.7))*VLOOKUP(P23,'MunicípiosEstados'!$S$2:$T$218,2,FALSE), O23="Mato Grosso",((W23*0.15)+(X23*0.7))*VLOOKUP(P23,'MunicípiosEstados'!$U$2:$V$143,2,FALSE), O23="Mato Grosso do Sul",((W23*0.15)+(X23*0.7))*VLOOKUP(P23,'MunicípiosEstados'!$W$2:$X$80,2,FALSE), O23="Minas Gerais",((W23*0.15)+(X23*0.7))*VLOOKUP(P23,'MunicípiosEstados'!$Y$2:$Z$854,2,FALSE), O23="Pará",((W23*0.15)+(X23*0.7))*VLOOKUP(P23,'MunicípiosEstados'!$AA$2:$AB$145,2,FALSE), O23="Paraíba",((W23*0.15)+(X23*0.7))*VLOOKUP(P23,'MunicípiosEstados'!$AC$2:$AD$224,2,FALSE), O23="Paraná",((W23*0.15)+(X23*0.7))*VLOOKUP(P23,'MunicípiosEstados'!$AE$2:$AF$400,2,FALSE), O23="Pernambuco",((W23*0.15)+(X23*0.7))*VLOOKUP(P23,'MunicípiosEstados'!$AG$2:$AH$186,2,FALSE), O23="Piauí",((W23*0.15)+(X23*0.7))*VLOOKUP(P23,'MunicípiosEstados'!$AI$2:$AJ$225,2,FALSE), O23="Rio Grande do Norte",((W23*0.15)+(X23*0.7))*VLOOKUP(P23,'MunicípiosEstados'!$AK$2:$AL$168,2,FALSE), O23="Rio Grande do Sul",((W23*0.15)+(X23*0.7))*VLOOKUP(P23,'MunicípiosEstados'!$AM$2:$AN$498,2,FALSE), O23="Rio de Janeiro",((W23*0.15)+(X23*0.7))*VLOOKUP(P23,'MunicípiosEstados'!$AO$2:$AP$93,2,FALSE), O23="Rondônia",((W23*0.15)+(X23*0.7))*VLOOKUP(P23,'MunicípiosEstados'!$AQ$2:$AR$53,2,FALSE), O23="Roraima",((W23*0.15)+(X23*0.7))*VLOOKUP(P23,'MunicípiosEstados'!$AS$2:$AT$16,2,FALSE), O23="Santa Catarina",((W23*0.15)+(X23*0.7))*VLOOKUP(P23,'MunicípiosEstados'!$AU$2:$AV$296,2,FALSE), O23="São Paulo",((W23*0.15)+(X23*0.7))*VLOOKUP(P23,'MunicípiosEstados'!$AW$2:$AX$646,2,FALSE), O23="Sergipe",((W23*0.15)+(X23*0.7))*VLOOKUP(P23,'MunicípiosEstados'!$AY$2:$AZ$76,2,FALSE), O23="Tocantins",((W23*0.15)+(X23*0.7))*VLOOKUP(P23,'MunicípiosEstados'!$BA$2:$BB$140,2,FALSE), O23="Exterior",((W23*0.15)+(X23*0.7))*VLOOKUP(P23,'MunicípiosEstados'!$BC$2:$BE$221,3,FALSE),TRUE,0 ) -> 9913.992 | AL23: =AK23+AJ23+AI23+AE23+AD23+AC23+AB23+AA23+Z23+Y23 -> 28513.992
A24: =ROW(A24)-1 -> 23 | B24: 45986.446 | C24: danielsoares@idr.pr.gov.br | D24: A aprovar | E24: =VLOOKUP(G24,DiretoriaDepart.Coord.!$A$1:$C$72,2,FALSE) -> Pesquisa e Inovação | F24: =VLOOKUP(G24,DiretoriaDepart.Coord.!$A$1:$C$72,3,FALSE) -> Inovação e Comunicação Científica | G24: Agrometereologia (Pesquisa) | I24: 76º Congresso Nacional de Botânica (CNBot) | J24: Congresso | K24: 1 | L24: Daniel Soares Alves | M24: Sociedade Botânica do Brasil | N24: 1 | O24: Mato Grosso do Sul | P24: Campo Grande | Q24: 45941.333 | R24: 45916.708 | S24: Sim | T24: Presencial | U24: Conservação e aplicações de plantas medicinais | V24: O Congresso Nacional de Botânica (CNBot), constitui o mais tradicional encontro da comunidade botânica brasileira, congregando especialistas em taxonomia, ecofisiologia, fisiologia vegetal, sistemática e conservação da flora. A participação possibilitará: Aprofundamento no conhecimento sobre caracterização botânica de espécies medicinais e aromáticas; Aprimoramento de técnicas de coleta, conservação e registro de germoplasma vegetal; Interação com pesquisadores que atuam em bancos genéticos e herbários nacionais; Acesso a discussões fundamentais para políticas de conservação e manejo sustentável de recursos genéticos. | W24: 16 | X24: 7 | Y24: 500 | Z24: 0 | AA24: 0 | AB24: 0 | AC24: 0 | AD24: 0 | AE24: 0 | AF24: Não | AG24: 1500 | AH24: Não | AI24: =IF(AF24="Sim",INT((R24-Q24+1))*K24*VLOOKUP(P24,'Tabelas Auxiliares'!$A$1:$C$400,3,FALSE),0) -> 0 | AJ24: =(AG24/10)*7 -> 1050 | AK24: =IFS( O24="Acre",((W24*0.15)+(X24*0.7))*VLOOKUP(P24,'MunicípiosEstados'!$A$2:$B$23,2,FALSE), O24="Alagoas",((W24*0.15)+(X24*0.7))*VLOOKUP(P24,'MunicípiosEstados'!$C$2:$D$103,2,FALSE), O24="Amapá",((W24*0.15)+(X24*0.7))*VLOOKUP(P24,'MunicípiosEstados'!$E$2:$F$17,2,FALSE), O24="Amazonas",((W24*0.15)+(X24*0.7))*VLOOKUP(P24,'MunicípiosEstados'!$G$2:$H$63,2,FALSE), O24="Bahia",((W24*0.15)+(X24*0.7))*VLOOKUP(P24,'MunicípiosEstados'!$I$2:$J$418,2,FALSE), O24="Ceará",((W24*0.15)+(X24*0.7))*VLOOKUP(P24,'MunicípiosEstados'!$K$2:$L$185,2,FALSE), O24="Distrito Federal",((W24*0.15)+(X24*0.7))*VLOOKUP(P24,'MunicípiosEstados'!$M$2:$N$2,2,FALSE), O24="Espírito Santo",((W24*0.15)+(X24*0.7))*VLOOKUP(P24,'MunicípiosEstados'!$O$2:$P$79,2,FALSE), O24="Goiás",((W24*0.15)+(X24*0.7))*VLOOKUP(P24,'MunicípiosEstados'!$Q$2:$R$247,2,FALSE), O24="Maranhão",((W24*0.15)+(X24*0.7))*VLOOKUP(P24,'MunicípiosEstados'!$S$2:$T$218,2,FALSE), O24="Mato Grosso",((W24*0.15)+(X24*0.7))*VLOOKUP(P24,'MunicípiosEstados'!$U$2:$V$143,2,FALSE), O24="Mato Grosso do Sul",((W24*0.15)+(X24*0.7))*VLOOKUP(P24,'MunicípiosEstados'!$W$2:$X$80,2,FALSE), O24="Minas Gerais",((W24*0.15)+(X24*0.7))*VLOOKUP(P24,'MunicípiosEstados'!$Y$2:$Z$854,2,FALSE), O24="Pará",((W24*0.15)+(X24*0.7))*VLOOKUP(P24,'MunicípiosEstados'!$AA$2:$AB$145,2,FALSE), O24="Paraíba",((W24*0.15)+(X24*0.7))*VLOOKUP(P24,'MunicípiosEstados'!$AC$2:$AD$224,2,FALSE), O24="Paraná",((W24*0.15)+(X24*0.7))*VLOOKUP(P24,'MunicípiosEstados'!$AE$2:$AF$400,2,FALSE), O24="Pernambuco",((W24*0.15)+(X24*0.7))*VLOOKUP(P24,'MunicípiosEstados'!$AG$2:$AH$186,2,FALSE), O24="Piauí",((W24*0.15)+(X24*0.7))*VLOOKUP(P24,'MunicípiosEstados'!$AI$2:$AJ$225,2,FALSE), O24="Rio Grande do Norte",((W24*0.15)+(X24*0.7))*VLOOKUP(P24,'MunicípiosEstados'!$AK$2:$AL$168,2,FALSE), O24="Rio Grande do Sul",((W24*0.15)+(X24*0.7))*VLOOKUP(P24,'MunicípiosEstados'!$AM$2:$AN$498,2,FALSE), O24="Rio de Janeiro",((W24*0.15)+(X24*0.7))*VLOOKUP(P24,'MunicípiosEstados'!$AO$2:$AP$93,2,FALSE), O24="Rondônia",((W24*0.15)+(X24*0.7))*VLOOKUP(P24,'MunicípiosEstados'!$AQ$2:$AR$53,2,FALSE), O24="Roraima",((W24*0.15)+(X24*0.7))*VLOOKUP(P24,'MunicípiosEstados'!$AS$2:$AT$16,2,FALSE), O24="Santa Catarina",((W24*0.15)+(X24*0.7))*VLOOKUP(P24,'MunicípiosEstados'!$AU$2:$AV$296,2,FALSE), O24="São Paulo",((W24*0.15)+(X24*0.7))*VLOOKUP(P24,'MunicípiosEstados'!$AW$2:$AX$646,2,FALSE), O24="Sergipe",((W24*0.15)+(X24*0.7))*VLOOKUP(P24,'MunicípiosEstados'!$AY$2:$AZ$76,2,FALSE), O24="Tocantins",((W24*0.15)+(X24*0.7))*VLOOKUP(P24,'MunicípiosEstados'!$BA$2:$BB$140,2,FALSE), O24="Exterior",((W24*0.15)+(X24*0.7))*VLOOKUP(P24,'MunicípiosEstados'!$BC$2:$BE$221,3,FALSE),TRUE,0 ) -> 2710.198 | AL24: =AK24+AJ24+AI24+AE24+AD24+AC24+AB24+AA24+Z24+Y24 -> 4260.198
A25: =ROW(A25)-1 -> 24 | B25: 45973.477 | C25: rafaelpiovezan@idr.pr.gov.br | D25: A aprovar | E25: =VLOOKUP(G25,DiretoriaDepart.Coord.!$A$1:$C$72,2,FALSE) -> Extensão Rural | F25: =VLOOKUP(G25,DiretoriaDepart.Coord.!$A$1:$C$72,3,FALSE) -> Projetos e Cadeias Produtivas | G25: Pecuária de Leite (Extensão Rural) | I25: INTERLEITE BRASIL 2026 | J25: Congresso | K25: 8 | M25: Milk Point | N25: 0 | O25: Minas Gerais | P25: Uberlândia | Q25: 45887.333 | R25: 45889.75 | S25: Sim | T25: Presencial | U25: Troca de experiências entre produtores, indústrias, técnicos e empresas de várias partes do Brasil | V25: Evento nacional, com papel importante na integração e no desenvolvimento das diversas bacias leiteiras do país | W25: 80 | X25: 40 | Y25: 5000 | Z25: 0 | AA25: 35000 | AB25: 0 | AC25: 3500 | AD25: 0 | AE25: 0 | AF25: Não | AG25: 2000 | AH25: Sim | AI25: =IF(AF25="Sim",INT((R25-Q25+1))*K25*VLOOKUP(P25,'Tabelas Auxiliares'!$A$1:$C$400,3,FALSE),0) -> 0 | AJ25: =(AG25/10)*7 -> 1400 | AK25: =IFS( O25="Acre",((W25*0.15)+(X25*0.7))*VLOOKUP(P25,'MunicípiosEstados'!$A$2:$B$23,2,FALSE), O25="Alagoas",((W25*0.15)+(X25*0.7))*VLOOKUP(P25,'MunicípiosEstados'!$C$2:$D$103,2,FALSE), O25="Amapá",((W25*0.15)+(X25*0.7))*VLOOKUP(P25,'MunicípiosEstados'!$E$2:$F$17,2,FALSE), O25="Amazonas",((W25*0.15)+(X25*0.7))*VLOOKUP(P25,'MunicípiosEstados'!$G$2:$H$63,2,FALSE), O25="Bahia",((W25*0.15)+(X25*0.7))*VLOOKUP(P25,'MunicípiosEstados'!$I$2:$J$418,2,FALSE), O25="Ceará",((W25*0.15)+(X25*0.7))*VLOOKUP(P25,'MunicípiosEstados'!$K$2:$L$185,2,FALSE), O25="Distrito Federal",((W25*0.15)+(X25*0.7))*VLOOKUP(P25,'MunicípiosEstados'!$M$2:$N$2,2,FALSE), O25="Espírito Santo",((W25*0.15)+(X25*0.7))*VLOOKUP(P25,'MunicípiosEstados'!$O$2:$P$79,2,FALSE), O25="Goiás",((W25*0.15)+(X25*0.7))*VLOOKUP(P25,'MunicípiosEstados'!$Q$2:$R$247,2,FALSE), O25="Maranhão",((W25*0.15)+(X25*0.7))*VLOOKUP(P25,'MunicípiosEstados'!$S$2:$T$218,2,FALSE), O25="Mato Grosso",((W25*0.15)+(X25*0.7))*VLOOKUP(P25,'MunicípiosEstados'!$U$2:$V$143,2,FALSE), O25="Mato Grosso do Sul",((W25*0.15)+(X25*0.7))*VLOOKUP(P25,'MunicípiosEstados'!$W$2:$X$80,2,FALSE), O25="Minas Gerais",((W25*0.15)+(X25*0.7))*VLOOKUP(P25,'MunicípiosEstados'!$Y$2:$Z$854,2,FALSE), O25="Pará",((W25*0.15)+(X25*0.7))*VLOOKUP(P25,'MunicípiosEstados'!$AA$2:$AB$145,2,FALSE), O25="Paraíba",((W25*0.15)+(X25*0.7))*VLOOKUP(P25,'MunicípiosEstados'!$AC$2:$AD$224,2,FALSE), O25="Paraná",((W25*0.15)+(X25*0.7))*VLOOKUP(P25,'MunicípiosEstados'!$AE$2:$AF$400,2,FALSE), O25="Pernambuco",((W25*0.15)+(X25*0.7))*VLOOKUP(P25,'MunicípiosEstados'!$AG$2:$AH$186,2,FALSE), O25="Piauí",((W25*0.15)+(X25*0.7))*VLOOKUP(P25,'MunicípiosEstados'!$AI$2:$AJ$225,2,FALSE), O25="Rio Grande do Norte",((W25*0.15)+(X25*0.7))*VLOOKUP(P25,'MunicípiosEstados'!$AK$2:$AL$168,2,FALSE), O25="Rio Grande do Sul",((W25*0.15)+(X25*0.7))*VLOOKUP(P25,'MunicípiosEstados'!$AM$2:$AN$498,2,FALSE), O25="Rio de Janeiro",((W25*0.15)+(X25*0.7))*VLOOKUP(P25,'MunicípiosEstados'!$AO$2:$AP$93,2,FALSE), O25="Rondônia",((W25*0.15)+(X25*0.7))*VLOOKUP(P25,'MunicípiosEstados'!$AQ$2:$AR$53,2,FALSE), O25="Roraima",((W25*0.15)+(X25*0.7))*VLOOKUP(P25,'MunicípiosEstados'!$AS$2:$AT$16,2,FALSE), O25="Santa Catarina",((W25*0.15)+(X25*0.7))*VLOOKUP(P25,'MunicípiosEstados'!$AU$2:$AV$296,2,FALSE), O25="São Paulo",((W25*0.15)+(X25*0.7))*VLOOKUP(P25,'MunicípiosEstados'!$AW$2:$AX$646,2,FALSE), O25="Sergipe",((W25*0.15)+(X25*0.7))*VLOOKUP(P25,'MunicípiosEstados'!$AY$2:$AZ$76,2,FALSE), O25="Tocantins",((W25*0.15)+(X25*0.7))*VLOOKUP(P25,'MunicípiosEstados'!$BA$2:$BB$140,2,FALSE), O25="Exterior",((W25*0.15)+(X25*0.7))*VLOOKUP(P25,'MunicípiosEstados'!$BC$2:$BE$221,3,FALSE),TRUE,0 ) -> 11622 | AL25: =AK25+AJ25+AI25+AE25+AD25+AC25+AB25+AA25+Z25+Y25 -> 56522
A26: =ROW(A26)-1 -> 25 | B26: 45978.635 | C26: laisepontes@idr.pr.gov.br | D26: A aprovar | E26: =VLOOKUP(G26,DiretoriaDepart.Coord.!$A$1:$C$72,2,FALSE) -> Pesquisa e Inovação | F26: =VLOOKUP(G26,DiretoriaDepart.Coord.!$A$1:$C$72,3,FALSE) -> Pesquisa e Capacitação | G26: Programa de Pecuária de Corte e ILPF (Pesquisa) | I26: Zootec 2026 | J26: Congresso | K26: 1 | L26: Laíse da Silveira Pontes | M26: Universidade Federal de Viçosa | N26: 350 | O26: Minas Gerais | P26: Viçosa | Q26: 45797.333 | R26: 45800.75 | S26: Sim | T26: Presencial | U26: A zootecnia dos Próximos 100 Anos | V26: O Congresso da Zootec constitui-se em um dos mais relevantes eventos científicos e técnicos da área de produção animal no Brasil, reunindo pesquisadores, profissionais, estudantes e representantes do setor produtivo. Trata-se de um espaço estratégico para a difusão de conhecimentos atualizados, apresentação de resultados de pesquisa e fortalecimento de parcerias institucionais. | W26: 10 | X26: 5 | Y26: 800 | Z26: 200 | AA26: 1700 | AB26: 320 | AC26: 200 | AD26: 0 | AE26: 0 | AF26: Não | AG26: 0 | AH26: Não | AI26: =IF(AF26="Sim",INT((R26-Q26+1))*K26*VLOOKUP(P26,'Tabelas Auxiliares'!$A$1:$C$400,3,FALSE),0) -> 0 | AJ26: =(AG26/10)*7 -> 0 | AK26: =IFS( O26="Acre",((W26*0.15)+(X26*0.7))*VLOOKUP(P26,'MunicípiosEstados'!$A$2:$B$23,2,FALSE), O26="Alagoas",((W26*0.15)+(X26*0.7))*VLOOKUP(P26,'MunicípiosEstados'!$C$2:$D$103,2,FALSE), O26="Amapá",((W26*0.15)+(X26*0.7))*VLOOKUP(P26,'MunicípiosEstados'!$E$2:$F$17,2,FALSE), O26="Amazonas",((W26*0.15)+(X26*0.7))*VLOOKUP(P26,'MunicípiosEstados'!$G$2:$H$63,2,FALSE), O26="Bahia",((W26*0.15)+(X26*0.7))*VLOOKUP(P26,'MunicípiosEstados'!$I$2:$J$418,2,FALSE), O26="Ceará",((W26*0.15)+(X26*0.7))*VLOOKUP(P26,'MunicípiosEstados'!$K$2:$L$185,2,FALSE), O26="Distrito Federal",((W26*0.15)+(X26*0.7))*VLOOKUP(P26,'MunicípiosEstados'!$M$2:$N$2,2,FALSE), O26="Espírito Santo",((W26*0.15)+(X26*0.7))*VLOOKUP(P26,'MunicípiosEstados'!$O$2:$P$79,2,FALSE), O26="Goiás",((W26*0.15)+(X26*0.7))*VLOOKUP(P26,'MunicípiosEstados'!$Q$2:$R$247,2,FALSE), O26="Maranhão",((W26*0.15)+(X26*0.7))*VLOOKUP(P26,'MunicípiosEstados'!$S$2:$T$218,2,FALSE), O26="Mato Grosso",((W26*0.15)+(X26*0.7))*VLOOKUP(P26,'MunicípiosEstados'!$U$2:$V$143,2,FALSE), O26="Mato Grosso do Sul",((W26*0.15)+(X26*0.7))*VLOOKUP(P26,'MunicípiosEstados'!$W$2:$X$80,2,FALSE), O26="Minas Gerais",((W26*0.15)+(X26*0.7))*VLOOKUP(P26,'MunicípiosEstados'!$Y$2:$Z$854,2,FALSE), O26="Pará",((W26*0.15)+(X26*0.7))*VLOOKUP(P26,'MunicípiosEstados'!$AA$2:$AB$145,2,FALSE), O26="Paraíba",((W26*0.15)+(X26*0.7))*VLOOKUP(P26,'MunicípiosEstados'!$AC$2:$AD$224,2,FALSE), O26="Paraná",((W26*0.15)+(X26*0.7))*VLOOKUP(P26,'MunicípiosEstados'!$AE$2:$AF$400,2,FALSE), O26="Pernambuco",((W26*0.15)+(X26*0.7))*VLOOKUP(P26,'MunicípiosEstados'!$AG$2:$AH$186,2,FALSE), O26="Piauí",((W26*0.15)+(X26*0.7))*VLOOKUP(P26,'MunicípiosEstados'!$AI$2:$AJ$225,2,FALSE), O26="Rio Grande do Norte",((W26*0.15)+(X26*0.7))*VLOOKUP(P26,'MunicípiosEstados'!$AK$2:$AL$168,2,FALSE), O26="Rio Grande do Sul",((W26*0.15)+(X26*0.7))*VLOOKUP(P26,'MunicípiosEstados'!$AM$2:$AN$498,2,FALSE), O26="Rio de Janeiro",((W26*0.15)+(X26*0.7))*VLOOKUP(P26,'MunicípiosEstados'!$AO$2:$AP$93,2,FALSE), O26="Rondônia",((W26*0.15)+(X26*0.7))*VLOOKUP(P26,'MunicípiosEstados'!$AQ$2:$AR$53,2,FALSE), O26="Roraima",((W26*0.15)+(X26*0.7))*VLOOKUP(P26,'MunicípiosEstados'!$AS$2:$AT$16,2,FALSE), O26="Santa Catarina",((W26*0.15)+(X26*0.7))*VLOOKUP(P26,'MunicípiosEstados'!$AU$2:$AV$296,2,FALSE), O26="São Paulo",((W26*0.15)+(X26*0.7))*VLOOKUP(P26,'MunicípiosEstados'!$AW$2:$AX$646,2,FALSE), O26="Sergipe",((W26*0.15)+(X26*0.7))*VLOOKUP(P26,'MunicípiosEstados'!$AY$2:$AZ$76,2,FALSE), O26="Tocantins",((W26*0.15)+(X26*0.7))*VLOOKUP(P26,'MunicípiosEstados'!$BA$2:$BB$140,2,FALSE), O26="Exterior",((W26*0.15)+(X26*0.7))*VLOOKUP(P26,'MunicípiosEstados'!$BC$2:$BE$221,3,FALSE),TRUE,0 ) -> 1452.75 | AL26: =AK26+AJ26+AI26+AE26+AD26+AC26+AB26+AA26+Z26+Y26 -> 4672.75
A27: =ROW(A27)-1 -> 26 | B27: 45978.642 | C27: kfgobbi@idr.pr.gov.br | D27: A aprovar | E27: =VLOOKUP(G27,DiretoriaDepart.Coord.!$A$1:$C$72,2,FALSE) -> Pesquisa e Inovação | F27: =VLOOKUP(G27,DiretoriaDepart.Coord.!$A$1:$C$72,3,FALSE) -> Pesquisa e Capacitação | G27: Programa de Pecuária de Corte e ILPF (Pesquisa) | I27: Congresso Brasileiro de Zootecnia - ZOOTEC 2026 | J27: Congresso | K27: 1 | M27: UFV | N27: 2000 | O27: Minas Gerais | P27: Viçosa | Q27: 45797.333 | R27: 45800.75 | S27: Sim | T27: Presencial | U27: Criação, manejo, produção e bem-estar de animais de interesse econômico, com o objetivo de otimizar a produtividade de forma sustentável e ética. | V27: O Congresso Brasileiro de Zootecnia (ZOOTEC) é um dos eventos de maior expressão da Zootecnia brasileira como ciência e profissão, organizado a 34 anos em parceria com instituições de alta referência acadêmica e de pesquisa, com vertentes nos debates das questões de ensino e temáticas científicas, técnicas e profissionais. A participação de pesquisadores da Área de Ciências Veterinárias e Zootecnia do IDR-paraná é importante para o intercâmbio de conhecimentos e apresentação de resultados de pesquisas desenvolvidas no Instituto. | W27: 7 | X27: 4 | Y27: 600 | Z27: 0 | AA27: 1700 | AB27: 316.6 | AC27: 200 | AD27: 0 | AE27: 0 | AF27: Não | AG27: 0 | AH27: Não | AI27: =IF(AF27="Sim",INT((R27-Q27+1))*K27*VLOOKUP(P27,'Tabelas Auxiliares'!$A$1:$C$400,3,FALSE),0) -> 0 | AJ27: =(AG27/10)*7 -> 0 | AK27: =IFS( O27="Acre",((W27*0.15)+(X27*0.7))*VLOOKUP(P27,'MunicípiosEstados'!$A$2:$B$23,2,FALSE), O27="Alagoas",((W27*0.15)+(X27*0.7))*VLOOKUP(P27,'MunicípiosEstados'!$C$2:$D$103,2,FALSE), O27="Amapá",((W27*0.15)+(X27*0.7))*VLOOKUP(P27,'MunicípiosEstados'!$E$2:$F$17,2,FALSE), O27="Amazonas",((W27*0.15)+(X27*0.7))*VLOOKUP(P27,'MunicípiosEstados'!$G$2:$H$63,2,FALSE), O27="Bahia",((W27*0.15)+(X27*0.7))*VLOOKUP(P27,'MunicípiosEstados'!$I$2:$J$418,2,FALSE), O27="Ceará",((W27*0.15)+(X27*0.7))*VLOOKUP(P27,'MunicípiosEstados'!$K$2:$L$185,2,FALSE), O27="Distrito Federal",((W27*0.15)+(X27*0.7))*VLOOKUP(P27,'MunicípiosEstados'!$M$2:$N$2,2,FALSE), O27="Espírito Santo",((W27*0.15)+(X27*0.7))*VLOOKUP(P27,'MunicípiosEstados'!$O$2:$P$79,2,FALSE), O27="Goiás",((W27*0.15)+(X27*0.7))*VLOOKUP(P27,'MunicípiosEstados'!$Q$2:$R$247,2,FALSE), O27="Maranhão",((W27*0.15)+(X27*0.7))*VLOOKUP(P27,'MunicípiosEstados'!$S$2:$T$218,2,FALSE), O27="Mato Grosso",((W27*0.15)+(X27*0.7))*VLOOKUP(P27,'MunicípiosEstados'!$U$2:$V$143,2,FALSE), O27="Mato Grosso do Sul",((W27*0.15)+(X27*0.7))*VLOOKUP(P27,'MunicípiosEstados'!$W$2:$X$80,2,FALSE), O27="Minas Gerais",((W27*0.15)+(X27*0.7))*VLOOKUP(P27,'MunicípiosEstados'!$Y$2:$Z$854,2,FALSE), O27="Pará",((W27*0.15)+(X27*0.7))*VLOOKUP(P27,'MunicípiosEstados'!$AA$2:$AB$145,2,FALSE), O27="Paraíba",((W27*0.15)+(X27*0.7))*VLOOKUP(P27,'MunicípiosEstados'!$AC$2:$AD$224,2,FALSE), O27="Paraná",((W27*0.15)+(X27*0.7))*VLOOKUP(P27,'MunicípiosEstados'!$AE$2:$AF$400,2,FALSE), O27="Pernambuco",((W27*0.15)+(X27*0.7))*VLOOKUP(P27,'MunicípiosEstados'!$AG$2:$AH$186,2,FALSE), O27="Piauí",((W27*0.15)+(X27*0.7))*VLOOKUP(P27,'MunicípiosEstados'!$AI$2:$AJ$225,2,FALSE), O27="Rio Grande do Norte",((W27*0.15)+(X27*0.7))*VLOOKUP(P27,'MunicípiosEstados'!$AK$2:$AL$168,2,FALSE), O27="Rio Grande do Sul",((W27*0.15)+(X27*0.7))*VLOOKUP(P27,'MunicípiosEstados'!$AM$2:$AN$498,2,FALSE), O27="Rio de Janeiro",((W27*0.15)+(X27*0.7))*VLOOKUP(P27,'MunicípiosEstados'!$AO$2:$AP$93,2,FALSE), O27="Rondônia",((W27*0.15)+(X27*0.7))*VLOOKUP(P27,'MunicípiosEstados'!$AQ$2:$AR$53,2,FALSE), O27="Roraima",((W27*0.15)+(X27*0.7))*VLOOKUP(P27,'MunicípiosEstados'!$AS$2:$AT$16,2,FALSE), O27="Santa Catarina",((W27*0.15)+(X27*0.7))*VLOOKUP(P27,'MunicípiosEstados'!$AU$2:$AV$296,2,FALSE), O27="São Paulo",((W27*0.15)+(X27*0.7))*VLOOKUP(P27,'MunicípiosEstados'!$AW$2:$AX$646,2,FALSE), O27="Sergipe",((W27*0.15)+(X27*0.7))*VLOOKUP(P27,'MunicípiosEstados'!$AY$2:$AZ$76,2,FALSE), O27="Tocantins",((W27*0.15)+(X27*0.7))*VLOOKUP(P27,'MunicípiosEstados'!$BA$2:$BB$140,2,FALSE), O27="Exterior",((W27*0.15)+(X27*0.7))*VLOOKUP(P27,'MunicípiosEstados'!$BC$2:$BE$221,3,FALSE),TRUE,0 ) -> 1118.6175 | AL27: =AK27+AJ27+AI27+AE27+AD27+AC27+AB27+AA27+Z27+Y27 -> 3935.2175
A28: =ROW(A28)-1 -> 27 | B28: 45978.643 | C28: laisepontes@idr.pr.gov.br | D28: A aprovar | E28: =VLOOKUP(G28,DiretoriaDepart.Coord.!$A$1:$C$72,2,FALSE) -> Pesquisa e Inovação | F28: =VLOOKUP(G28,DiretoriaDepart.Coord.!$A$1:$C$72,3,FALSE) -> Pesquisa e Capacitação | G28: Programa de Pecuária de Corte e ILPF (Pesquisa) | I28: SBZ 2026 | J28: Congresso | K28: 1 | L28: Laíse da Silveira Pontes | M28: Universidade Federal de Lavras | N28: 500 | O28: Minas Gerais | P28: Lavras | Q28: 45865.333 | R28: 45869.75 | S28: Sim | T28: Presencial | U28: Ciência e Prática Gerando Valor na Produção Animal | V28: A 59ª Reunião da Sociedade Brasileira de Zootecnia constitui-se em um dos mais relevantes eventos científicos e técnicos da área de produção animal no Brasil, reunindo pesquisadores, profissionais, estudantes e representantes do setor produtivo. Trata-se de um espaço estratégico para a difusão de conhecimentos atualizados, apresentação de resultados de pesquisa e fortalecimento de parcerias institucionais. | W28: 10 | X28: 6 | Y28: 800 | Z28: 200 | AA28: 1500 | AB28: 130 | AC28: 100 | AD28: 0 | AE28: 0 | AF28: Não | AG28: 0 | AH28: Não | AI28: =IF(AF28="Sim",INT((R28-Q28+1))*K28*VLOOKUP(P28,'Tabelas Auxiliares'!$A$1:$C$400,3,FALSE),0) -> 0 | AJ28: =(AG28/10)*7 -> 0 | AK28: =IFS( O28="Acre",((W28*0.15)+(X28*0.7))*VLOOKUP(P28,'MunicípiosEstados'!$A$2:$B$23,2,FALSE), O28="Alagoas",((W28*0.15)+(X28*0.7))*VLOOKUP(P28,'MunicípiosEstados'!$C$2:$D$103,2,FALSE), O28="Amapá",((W28*0.15)+(X28*0.7))*VLOOKUP(P28,'MunicípiosEstados'!$E$2:$F$17,2,FALSE), O28="Amazonas",((W28*0.15)+(X28*0.7))*VLOOKUP(P28,'MunicípiosEstados'!$G$2:$H$63,2,FALSE), O28="Bahia",((W28*0.15)+(X28*0.7))*VLOOKUP(P28,'MunicípiosEstados'!$I$2:$J$418,2,FALSE), O28="Ceará",((W28*0.15)+(X28*0.7))*VLOOKUP(P28,'MunicípiosEstados'!$K$2:$L$185,2,FALSE), O28="Distrito Federal",((W28*0.15)+(X28*0.7))*VLOOKUP(P28,'MunicípiosEstados'!$M$2:$N$2,2,FALSE), O28="Espírito Santo",((W28*0.15)+(X28*0.7))*VLOOKUP(P28,'MunicípiosEstados'!$O$2:$P$79,2,FALSE), O28="Goiás",((W28*0.15)+(X28*0.7))*VLOOKUP(P28,'MunicípiosEstados'!$Q$2:$R$247,2,FALSE), O28="Maranhão",((W28*0.15)+(X28*0.7))*VLOOKUP(P28,'MunicípiosEstados'!$S$2:$T$218,2,FALSE), O28="Mato Grosso",((W28*0.15)+(X28*0.7))*VLOOKUP(P28,'MunicípiosEstados'!$U$2:$V$143,2,FALSE), O28="Mato Grosso do Sul",((W28*0.15)+(X28*0.7))*VLOOKUP(P28,'MunicípiosEstados'!$W$2:$X$80,2,FALSE), O28="Minas Gerais",((W28*0.15)+(X28*0.7))*VLOOKUP(P28,'MunicípiosEstados'!$Y$2:$Z$854,2,FALSE), O28="Pará",((W28*0.15)+(X28*0.7))*VLOOKUP(P28,'MunicípiosEstados'!$AA$2:$AB$145,2,FALSE), O28="Paraíba",((W28*0.15)+(X28*0.7))*VLOOKUP(P28,'MunicípiosEstados'!$AC$2:$AD$224,2,FALSE), O28="Paraná",((W28*0.15)+(X28*0.7))*VLOOKUP(P28,'MunicípiosEstados'!$AE$2:$AF$400,2,FALSE), O28="Pernambuco",((W28*0.15)+(X28*0.7))*VLOOKUP(P28,'MunicípiosEstados'!$AG$2:$AH$186,2,FALSE), O28="Piauí",((W28*0.15)+(X28*0.7))*VLOOKUP(P28,'MunicípiosEstados'!$AI$2:$AJ$225,2,FALSE), O28="Rio Grande do Norte",((W28*0.15)+(X28*0.7))*VLOOKUP(P28,'MunicípiosEstados'!$AK$2:$AL$168,2,FALSE), O28="Rio Grande do Sul",((W28*0.15)+(X28*0.7))*VLOOKUP(P28,'MunicípiosEstados'!$AM$2:$AN$498,2,FALSE), O28="Rio de Janeiro",((W28*0.15)+(X28*0.7))*VLOOKUP(P28,'MunicípiosEstados'!$AO$2:$AP$93,2,FALSE), O28="Rondônia",((W28*0.15)+(X28*0.7))*VLOOKUP(P28,'MunicípiosEstados'!$AQ$2:$AR$53,2,FALSE), O28="Roraima",((W28*0.15)+(X28*0.7))*VLOOKUP(P28,'MunicípiosEstados'!$AS$2:$AT$16,2,FALSE), O28="Santa Catarina",((W28*0.15)+(X28*0.7))*VLOOKUP(P28,'MunicípiosEstados'!$AU$2:$AV$296,2,FALSE), O28="São Paulo",((W28*0.15)+(X28*0.7))*VLOOKUP(P28,'MunicípiosEstados'!$AW$2:$AX$646,2,FALSE), O28="Sergipe",((W28*0.15)+(X28*0.7))*VLOOKUP(P28,'MunicípiosEstados'!$AY$2:$AZ$76,2,FALSE), O28="Tocantins",((W28*0.15)+(X28*0.7))*VLOOKUP(P28,'MunicípiosEstados'!$BA$2:$BB$140,2,FALSE), O28="Exterior",((W28*0.15)+(X28*0.7))*VLOOKUP(P28,'MunicípiosEstados'!$BC$2:$BE$221,3,FALSE),TRUE,0 ) -> 1656.135 | AL28: =AK28+AJ28+AI28+AE28+AD28+AC28+AB28+AA28+Z28+Y28 -> 4386.135
A29: =ROW(A29)-1 -> 28 | B29: 45979.461 | C29: gustavosera@idr.pr.gov.br | D29: A aprovar | E29: =VLOOKUP(G29,DiretoriaDepart.Coord.!$A$1:$C$72,2,FALSE) -> Pesquisa e Inovação | F29: =VLOOKUP(G29,DiretoriaDepart.Coord.!$A$1:$C$72,3,FALSE) -> Pesquisa e Capacitação | G29: Programa de Café e Cultivos Industriais (Pesquisa) | I29: Congresso Brasileiro de Pesquisas Cafeeiras | J29: Congresso | K29: 1 | L29: Gustavo Hiroshi Sera | M29: Consórcio Brasileiro de Pesquisa e Desenvolvimento do Café - Consórcio Pesquisa Café | N29: 0 | O29: Minas Gerais | P29: Belo Horizonte | Q29: 45957.333 | R29: 45961.708 | S29: Não | T29: Presencial | U29: Cultura do café | V29: O Congresso Brasileiro de Pesquisas Cafeeiras é o principal evento técnico-científico do café no Brasil. É uma oportunidade de atualizar os conhecimentos na cultura do café e manter contato e trocar experiências com profissionais da cadeia produtiva do café. | W29: 12 | X29: 6 | Y29: 200 | Z29: 0 | AA29: 0 | AB29: 0 | AC29: 0 | AD29: 200 | AE29: 0 | AF29: Não | AG29: 1300 | AH29: Sim | AI29: =IF(AF29="Sim",INT((R29-Q29+1))*K29*VLOOKUP(P29,'Tabelas Auxiliares'!$A$1:$C$400,3,FALSE),0) -> 0 | AJ29: =(AG29/10)*7 -> 910 | AK29: =IFS( O29="Acre",((W29*0.15)+(X29*0.7))*VLOOKUP(P29,'MunicípiosEstados'!$A$2:$B$23,2,FALSE), O29="Alagoas",((W29*0.15)+(X29*0.7))*VLOOKUP(P29,'MunicípiosEstados'!$C$2:$D$103,2,FALSE), O29="Amapá",((W29*0.15)+(X29*0.7))*VLOOKUP(P29,'MunicípiosEstados'!$E$2:$F$17,2,FALSE), O29="Amazonas",((W29*0.15)+(X29*0.7))*VLOOKUP(P29,'MunicípiosEstados'!$G$2:$H$63,2,FALSE), O29="Bahia",((W29*0.15)+(X29*0.7))*VLOOKUP(P29,'MunicípiosEstados'!$I$2:$J$418,2,FALSE), O29="Ceará",((W29*0.15)+(X29*0.7))*VLOOKUP(P29,'MunicípiosEstados'!$K$2:$L$185,2,FALSE), O29="Distrito Federal",((W29*0.15)+(X29*0.7))*VLOOKUP(P29,'MunicípiosEstados'!$M$2:$N$2,2,FALSE), O29="Espírito Santo",((W29*0.15)+(X29*0.7))*VLOOKUP(P29,'MunicípiosEstados'!$O$2:$P$79,2,FALSE), O29="Goiás",((W29*0.15)+(X29*0.7))*VLOOKUP(P29,'MunicípiosEstados'!$Q$2:$R$247,2,FALSE), O29="Maranhão",((W29*0.15)+(X29*0.7))*VLOOKUP(P29,'MunicípiosEstados'!$S$2:$T$218,2,FALSE), O29="Mato Grosso",((W29*0.15)+(X29*0.7))*VLOOKUP(P29,'MunicípiosEstados'!$U$2:$V$143,2,FALSE), O29="Mato Grosso do Sul",((W29*0.15)+(X29*0.7))*VLOOKUP(P29,'MunicípiosEstados'!$W$2:$X$80,2,FALSE), O29="Minas Gerais",((W29*0.15)+(X29*0.7))*VLOOKUP(P29,'MunicípiosEstados'!$Y$2:$Z$854,2,FALSE), O29="Pará",((W29*0.15)+(X29*0.7))*VLOOKUP(P29,'MunicípiosEstados'!$AA$2:$AB$145,2,FALSE), O29="Paraíba",((W29*0.15)+(X29*0.7))*VLOOKUP(P29,'MunicípiosEstados'!$AC$2:$AD$224,2,FALSE), O29="Paraná",((W29*0.15)+(X29*0.7))*VLOOKUP(P29,'MunicípiosEstados'!$AE$2:$AF$400,2,FALSE), O29="Pernambuco",((W29*0.15)+(X29*0.7))*VLOOKUP(P29,'MunicípiosEstados'!$AG$2:$AH$186,2,FALSE), O29="Piauí",((W29*0.15)+(X29*0.7))*VLOOKUP(P29,'MunicípiosEstados'!$AI$2:$AJ$225,2,FALSE), O29="Rio Grande do Norte",((W29*0.15)+(X29*0.7))*VLOOKUP(P29,'MunicípiosEstados'!$AK$2:$AL$168,2,FALSE), O29="Rio Grande do Sul",((W29*0.15)+(X29*0.7))*VLOOKUP(P29,'MunicípiosEstados'!$AM$2:$AN$498,2,FALSE), O29="Rio de Janeiro",((W29*0.15)+(X29*0.7))*VLOOKUP(P29,'MunicípiosEstados'!$AO$2:$AP$93,2,FALSE), O29="Rondônia",((W29*0.15)+(X29*0.7))*VLOOKUP(P29,'MunicípiosEstados'!$AQ$2:$AR$53,2,FALSE), O29="Roraima",((W29*0.15)+(X29*0.7))*VLOOKUP(P29,'MunicípiosEstados'!$AS$2:$AT$16,2,FALSE), O29="Santa Catarina",((W29*0.15)+(X29*0.7))*VLOOKUP(P29,'MunicípiosEstados'!$AU$2:$AV$296,2,FALSE), O29="São Paulo",((W29*0.15)+(X29*0.7))*VLOOKUP(P29,'MunicípiosEstados'!$AW$2:$AX$646,2,FALSE), O29="Sergipe",((W29*0.15)+(X29*0.7))*VLOOKUP(P29,'MunicípiosEstados'!$AY$2:$AZ$76,2,FALSE), O29="Tocantins",((W29*0.15)+(X29*0.7))*VLOOKUP(P29,'MunicípiosEstados'!$BA$2:$BB$140,2,FALSE), O29="Exterior",((W29*0.15)+(X29*0.7))*VLOOKUP(P29,'MunicípiosEstados'!$BC$2:$BE$221,3,FALSE),TRUE,0 ) -> 2227.56 | AL29: =AK29+AJ29+AI29+AE29+AD29+AC29+AB29+AA29+Z29+Y29 -> 3537.56
A30: =ROW(A30)-1 -> 29 | B30: 45979.462 | C30: ipbruno@idr.pr.gov.br | D30: A aprovar | E30: =VLOOKUP(G30,DiretoriaDepart.Coord.!$A$1:$C$72,2,FALSE) -> Pesquisa e Inovação | F30: =VLOOKUP(G30,DiretoriaDepart.Coord.!$A$1:$C$72,3,FALSE) -> Pesquisa e Capacitação | G30: Programa de Café e Cultivos Industriais (Pesquisa) | I30: Congresso Brasileiro de Pesquisas Cafeeiras | J30: Congresso | K30: 3 | L30: Isabeli Pereira Bruno (pesquisadora); Ana Cláudia de Souza dos Santos (bolsista); Mariany Muzza da Silva (bolsista). | M30: Não há. | N30: 0 | O30: Minas Gerais | P30: Poços de Caldas | Q30: 45958.333 | R30: 45961.333 | S30: Não | T30: Presencial | U30: Cafeicultura. | V30: Atualização dos conhecimentos sobre cafeicultura e apresentação dos resultados de trabalhos desenvolvidos no IDR-Paraná. | W30: 36 | X30: 12 | Y30: 700 | Z30: 0 | AA30: 15000 | AB30: 750 | AC30: 200 | AD30: 0 | AE30: 0 | AF30: Não | AG30: 0 | AH30: Não | AI30: =IF(AF30="Sim",INT((R30-Q30+1))*K30*VLOOKUP(P30,'Tabelas Auxiliares'!$A$1:$C$400,3,FALSE),0) -> 0 | AJ30: =(AG30/10)*7 -> 0 | AK30: =IFS( O30="Acre",((W30*0.15)+(X30*0.7))*VLOOKUP(P30,'MunicípiosEstados'!$A$2:$B$23,2,FALSE), O30="Alagoas",((W30*0.15)+(X30*0.7))*VLOOKUP(P30,'MunicípiosEstados'!$C$2:$D$103,2,FALSE), O30="Amapá",((W30*0.15)+(X30*0.7))*VLOOKUP(P30,'MunicípiosEstados'!$E$2:$F$17,2,FALSE), O30="Amazonas",((W30*0.15)+(X30*0.7))*VLOOKUP(P30,'MunicípiosEstados'!$G$2:$H$63,2,FALSE), O30="Bahia",((W30*0.15)+(X30*0.7))*VLOOKUP(P30,'MunicípiosEstados'!$I$2:$J$418,2,FALSE), O30="Ceará",((W30*0.15)+(X30*0.7))*VLOOKUP(P30,'MunicípiosEstados'!$K$2:$L$185,2,FALSE), O30="Distrito Federal",((W30*0.15)+(X30*0.7))*VLOOKUP(P30,'MunicípiosEstados'!$M$2:$N$2,2,FALSE), O30="Espírito Santo",((W30*0.15)+(X30*0.7))*VLOOKUP(P30,'MunicípiosEstados'!$O$2:$P$79,2,FALSE), O30="Goiás",((W30*0.15)+(X30*0.7))*VLOOKUP(P30,'MunicípiosEstados'!$Q$2:$R$247,2,FALSE), O30="Maranhão",((W30*0.15)+(X30*0.7))*VLOOKUP(P30,'MunicípiosEstados'!$S$2:$T$218,2,FALSE), O30="Mato Grosso",((W30*0.15)+(X30*0.7))*VLOOKUP(P30,'MunicípiosEstados'!$U$2:$V$143,2,FALSE), O30="Mato Grosso do Sul",((W30*0.15)+(X30*0.7))*VLOOKUP(P30,'MunicípiosEstados'!$W$2:$X$80,2,FALSE), O30="Minas Gerais",((W30*0.15)+(X30*0.7))*VLOOKUP(P30,'MunicípiosEstados'!$Y$2:$Z$854,2,FALSE), O30="Pará",((W30*0.15)+(X30*0.7))*VLOOKUP(P30,'MunicípiosEstados'!$AA$2:$AB$145,2,FALSE), O30="Paraíba",((W30*0.15)+(X30*0.7))*VLOOKUP(P30,'MunicípiosEstados'!$AC$2:$AD$224,2,FALSE), O30="Paraná",((W30*0.15)+(X30*0.7))*VLOOKUP(P30,'MunicípiosEstados'!$AE$2:$AF$400,2,FALSE), O30="Pernambuco",((W30*0.15)+(X30*0.7))*VLOOKUP(P30,'MunicípiosEstados'!$AG$2:$AH$186,2,FALSE), O30="Piauí",((W30*0.15)+(X30*0.7))*VLOOKUP(P30,'MunicípiosEstados'!$AI$2:$AJ$225,2,FALSE), O30="Rio Grande do Norte",((W30*0.15)+(X30*0.7))*VLOOKUP(P30,'MunicípiosEstados'!$AK$2:$AL$168,2,FALSE), O30="Rio Grande do Sul",((W30*0.15)+(X30*0.7))*VLOOKUP(P30,'MunicípiosEstados'!$AM$2:$AN$498,2,FALSE), O30="Rio de Janeiro",((W30*0.15)+(X30*0.7))*VLOOKUP(P30,'MunicípiosEstados'!$AO$2:$AP$93,2,FALSE), O30="Rondônia",((W30*0.15)+(X30*0.7))*VLOOKUP(P30,'MunicípiosEstados'!$AQ$2:$AR$53,2,FALSE), O30="Roraima",((W30*0.15)+(X30*0.7))*VLOOKUP(P30,'MunicípiosEstados'!$AS$2:$AT$16,2,FALSE), O30="Santa Catarina",((W30*0.15)+(X30*0.7))*VLOOKUP(P30,'MunicípiosEstados'!$AU$2:$AV$296,2,FALSE), O30="São Paulo",((W30*0.15)+(X30*0.7))*VLOOKUP(P30,'MunicípiosEstados'!$AW$2:$AX$646,2,FALSE), O30="Sergipe",((W30*0.15)+(X30*0.7))*VLOOKUP(P30,'MunicípiosEstados'!$AY$2:$AZ$76,2,FALSE), O30="Tocantins",((W30*0.15)+(X30*0.7))*VLOOKUP(P30,'MunicípiosEstados'!$BA$2:$BB$140,2,FALSE), O30="Exterior",((W30*0.15)+(X30*0.7))*VLOOKUP(P30,'MunicípiosEstados'!$BC$2:$BE$221,3,FALSE),TRUE,0 ) -> 4009.59 | AL30: =AK30+AJ30+AI30+AE30+AD30+AC30+AB30+AA30+Z30+Y30 -> 20659.59
A31: =ROW(A31)-1 -> 30 | B31: 45980.478 | C31: defantin@idr.pr.gov.br | D31: A aprovar | E31: =VLOOKUP(G31,DiretoriaDepart.Coord.!$A$1:$C$72,2,FALSE) -> Pesquisa e Inovação | F31: =VLOOKUP(G31,DiretoriaDepart.Coord.!$A$1:$C$72,3,FALSE) -> Pesquisa e Capacitação | G31: Programa de Café e Cultivos Industriais (Pesquisa) | I31: Semana internacional do café | J31: Feira | K31: 01 | M31: sca | N31: 27000 | O31: Minas Gerais | P31: Belo horizonte | Q31: 45972.417 | R31: 45974.792 | S31: Sim | T31: Presencial | U31: atualização completa no tema café | V31: profissionais renomados do setor cafeeiro estarão na SIC para moldar os próximos passos da cafeicultura e temos que aproveitar a oportunidade para nos atualizar e também provavelmente o governo do estado terá um estande onde atenderemos os visitantes | W31: 12 | X31: 6 | Y31: 0 | Z31: 0 | AA31: 0 | AB31: 0 | AC31: 0 | AD31: 400 | AE31: 0 | AF31: Não | AG31: 2500 | AH31: Sim | AI31: =IF(AF31="Sim",INT((R31-Q31+1))*K31*VLOOKUP(P31,'Tabelas Auxiliares'!$A$1:$C$400,3,FALSE),0) -> 0 | AJ31: =(AG31/10)*7 -> 1750 | AK31: =IFS( O31="Acre",((W31*0.15)+(X31*0.7))*VLOOKUP(P31,'MunicípiosEstados'!$A$2:$B$23,2,FALSE), O31="Alagoas",((W31*0.15)+(X31*0.7))*VLOOKUP(P31,'MunicípiosEstados'!$C$2:$D$103,2,FALSE), O31="Amapá",((W31*0.15)+(X31*0.7))*VLOOKUP(P31,'MunicípiosEstados'!$E$2:$F$17,2,FALSE), O31="Amazonas",((W31*0.15)+(X31*0.7))*VLOOKUP(P31,'MunicípiosEstados'!$G$2:$H$63,2,FALSE), O31="Bahia",((W31*0.15)+(X31*0.7))*VLOOKUP(P31,'MunicípiosEstados'!$I$2:$J$418,2,FALSE), O31="Ceará",((W31*0.15)+(X31*0.7))*VLOOKUP(P31,'MunicípiosEstados'!$K$2:$L$185,2,FALSE), O31="Distrito Federal",((W31*0.15)+(X31*0.7))*VLOOKUP(P31,'MunicípiosEstados'!$M$2:$N$2,2,FALSE), O31="Espírito Santo",((W31*0.15)+(X31*0.7))*VLOOKUP(P31,'MunicípiosEstados'!$O$2:$P$79,2,FALSE), O31="Goiás",((W31*0.15)+(X31*0.7))*VLOOKUP(P31,'MunicípiosEstados'!$Q$2:$R$247,2,FALSE), O31="Maranhão",((W31*0.15)+(X31*0.7))*VLOOKUP(P31,'MunicípiosEstados'!$S$2:$T$218,2,FALSE), O31="Mato Grosso",((W31*0.15)+(X31*0.7))*VLOOKUP(P31,'MunicípiosEstados'!$U$2:$V$143,2,FALSE), O31="Mato Grosso do Sul",((W31*0.15)+(X31*0.7))*VLOOKUP(P31,'MunicípiosEstados'!$W$2:$X$80,2,FALSE), O31="Minas Gerais",((W31*0.15)+(X31*0.7))*VLOOKUP(P31,'MunicípiosEstados'!$Y$2:$Z$854,2,FALSE), O31="Pará",((W31*0.15)+(X31*0.7))*VLOOKUP(P31,'MunicípiosEstados'!$AA$2:$AB$145,2,FALSE), O31="Paraíba",((W31*0.15)+(X31*0.7))*VLOOKUP(P31,'MunicípiosEstados'!$AC$2:$AD$224,2,FALSE), O31="Paraná",((W31*0.15)+(X31*0.7))*VLOOKUP(P31,'MunicípiosEstados'!$AE$2:$AF$400,2,FALSE), O31="Pernambuco",((W31*0.15)+(X31*0.7))*VLOOKUP(P31,'MunicípiosEstados'!$AG$2:$AH$186,2,FALSE), O31="Piauí",((W31*0.15)+(X31*0.7))*VLOOKUP(P31,'MunicípiosEstados'!$AI$2:$AJ$225,2,FALSE), O31="Rio Grande do Norte",((W31*0.15)+(X31*0.7))*VLOOKUP(P31,'MunicípiosEstados'!$AK$2:$AL$168,2,FALSE), O31="Rio Grande do Sul",((W31*0.15)+(X31*0.7))*VLOOKUP(P31,'MunicípiosEstados'!$AM$2:$AN$498,2,FALSE), O31="Rio de Janeiro",((W31*0.15)+(X31*0.7))*VLOOKUP(P31,'MunicípiosEstados'!$AO$2:$AP$93,2,FALSE), O31="Rondônia",((W31*0.15)+(X31*0.7))*VLOOKUP(P31,'MunicípiosEstados'!$AQ$2:$AR$53,2,FALSE), O31="Roraima",((W31*0.15)+(X31*0.7))*VLOOKUP(P31,'MunicípiosEstados'!$AS$2:$AT$16,2,FALSE), O31="Santa Catarina",((W31*0.15)+(X31*0.7))*VLOOKUP(P31,'MunicípiosEstados'!$AU$2:$AV$296,2,FALSE), O31="São Paulo",((W31*0.15)+(X31*0.7))*VLOOKUP(P31,'MunicípiosEstados'!$AW$2:$AX$646,2,FALSE), O31="Sergipe",((W31*0.15)+(X31*0.7))*VLOOKUP(P31,'MunicípiosEstados'!$AY$2:$AZ$76,2,FALSE), O31="Tocantins",((W31*0.15)+(X31*0.7))*VLOOKUP(P31,'MunicípiosEstados'!$BA$2:$BB$140,2,FALSE), O31="Exterior",((W31*0.15)+(X31*0.7))*VLOOKUP(P31,'MunicípiosEstados'!$BC$2:$BE$221,3,FALSE),TRUE,0 ) -> 2227.56 | AL31: =AK31+AJ31+AI31+AE31+AD31+AC31+AB31+AA31+Z31+Y31 -> 4377.56
A32: =ROW(A32)-1 -> 31 | B32: 45980.631 | C32: defantin@idr.pr.gov.br | D32: A aprovar | E32: =VLOOKUP(G32,DiretoriaDepart.Coord.!$A$1:$C$72,2,FALSE) -> Pesquisa e Inovação | F32: =VLOOKUP(G32,DiretoriaDepart.Coord.!$A$1:$C$72,3,FALSE) -> Pesquisa e Capacitação | G32: Programa de Café e Cultivos Industriais (Pesquisa) | I32: Expocafé 2026 | J32: Exposição | K32: 01 | M32: epamig | N32: 30000 | O32: Minas Gerais | P32: três pontas | Q32: 45802.333 | R32: 45806.708 | S32: Sim | T32: Presencial | U32: a maior exposição de mecanização da cafeicultura brasileira | V32: nesta visita poderemos conhecer as mais recentes tecnologias e equipamentos voltados para a cafeicultura, além de participar de palestras e workshops com especialistas do setor, ampliando o networking e explorando novas oportunidades para cafeicultura do parana. | W32: 10 | X32: 4 | Y32: 0 | Z32: 0 | AA32: 0 | AB32: 0 | AC32: 0 | AD32: 300 | AE32: 0 | AF32: Não | AG32: 1300 | AH32: Sim | AI32: =IF(AF32="Sim",INT((R32-Q32+1))*K32*VLOOKUP(P32,'Tabelas Auxiliares'!$A$1:$C$400,3,FALSE),0) -> 0 | AJ32: =(AG32/10)*7 -> 910 | AK32: =IFS( O32="Acre",((W32*0.15)+(X32*0.7))*VLOOKUP(P32,'MunicípiosEstados'!$A$2:$B$23,2,FALSE), O32="Alagoas",((W32*0.15)+(X32*0.7))*VLOOKUP(P32,'MunicípiosEstados'!$C$2:$D$103,2,FALSE), O32="Amapá",((W32*0.15)+(X32*0.7))*VLOOKUP(P32,'MunicípiosEstados'!$E$2:$F$17,2,FALSE), O32="Amazonas",((W32*0.15)+(X32*0.7))*VLOOKUP(P32,'MunicípiosEstados'!$G$2:$H$63,2,FALSE), O32="Bahia",((W32*0.15)+(X32*0.7))*VLOOKUP(P32,'MunicípiosEstados'!$I$2:$J$418,2,FALSE), O32="Ceará",((W32*0.15)+(X32*0.7))*VLOOKUP(P32,'MunicípiosEstados'!$K$2:$L$185,2,FALSE), O32="Distrito Federal",((W32*0.15)+(X32*0.7))*VLOOKUP(P32,'MunicípiosEstados'!$M$2:$N$2,2,FALSE), O32="Espírito Santo",((W32*0.15)+(X32*0.7))*VLOOKUP(P32,'MunicípiosEstados'!$O$2:$P$79,2,FALSE), O32="Goiás",((W32*0.15)+(X32*0.7))*VLOOKUP(P32,'MunicípiosEstados'!$Q$2:$R$247,2,FALSE), O32="Maranhão",((W32*0.15)+(X32*0.7))*VLOOKUP(P32,'MunicípiosEstados'!$S$2:$T$218,2,FALSE), O32="Mato Grosso",((W32*0.15)+(X32*0.7))*VLOOKUP(P32,'MunicípiosEstados'!$U$2:$V$143,2,FALSE), O32="Mato Grosso do Sul",((W32*0.15)+(X32*0.7))*VLOOKUP(P32,'MunicípiosEstados'!$W$2:$X$80,2,FALSE), O32="Minas Gerais",((W32*0.15)+(X32*0.7))*VLOOKUP(P32,'MunicípiosEstados'!$Y$2:$Z$854,2,FALSE), O32="Pará",((W32*0.15)+(X32*0.7))*VLOOKUP(P32,'MunicípiosEstados'!$AA$2:$AB$145,2,FALSE), O32="Paraíba",((W32*0.15)+(X32*0.7))*VLOOKUP(P32,'MunicípiosEstados'!$AC$2:$AD$224,2,FALSE), O32="Paraná",((W32*0.15)+(X32*0.7))*VLOOKUP(P32,'MunicípiosEstados'!$AE$2:$AF$400,2,FALSE), O32="Pernambuco",((W32*0.15)+(X32*0.7))*VLOOKUP(P32,'MunicípiosEstados'!$AG$2:$AH$186,2,FALSE), O32="Piauí",((W32*0.15)+(X32*0.7))*VLOOKUP(P32,'MunicípiosEstados'!$AI$2:$AJ$225,2,FALSE), O32="Rio Grande do Norte",((W32*0.15)+(X32*0.7))*VLOOKUP(P32,'MunicípiosEstados'!$AK$2:$AL$168,2,FALSE), O32="Rio Grande do Sul",((W32*0.15)+(X32*0.7))*VLOOKUP(P32,'MunicípiosEstados'!$AM$2:$AN$498,2,FALSE), O32="Rio de Janeiro",((W32*0.15)+(X32*0.7))*VLOOKUP(P32,'MunicípiosEstados'!$AO$2:$AP$93,2,FALSE), O32="Rondônia",((W32*0.15)+(X32*0.7))*VLOOKUP(P32,'MunicípiosEstados'!$AQ$2:$AR$53,2,FALSE), O32="Roraima",((W32*0.15)+(X32*0.7))*VLOOKUP(P32,'MunicípiosEstados'!$AS$2:$AT$16,2,FALSE), O32="Santa Catarina",((W32*0.15)+(X32*0.7))*VLOOKUP(P32,'MunicípiosEstados'!$AU$2:$AV$296,2,FALSE), O32="São Paulo",((W32*0.15)+(X32*0.7))*VLOOKUP(P32,'MunicípiosEstados'!$AW$2:$AX$646,2,FALSE), O32="Sergipe",((W32*0.15)+(X32*0.7))*VLOOKUP(P32,'MunicípiosEstados'!$AY$2:$AZ$76,2,FALSE), O32="Tocantins",((W32*0.15)+(X32*0.7))*VLOOKUP(P32,'MunicípiosEstados'!$BA$2:$BB$140,2,FALSE), O32="Exterior",((W32*0.15)+(X32*0.7))*VLOOKUP(P32,'MunicípiosEstados'!$BC$2:$BE$221,3,FALSE),TRUE,0 ) -> 1249.365 | AL32: =AK32+AJ32+AI32+AE32+AD32+AC32+AB32+AA32+Z32+Y32 -> 2459.365
A33: =ROW(A33)-1 -> 32 | B33: 45980.64 | C33: defantin@idr.pr.gov.br | D33: A aprovar | E33: =VLOOKUP(G33,DiretoriaDepart.Coord.!$A$1:$C$72,2,FALSE) -> Pesquisa e Inovação | F33: =VLOOKUP(G33,DiretoriaDepart.Coord.!$A$1:$C$72,3,FALSE) -> Pesquisa e Capacitação | G33: Programa de Café e Cultivos Industriais (Pesquisa) | I33: Congresso Brasileiro de Pesquisas Cafeeiras | J33: Congresso | K33: 1 | M33: procafé | N33: 400 | O33: Minas Gerais | P33: poços de caldas | Q33: 45954.333 | R33: 45959.708 | S33: Não | T33: Presencial | U33: Ferrugem do Cafeeiro 55 anos: antes doença temida, hoje vencida pela tecnologia". O evento foca nos avanços tecnológicos que permitiram o controle dessa doença e também em outras inovações para o setor | V33: A participação no Congresso Brasileiro de Pesquisas Cafeeiras é fundamental para o aprimoramento técnico e científico relacionado à cafeicultura, área diretamente ligada às atividades que desenvolvo. O evento reúne especialistas, pesquisadores, produtores, instituições de pesquisa e empresas do setor, proporcionando acesso a conhecimentos atualizados, tecnologias emergentes e práticas inovadoras que impactam diretamente a produtividade, sustentabilidade e competitividade da cadeia do café. | W33: 10 | X33: 5 | Y33: 250 | Z33: 0 | AA33: 0 | AB33: 0 | AC33: 0 | AD33: 300 | AE33: 0 | AF33: Não | AG33: 1300 | AH33: Sim | AI33: =IF(AF33="Sim",INT((R33-Q33+1))*K33*VLOOKUP(P33,'Tabelas Auxiliares'!$A$1:$C$400,3,FALSE),0) -> 0 | AJ33: =(AG33/10)*7 -> 910 | AK33: =IFS( O33="Acre",((W33*0.15)+(X33*0.7))*VLOOKUP(P33,'MunicípiosEstados'!$A$2:$B$23,2,FALSE), O33="Alagoas",((W33*0.15)+(X33*0.7))*VLOOKUP(P33,'MunicípiosEstados'!$C$2:$D$103,2,FALSE), O33="Amapá",((W33*0.15)+(X33*0.7))*VLOOKUP(P33,'MunicípiosEstados'!$E$2:$F$17,2,FALSE), O33="Amazonas",((W33*0.15)+(X33*0.7))*VLOOKUP(P33,'MunicípiosEstados'!$G$2:$H$63,2,FALSE), O33="Bahia",((W33*0.15)+(X33*0.7))*VLOOKUP(P33,'MunicípiosEstados'!$I$2:$J$418,2,FALSE), O33="Ceará",((W33*0.15)+(X33*0.7))*VLOOKUP(P33,'MunicípiosEstados'!$K$2:$L$185,2,FALSE), O33="Distrito Federal",((W33*0.15)+(X33*0.7))*VLOOKUP(P33,'MunicípiosEstados'!$M$2:$N$2,2,FALSE), O33="Espírito Santo",((W33*0.15)+(X33*0.7))*VLOOKUP(P33,'MunicípiosEstados'!$O$2:$P$79,2,FALSE), O33="Goiás",((W33*0.15)+(X33*0.7))*VLOOKUP(P33,'MunicípiosEstados'!$Q$2:$R$247,2,FALSE), O33="Maranhão",((W33*0.15)+(X33*0.7))*VLOOKUP(P33,'MunicípiosEstados'!$S$2:$T$218,2,FALSE), O33="Mato Grosso",((W33*0.15)+(X33*0.7))*VLOOKUP(P33,'MunicípiosEstados'!$U$2:$V$143,2,FALSE), O33="Mato Grosso do Sul",((W33*0.15)+(X33*0.7))*VLOOKUP(P33,'MunicípiosEstados'!$W$2:$X$80,2,FALSE), O33="Minas Gerais",((W33*0.15)+(X33*0.7))*VLOOKUP(P33,'MunicípiosEstados'!$Y$2:$Z$854,2,FALSE), O33="Pará",((W33*0.15)+(X33*0.7))*VLOOKUP(P33,'MunicípiosEstados'!$AA$2:$AB$145,2,FALSE), O33="Paraíba",((W33*0.15)+(X33*0.7))*VLOOKUP(P33,'MunicípiosEstados'!$AC$2:$AD$224,2,FALSE), O33="Paraná",((W33*0.15)+(X33*0.7))*VLOOKUP(P33,'MunicípiosEstados'!$AE$2:$AF$400,2,FALSE), O33="Pernambuco",((W33*0.15)+(X33*0.7))*VLOOKUP(P33,'MunicípiosEstados'!$AG$2:$AH$186,2,FALSE), O33="Piauí",((W33*0.15)+(X33*0.7))*VLOOKUP(P33,'MunicípiosEstados'!$AI$2:$AJ$225,2,FALSE), O33="Rio Grande do Norte",((W33*0.15)+(X33*0.7))*VLOOKUP(P33,'MunicípiosEstados'!$AK$2:$AL$168,2,FALSE), O33="Rio Grande do Sul",((W33*0.15)+(X33*0.7))*VLOOKUP(P33,'MunicípiosEstados'!$AM$2:$AN$498,2,FALSE), O33="Rio de Janeiro",((W33*0.15)+(X33*0.7))*VLOOKUP(P33,'MunicípiosEstados'!$AO$2:$AP$93,2,FALSE), O33="Rondônia",((W33*0.15)+(X33*0.7))*VLOOKUP(P33,'MunicípiosEstados'!$AQ$2:$AR$53,2,FALSE), O33="Roraima",((W33*0.15)+(X33*0.7))*VLOOKUP(P33,'MunicípiosEstados'!$AS$2:$AT$16,2,FALSE), O33="Santa Catarina",((W33*0.15)+(X33*0.7))*VLOOKUP(P33,'MunicípiosEstados'!$AU$2:$AV$296,2,FALSE), O33="São Paulo",((W33*0.15)+(X33*0.7))*VLOOKUP(P33,'MunicípiosEstados'!$AW$2:$AX$646,2,FALSE), O33="Sergipe",((W33*0.15)+(X33*0.7))*VLOOKUP(P33,'MunicípiosEstados'!$AY$2:$AZ$76,2,FALSE), O33="Tocantins",((W33*0.15)+(X33*0.7))*VLOOKUP(P33,'MunicípiosEstados'!$BA$2:$BB$140,2,FALSE), O33="Exterior",((W33*0.15)+(X33*0.7))*VLOOKUP(P33,'MunicípiosEstados'!$BC$2:$BE$221,3,FALSE),TRUE,0 ) -> 1452.75 | AL33: =AK33+AJ33+AI33+AE33+AD33+AC33+AB33+AA33+Z33+Y33 -> 2912.75
A34: =ROW(A34)-1 -> 33 | B34: 45985.969 | C34: romeugair@idr.pr.gov.br | D34: A aprovar | E34: =VLOOKUP(G34,DiretoriaDepart.Coord.!$A$1:$C$72,2,FALSE) -> Extensão Rural | F34: =VLOOKUP(G34,DiretoriaDepart.Coord.!$A$1:$C$72,3,FALSE) -> Projetos e Cadeias Produtivas | G34: Café (Extensão Rural) | I34: EXPOCAFÉ 2026 | J34: Exposição | K34: 4 | M34: Não há | N34: 0 | O34: Minas Gerais | P34: Três Pontas | Q34: 45803.333 | R34: 45805.708 | S34: Não | T34: Presencial | U34: Mecanização da cafeicultura | V34: A mecanização da lavoura cafeeira é fundamental na sua sustentabilidade, pois a falta de mão de obra se agrava a cada ano, o trabalho sem mecanização é penoso e de alto custo. Neste evento os técnicos e cafeicultores conhecem as últimas pesquisas da área e acompanham as máquinas trabalhando. | W34: 40 | X34: 16 | Y34: 0 | Z34: 0 | AA34: 0 | AB34: 0 | AC34: 0 | AD34: 300 | AE34: 0 | AF34: Não | AG34: 2000 | AH34: Não | AI34: =IF(AF34="Sim",INT((R34-Q34+1))*K34*VLOOKUP(P34,'Tabelas Auxiliares'!$A$1:$C$400,3,FALSE),0) -> 0 | AJ34: =(AG34/10)*7 -> 1400 | AK34: =IFS( O34="Acre",((W34*0.15)+(X34*0.7))*VLOOKUP(P34,'MunicípiosEstados'!$A$2:$B$23,2,FALSE), O34="Alagoas",((W34*0.15)+(X34*0.7))*VLOOKUP(P34,'MunicípiosEstados'!$C$2:$D$103,2,FALSE), O34="Amapá",((W34*0.15)+(X34*0.7))*VLOOKUP(P34,'MunicípiosEstados'!$E$2:$F$17,2,FALSE), O34="Amazonas",((W34*0.15)+(X34*0.7))*VLOOKUP(P34,'MunicípiosEstados'!$G$2:$H$63,2,FALSE), O34="Bahia",((W34*0.15)+(X34*0.7))*VLOOKUP(P34,'MunicípiosEstados'!$I$2:$J$418,2,FALSE), O34="Ceará",((W34*0.15)+(X34*0.7))*VLOOKUP(P34,'MunicípiosEstados'!$K$2:$L$185,2,FALSE), O34="Distrito Federal",((W34*0.15)+(X34*0.7))*VLOOKUP(P34,'MunicípiosEstados'!$M$2:$N$2,2,FALSE), O34="Espírito Santo",((W34*0.15)+(X34*0.7))*VLOOKUP(P34,'MunicípiosEstados'!$O$2:$P$79,2,FALSE), O34="Goiás",((W34*0.15)+(X34*0.7))*VLOOKUP(P34,'MunicípiosEstados'!$Q$2:$R$247,2,FALSE), O34="Maranhão",((W34*0.15)+(X34*0.7))*VLOOKUP(P34,'MunicípiosEstados'!$S$2:$T$218,2,FALSE), O34="Mato Grosso",((W34*0.15)+(X34*0.7))*VLOOKUP(P34,'MunicípiosEstados'!$U$2:$V$143,2,FALSE), O34="Mato Grosso do Sul",((W34*0.15)+(X34*0.7))*VLOOKUP(P34,'MunicípiosEstados'!$W$2:$X$80,2,FALSE), O34="Minas Gerais",((W34*0.15)+(X34*0.7))*VLOOKUP(P34,'MunicípiosEstados'!$Y$2:$Z$854,2,FALSE), O34="Pará",((W34*0.15)+(X34*0.7))*VLOOKUP(P34,'MunicípiosEstados'!$AA$2:$AB$145,2,FALSE), O34="Paraíba",((W34*0.15)+(X34*0.7))*VLOOKUP(P34,'MunicípiosEstados'!$AC$2:$AD$224,2,FALSE), O34="Paraná",((W34*0.15)+(X34*0.7))*VLOOKUP(P34,'MunicípiosEstados'!$AE$2:$AF$400,2,FALSE), O34="Pernambuco",((W34*0.15)+(X34*0.7))*VLOOKUP(P34,'MunicípiosEstados'!$AG$2:$AH$186,2,FALSE), O34="Piauí",((W34*0.15)+(X34*0.7))*VLOOKUP(P34,'MunicípiosEstados'!$AI$2:$AJ$225,2,FALSE), O34="Rio Grande do Norte",((W34*0.15)+(X34*0.7))*VLOOKUP(P34,'MunicípiosEstados'!$AK$2:$AL$168,2,FALSE), O34="Rio Grande do Sul",((W34*0.15)+(X34*0.7))*VLOOKUP(P34,'MunicípiosEstados'!$AM$2:$AN$498,2,FALSE), O34="Rio de Janeiro",((W34*0.15)+(X34*0.7))*VLOOKUP(P34,'MunicípiosEstados'!$AO$2:$AP$93,2,FALSE), O34="Rondônia",((W34*0.15)+(X34*0.7))*VLOOKUP(P34,'MunicípiosEstados'!$AQ$2:$AR$53,2,FALSE), O34="Roraima",((W34*0.15)+(X34*0.7))*VLOOKUP(P34,'MunicípiosEstados'!$AS$2:$AT$16,2,FALSE), O34="Santa Catarina",((W34*0.15)+(X34*0.7))*VLOOKUP(P34,'MunicípiosEstados'!$AU$2:$AV$296,2,FALSE), O34="São Paulo",((W34*0.15)+(X34*0.7))*VLOOKUP(P34,'MunicípiosEstados'!$AW$2:$AX$646,2,FALSE), O34="Sergipe",((W34*0.15)+(X34*0.7))*VLOOKUP(P34,'MunicípiosEstados'!$AY$2:$AZ$76,2,FALSE), O34="Tocantins",((W34*0.15)+(X34*0.7))*VLOOKUP(P34,'MunicípiosEstados'!$BA$2:$BB$140,2,FALSE), O34="Exterior",((W34*0.15)+(X34*0.7))*VLOOKUP(P34,'MunicípiosEstados'!$BC$2:$BE$221,3,FALSE),TRUE,0 ) -> 4997.46 | AL34: =AK34+AJ34+AI34+AE34+AD34+AC34+AB34+AA34+Z34+Y34 -> 6697.46
A35: =ROW(A35)-1 -> 34 | B35: 45987.459 | C35: heverly@idr.pr.gov.br | D35: A aprovar | E35: =VLOOKUP(G35,DiretoriaDepart.Coord.!$A$1:$C$72,2,FALSE) -> Pesquisa e Inovação | F35: =VLOOKUP(G35,DiretoriaDepart.Coord.!$A$1:$C$72,3,FALSE) -> Pesquisa e Capacitação | G35: Programa de Café e Cultivos Industriais (Pesquisa) | I35: Semana Internacional do Cafe | J35: Simpósio | K35: 2 | M35: Nãos e aplica | N35: 0 | O35: Minas Gerais | P35: Belo Horizonte | Q35: 45972.333 | R35: 45974.75 | S35: Sim | T35: Presencial | U35: Café em transformação, inovação e sustentabilidade | V35: A pesquisadora Dra. Heverly Morais desenvolve suas atividades com a cultura cafeeira desde 1997, tendo participado de inúmeros projetos. Coordena atualmente projetos de pesquisa, experimentos de campo e atividades na cafeicultura. A mesma possui inúmeras publicações em revistas científicas especializadas, congressos, livros e circulares sobre a cultura cafeeira. Sua participação neste evento terá como fim interação com a comunidade científica e atualização dos seus conhecimentos sobre quais as inovações, expectativas e avanços da cafeicultura. Além disso, através desse evento poderão ser formados contatos e parcerias entre o IDR-Paraná e universidades e institutos de pesquisa. | W35: 18 | X35: 4 | Y35: 200 | Z35: 0 | AA35: 2400 | AB35: 0 | AC35: 400 | AD35: 0 | AE35: 0 | AF35: Não | AG35: 0 | AH35: Não | AI35: =IF(AF35="Sim",INT((R35-Q35+1))*K35*VLOOKUP(P35,'Tabelas Auxiliares'!$A$1:$C$400,3,FALSE),0) -> 0 | AJ35: =(AG35/10)*7 -> 0 | AK35: =IFS( O35="Acre",((W35*0.15)+(X35*0.7))*VLOOKUP(P35,'MunicípiosEstados'!$A$2:$B$23,2,FALSE), O35="Alagoas",((W35*0.15)+(X35*0.7))*VLOOKUP(P35,'MunicípiosEstados'!$C$2:$D$103,2,FALSE), O35="Amapá",((W35*0.15)+(X35*0.7))*VLOOKUP(P35,'MunicípiosEstados'!$E$2:$F$17,2,FALSE), O35="Amazonas",((W35*0.15)+(X35*0.7))*VLOOKUP(P35,'MunicípiosEstados'!$G$2:$H$63,2,FALSE), O35="Bahia",((W35*0.15)+(X35*0.7))*VLOOKUP(P35,'MunicípiosEstados'!$I$2:$J$418,2,FALSE), O35="Ceará",((W35*0.15)+(X35*0.7))*VLOOKUP(P35,'MunicípiosEstados'!$K$2:$L$185,2,FALSE), O35="Distrito Federal",((W35*0.15)+(X35*0.7))*VLOOKUP(P35,'MunicípiosEstados'!$M$2:$N$2,2,FALSE), O35="Espírito Santo",((W35*0.15)+(X35*0.7))*VLOOKUP(P35,'MunicípiosEstados'!$O$2:$P$79,2,FALSE), O35="Goiás",((W35*0.15)+(X35*0.7))*VLOOKUP(P35,'MunicípiosEstados'!$Q$2:$R$247,2,FALSE), O35="Maranhão",((W35*0.15)+(X35*0.7))*VLOOKUP(P35,'MunicípiosEstados'!$S$2:$T$218,2,FALSE), O35="Mato Grosso",((W35*0.15)+(X35*0.7))*VLOOKUP(P35,'MunicípiosEstados'!$U$2:$V$143,2,FALSE), O35="Mato Grosso do Sul",((W35*0.15)+(X35*0.7))*VLOOKUP(P35,'MunicípiosEstados'!$W$2:$X$80,2,FALSE), O35="Minas Gerais",((W35*0.15)+(X35*0.7))*VLOOKUP(P35,'MunicípiosEstados'!$Y$2:$Z$854,2,FALSE), O35="Pará",((W35*0.15)+(X35*0.7))*VLOOKUP(P35,'MunicípiosEstados'!$AA$2:$AB$145,2,FALSE), O35="Paraíba",((W35*0.15)+(X35*0.7))*VLOOKUP(P35,'MunicípiosEstados'!$AC$2:$AD$224,2,FALSE), O35="Paraná",((W35*0.15)+(X35*0.7))*VLOOKUP(P35,'MunicípiosEstados'!$AE$2:$AF$400,2,FALSE), O35="Pernambuco",((W35*0.15)+(X35*0.7))*VLOOKUP(P35,'MunicípiosEstados'!$AG$2:$AH$186,2,FALSE), O35="Piauí",((W35*0.15)+(X35*0.7))*VLOOKUP(P35,'MunicípiosEstados'!$AI$2:$AJ$225,2,FALSE), O35="Rio Grande do Norte",((W35*0.15)+(X35*0.7))*VLOOKUP(P35,'MunicípiosEstados'!$AK$2:$AL$168,2,FALSE), O35="Rio Grande do Sul",((W35*0.15)+(X35*0.7))*VLOOKUP(P35,'MunicípiosEstados'!$AM$2:$AN$498,2,FALSE), O35="Rio de Janeiro",((W35*0.15)+(X35*0.7))*VLOOKUP(P35,'MunicípiosEstados'!$AO$2:$AP$93,2,FALSE), O35="Rondônia",((W35*0.15)+(X35*0.7))*VLOOKUP(P35,'MunicípiosEstados'!$AQ$2:$AR$53,2,FALSE), O35="Roraima",((W35*0.15)+(X35*0.7))*VLOOKUP(P35,'MunicípiosEstados'!$AS$2:$AT$16,2,FALSE), O35="Santa Catarina",((W35*0.15)+(X35*0.7))*VLOOKUP(P35,'MunicípiosEstados'!$AU$2:$AV$296,2,FALSE), O35="São Paulo",((W35*0.15)+(X35*0.7))*VLOOKUP(P35,'MunicípiosEstados'!$AW$2:$AX$646,2,FALSE), O35="Sergipe",((W35*0.15)+(X35*0.7))*VLOOKUP(P35,'MunicípiosEstados'!$AY$2:$AZ$76,2,FALSE), O35="Tocantins",((W35*0.15)+(X35*0.7))*VLOOKUP(P35,'MunicípiosEstados'!$BA$2:$BB$140,2,FALSE), O35="Exterior",((W35*0.15)+(X35*0.7))*VLOOKUP(P35,'MunicípiosEstados'!$BC$2:$BE$221,3,FALSE),TRUE,0 ) -> 2041.93 | AL35: =AK35+AJ35+AI35+AE35+AD35+AC35+AB35+AA35+Z35+Y35 -> 5041.93
A36: =ROW(A36)-1 -> 35 | B36: 45988.738 | C36: romeugair@idr.pr.gov.br | D36: A aprovar | E36: =VLOOKUP(G36,DiretoriaDepart.Coord.!$A$1:$C$72,2,FALSE) -> Extensão Rural | F36: =VLOOKUP(G36,DiretoriaDepart.Coord.!$A$1:$C$72,3,FALSE) -> Projetos e Cadeias Produtivas | G36: Café (Extensão Rural) | I36: Semana Internacional do Café | J36: Feira | K36: 8 | M36: A negociar | N36: 10 | O36: Minas Gerais | P36: Belo Horizonte | Q36: 45972.333 | R36: 45974.792 | S36: Não | T36: Presencial | U36: Feira de cafés especiais - Stand Paraná | V36: Neste evento se reúne as principais empresas nacionais e algumas mundiais que comercializam cafés especiais e máquinas para preparo de cafés especiais e afins. Também estão presentes com oferta de cafés para degustação todas as regiões cafeeiras do Brasil e de algumas do exterior. Evento indispensável para os técnicos que estão na área de cafés especiais e que apoiam as famílias cafeicultoras em abertura de nichos específicos de mercados com alta agregação de valor. Haverá um Stand do Governo do Paraná onde os extensionista no formato de revezamento organizarão e atenderão o público da feira. | W36: 86 | X36: 38 | Y36: 0 | Z36: 0 | AA36: 0 | AB36: 0 | AC36: 0 | AD36: 800 | AE36: 0 | AF36: Não | AG36: 5000 | AH36: Sim | AI36: =IF(AF36="Sim",INT((R36-Q36+1))*K36*VLOOKUP(P36,'Tabelas Auxiliares'!$A$1:$C$400,3,FALSE),0) -> 0 | AJ36: =(AG36/10)*7 -> 3500 | AK36: =IFS( O36="Acre",((W36*0.15)+(X36*0.7))*VLOOKUP(P36,'MunicípiosEstados'!$A$2:$B$23,2,FALSE), O36="Alagoas",((W36*0.15)+(X36*0.7))*VLOOKUP(P36,'MunicípiosEstados'!$C$2:$D$103,2,FALSE), O36="Amapá",((W36*0.15)+(X36*0.7))*VLOOKUP(P36,'MunicípiosEstados'!$E$2:$F$17,2,FALSE), O36="Amazonas",((W36*0.15)+(X36*0.7))*VLOOKUP(P36,'MunicípiosEstados'!$G$2:$H$63,2,FALSE), O36="Bahia",((W36*0.15)+(X36*0.7))*VLOOKUP(P36,'MunicípiosEstados'!$I$2:$J$418,2,FALSE), O36="Ceará",((W36*0.15)+(X36*0.7))*VLOOKUP(P36,'MunicípiosEstados'!$K$2:$L$185,2,FALSE), O36="Distrito Federal",((W36*0.15)+(X36*0.7))*VLOOKUP(P36,'MunicípiosEstados'!$M$2:$N$2,2,FALSE), O36="Espírito Santo",((W36*0.15)+(X36*0.7))*VLOOKUP(P36,'MunicípiosEstados'!$O$2:$P$79,2,FALSE), O36="Goiás",((W36*0.15)+(X36*0.7))*VLOOKUP(P36,'MunicípiosEstados'!$Q$2:$R$247,2,FALSE), O36="Maranhão",((W36*0.15)+(X36*0.7))*VLOOKUP(P36,'MunicípiosEstados'!$S$2:$T$218,2,FALSE), O36="Mato Grosso",((W36*0.15)+(X36*0.7))*VLOOKUP(P36,'MunicípiosEstados'!$U$2:$V$143,2,FALSE), O36="Mato Grosso do Sul",((W36*0.15)+(X36*0.7))*VLOOKUP(P36,'MunicípiosEstados'!$W$2:$X$80,2,FALSE), O36="Minas Gerais",((W36*0.15)+(X36*0.7))*VLOOKUP(P36,'MunicípiosEstados'!$Y$2:$Z$854,2,FALSE), O36="Pará",((W36*0.15)+(X36*0.7))*VLOOKUP(P36,'MunicípiosEstados'!$AA$2:$AB$145,2,FALSE), O36="Paraíba",((W36*0.15)+(X36*0.7))*VLOOKUP(P36,'MunicípiosEstados'!$AC$2:$AD$224,2,FALSE), O36="Paraná",((W36*0.15)+(X36*0.7))*VLOOKUP(P36,'MunicípiosEstados'!$AE$2:$AF$400,2,FALSE), O36="Pernambuco",((W36*0.15)+(X36*0.7))*VLOOKUP(P36,'MunicípiosEstados'!$AG$2:$AH$186,2,FALSE), O36="Piauí",((W36*0.15)+(X36*0.7))*VLOOKUP(P36,'MunicípiosEstados'!$AI$2:$AJ$225,2,FALSE), O36="Rio Grande do Norte",((W36*0.15)+(X36*0.7))*VLOOKUP(P36,'MunicípiosEstados'!$AK$2:$AL$168,2,FALSE), O36="Rio Grande do Sul",((W36*0.15)+(X36*0.7))*VLOOKUP(P36,'MunicípiosEstados'!$AM$2:$AN$498,2,FALSE), O36="Rio de Janeiro",((W36*0.15)+(X36*0.7))*VLOOKUP(P36,'MunicípiosEstados'!$AO$2:$AP$93,2,FALSE), O36="Rondônia",((W36*0.15)+(X36*0.7))*VLOOKUP(P36,'MunicípiosEstados'!$AQ$2:$AR$53,2,FALSE), O36="Roraima",((W36*0.15)+(X36*0.7))*VLOOKUP(P36,'MunicípiosEstados'!$AS$2:$AT$16,2,FALSE), O36="Santa Catarina",((W36*0.15)+(X36*0.7))*VLOOKUP(P36,'MunicípiosEstados'!$AU$2:$AV$296,2,FALSE), O36="São Paulo",((W36*0.15)+(X36*0.7))*VLOOKUP(P36,'MunicípiosEstados'!$AW$2:$AX$646,2,FALSE), O36="Sergipe",((W36*0.15)+(X36*0.7))*VLOOKUP(P36,'MunicípiosEstados'!$AY$2:$AZ$76,2,FALSE), O36="Tocantins",((W36*0.15)+(X36*0.7))*VLOOKUP(P36,'MunicípiosEstados'!$BA$2:$BB$140,2,FALSE), O36="Exterior",((W36*0.15)+(X36*0.7))*VLOOKUP(P36,'MunicípiosEstados'!$BC$2:$BE$221,3,FALSE),TRUE,0 ) -> 14664.77 | AL36: =AK36+AJ36+AI36+AE36+AD36+AC36+AB36+AA36+Z36+Y36 -> 18964.77
A37: =ROW(A37)-1 -> 36 | B37: 45989.589 | C37: romeugair@idr.pr.gov.br | D37: A aprovar | E37: =VLOOKUP(G37,DiretoriaDepart.Coord.!$A$1:$C$72,2,FALSE) -> Extensão Rural | F37: =VLOOKUP(G37,DiretoriaDepart.Coord.!$A$1:$C$72,3,FALSE) -> Projetos e Cadeias Produtivas | G37: Café (Extensão Rural) | I37: Fenicafé | J37: Feira | K37: 2 | M37: Não há | N37: 0 | O37: Minas Gerais | P37: Araguari | Q37: 45760.708 | R37: 45763.708 | S37: Não | T37: Presencial | U37: Cafeicultura Irrigada | V37: A Fenicafé é uma feira de implementos, máquinas, serviços e tecnologia, aliados a muita informação. XXVI Encontro Nacional de Irrigação da Cafeicultura do Cerrado e a XXV Feira de Irrigação em Café do Brasil. A importância dos extensionistas em buscar qualificação em irrigação de café. | W37: 20 | X37: 8 | Y37: 600 | Z37: 0 | AA37: 0 | AB37: 0 | AC37: 0 | AD37: 300 | AE37: 0 | AF37: Não | AG37: 2000 | AH37: Não | AI37: =IF(AF37="Sim",INT((R37-Q37+1))*K37*VLOOKUP(P37,'Tabelas Auxiliares'!$A$1:$C$400,3,FALSE),0) -> 0 | AJ37: =(AG37/10)*7 -> 1400 | AK37: =IFS( O37="Acre",((W37*0.15)+(X37*0.7))*VLOOKUP(P37,'MunicípiosEstados'!$A$2:$B$23,2,FALSE), O37="Alagoas",((W37*0.15)+(X37*0.7))*VLOOKUP(P37,'MunicípiosEstados'!$C$2:$D$103,2,FALSE), O37="Amapá",((W37*0.15)+(X37*0.7))*VLOOKUP(P37,'MunicípiosEstados'!$E$2:$F$17,2,FALSE), O37="Amazonas",((W37*0.15)+(X37*0.7))*VLOOKUP(P37,'MunicípiosEstados'!$G$2:$H$63,2,FALSE), O37="Bahia",((W37*0.15)+(X37*0.7))*VLOOKUP(P37,'MunicípiosEstados'!$I$2:$J$418,2,FALSE), O37="Ceará",((W37*0.15)+(X37*0.7))*VLOOKUP(P37,'MunicípiosEstados'!$K$2:$L$185,2,FALSE), O37="Distrito Federal",((W37*0.15)+(X37*0.7))*VLOOKUP(P37,'MunicípiosEstados'!$M$2:$N$2,2,FALSE), O37="Espírito Santo",((W37*0.15)+(X37*0.7))*VLOOKUP(P37,'MunicípiosEstados'!$O$2:$P$79,2,FALSE), O37="Goiás",((W37*0.15)+(X37*0.7))*VLOOKUP(P37,'MunicípiosEstados'!$Q$2:$R$247,2,FALSE), O37="Maranhão",((W37*0.15)+(X37*0.7))*VLOOKUP(P37,'MunicípiosEstados'!$S$2:$T$218,2,FALSE), O37="Mato Grosso",((W37*0.15)+(X37*0.7))*VLOOKUP(P37,'MunicípiosEstados'!$U$2:$V$143,2,FALSE), O37="Mato Grosso do Sul",((W37*0.15)+(X37*0.7))*VLOOKUP(P37,'MunicípiosEstados'!$W$2:$X$80,2,FALSE), O37="Minas Gerais",((W37*0.15)+(X37*0.7))*VLOOKUP(P37,'MunicípiosEstados'!$Y$2:$Z$854,2,FALSE), O37="Pará",((W37*0.15)+(X37*0.7))*VLOOKUP(P37,'MunicípiosEstados'!$AA$2:$AB$145,2,FALSE), O37="Paraíba",((W37*0.15)+(X37*0.7))*VLOOKUP(P37,'MunicípiosEstados'!$AC$2:$AD$224,2,FALSE), O37="Paraná",((W37*0.15)+(X37*0.7))*VLOOKUP(P37,'MunicípiosEstados'!$AE$2:$AF$400,2,FALSE), O37="Pernambuco",((W37*0.15)+(X37*0.7))*VLOOKUP(P37,'MunicípiosEstados'!$AG$2:$AH$186,2,FALSE), O37="Piauí",((W37*0.15)+(X37*0.7))*VLOOKUP(P37,'MunicípiosEstados'!$AI$2:$AJ$225,2,FALSE), O37="Rio Grande do Norte",((W37*0.15)+(X37*0.7))*VLOOKUP(P37,'MunicípiosEstados'!$AK$2:$AL$168,2,FALSE), O37="Rio Grande do Sul",((W37*0.15)+(X37*0.7))*VLOOKUP(P37,'MunicípiosEstados'!$AM$2:$AN$498,2,FALSE), O37="Rio de Janeiro",((W37*0.15)+(X37*0.7))*VLOOKUP(P37,'MunicípiosEstados'!$AO$2:$AP$93,2,FALSE), O37="Rondônia",((W37*0.15)+(X37*0.7))*VLOOKUP(P37,'MunicípiosEstados'!$AQ$2:$AR$53,2,FALSE), O37="Roraima",((W37*0.15)+(X37*0.7))*VLOOKUP(P37,'MunicípiosEstados'!$AS$2:$AT$16,2,FALSE), O37="Santa Catarina",((W37*0.15)+(X37*0.7))*VLOOKUP(P37,'MunicípiosEstados'!$AU$2:$AV$296,2,FALSE), O37="São Paulo",((W37*0.15)+(X37*0.7))*VLOOKUP(P37,'MunicípiosEstados'!$AW$2:$AX$646,2,FALSE), O37="Sergipe",((W37*0.15)+(X37*0.7))*VLOOKUP(P37,'MunicípiosEstados'!$AY$2:$AZ$76,2,FALSE), O37="Tocantins",((W37*0.15)+(X37*0.7))*VLOOKUP(P37,'MunicípiosEstados'!$BA$2:$BB$140,2,FALSE), O37="Exterior",((W37*0.15)+(X37*0.7))*VLOOKUP(P37,'MunicípiosEstados'!$BC$2:$BE$221,3,FALSE),TRUE,0 ) -> 2498.73 | AL37: =AK37+AJ37+AI37+AE37+AD37+AC37+AB37+AA37+Z37+Y37 -> 4798.73
A38: =ROW(A38)-1 -> 37 | B38: 45988.753 | C38: romeugair@idr.pr.gov.br | D38: A aprovar | E38: =VLOOKUP(G38,DiretoriaDepart.Coord.!$A$1:$C$72,2,FALSE) -> Extensão Rural | F38: =VLOOKUP(G38,DiretoriaDepart.Coord.!$A$1:$C$72,3,FALSE) -> Projetos e Cadeias Produtivas | G38: Café (Extensão Rural) | I38: Congresso Brasileiro de Café | J38: Congresso | K38: 3 | M38: Não há | N38: 0 | O38: Minas Gerais | P38: Varginha | Q38: 45931.333 | R38: 45933.708 | S38: Não | T38: Presencial | U38: Apresentação de pesquisas cafeeiras | V38: No Congresso Brasileiro de Pesquisas Cafeeiras são divulgados todos os resultados das pesquisas em café realizada no Brasil. Precisamos sempre ter alguns técnicos da equipe participando para se inteirar dos resultados das pesquisas recentes, assim melhorar nosso atendimento ao público assistido e atendido. | W38: 30 | X38: 12 | Y38: 1500 | Z38: 0 | AA38: 0 | AB38: 0 | AC38: 0 | AD38: 350 | AE38: 0 | AF38: Não | AG38: 2000 | AH38: Sim | AI38: =IF(AF38="Sim",INT((R38-Q38+1))*K38*VLOOKUP(P38,'Tabelas Auxiliares'!$A$1:$C$400,3,FALSE),0) -> 0 | AJ38: =(AG38/10)*7 -> 1400 | AK38: =IFS( O38="Acre",((W38*0.15)+(X38*0.7))*VLOOKUP(P38,'MunicípiosEstados'!$A$2:$B$23,2,FALSE), O38="Alagoas",((W38*0.15)+(X38*0.7))*VLOOKUP(P38,'MunicípiosEstados'!$C$2:$D$103,2,FALSE), O38="Amapá",((W38*0.15)+(X38*0.7))*VLOOKUP(P38,'MunicípiosEstados'!$E$2:$F$17,2,FALSE), O38="Amazonas",((W38*0.15)+(X38*0.7))*VLOOKUP(P38,'MunicípiosEstados'!$G$2:$H$63,2,FALSE), O38="Bahia",((W38*0.15)+(X38*0.7))*VLOOKUP(P38,'MunicípiosEstados'!$I$2:$J$418,2,FALSE), O38="Ceará",((W38*0.15)+(X38*0.7))*VLOOKUP(P38,'MunicípiosEstados'!$K$2:$L$185,2,FALSE), O38="Distrito Federal",((W38*0.15)+(X38*0.7))*VLOOKUP(P38,'MunicípiosEstados'!$M$2:$N$2,2,FALSE), O38="Espírito Santo",((W38*0.15)+(X38*0.7))*VLOOKUP(P38,'MunicípiosEstados'!$O$2:$P$79,2,FALSE), O38="Goiás",((W38*0.15)+(X38*0.7))*VLOOKUP(P38,'MunicípiosEstados'!$Q$2:$R$247,2,FALSE), O38="Maranhão",((W38*0.15)+(X38*0.7))*VLOOKUP(P38,'MunicípiosEstados'!$S$2:$T$218,2,FALSE), O38="Mato Grosso",((W38*0.15)+(X38*0.7))*VLOOKUP(P38,'MunicípiosEstados'!$U$2:$V$143,2,FALSE), O38="Mato Grosso do Sul",((W38*0.15)+(X38*0.7))*VLOOKUP(P38,'MunicípiosEstados'!$W$2:$X$80,2,FALSE), O38="Minas Gerais",((W38*0.15)+(X38*0.7))*VLOOKUP(P38,'MunicípiosEstados'!$Y$2:$Z$854,2,FALSE), O38="Pará",((W38*0.15)+(X38*0.7))*VLOOKUP(P38,'MunicípiosEstados'!$AA$2:$AB$145,2,FALSE), O38="Paraíba",((W38*0.15)+(X38*0.7))*VLOOKUP(P38,'MunicípiosEstados'!$AC$2:$AD$224,2,FALSE), O38="Paraná",((W38*0.15)+(X38*0.7))*VLOOKUP(P38,'MunicípiosEstados'!$AE$2:$AF$400,2,FALSE), O38="Pernambuco",((W38*0.15)+(X38*0.7))*VLOOKUP(P38,'MunicípiosEstados'!$AG$2:$AH$186,2,FALSE), O38="Piauí",((W38*0.15)+(X38*0.7))*VLOOKUP(P38,'MunicípiosEstados'!$AI$2:$AJ$225,2,FALSE), O38="Rio Grande do Norte",((W38*0.15)+(X38*0.7))*VLOOKUP(P38,'MunicípiosEstados'!$AK$2:$AL$168,2,FALSE), O38="Rio Grande do Sul",((W38*0.15)+(X38*0.7))*VLOOKUP(P38,'MunicípiosEstados'!$AM$2:$AN$498,2,FALSE), O38="Rio de Janeiro",((W38*0.15)+(X38*0.7))*VLOOKUP(P38,'MunicípiosEstados'!$AO$2:$AP$93,2,FALSE), O38="Rondônia",((W38*0.15)+(X38*0.7))*VLOOKUP(P38,'MunicípiosEstados'!$AQ$2:$AR$53,2,FALSE), O38="Roraima",((W38*0.15)+(X38*0.7))*VLOOKUP(P38,'MunicípiosEstados'!$AS$2:$AT$16,2,FALSE), O38="Santa Catarina",((W38*0.15)+(X38*0.7))*VLOOKUP(P38,'MunicípiosEstados'!$AU$2:$AV$296,2,FALSE), O38="São Paulo",((W38*0.15)+(X38*0.7))*VLOOKUP(P38,'MunicípiosEstados'!$AW$2:$AX$646,2,FALSE), O38="Sergipe",((W38*0.15)+(X38*0.7))*VLOOKUP(P38,'MunicípiosEstados'!$AY$2:$AZ$76,2,FALSE), O38="Tocantins",((W38*0.15)+(X38*0.7))*VLOOKUP(P38,'MunicípiosEstados'!$BA$2:$BB$140,2,FALSE), O38="Exterior",((W38*0.15)+(X38*0.7))*VLOOKUP(P38,'MunicípiosEstados'!$BC$2:$BE$221,3,FALSE),TRUE,0 ) -> 3748.095 | AL38: =AK38+AJ38+AI38+AE38+AD38+AC38+AB38+AA38+Z38+Y38 -> 6998.095
A39: =ROW(A39)-1 -> 38 | B39: 45989.472 | C39: ito@idr.pr.gov.br | D39: A aprovar | E39: =VLOOKUP(G39,DiretoriaDepart.Coord.!$A$1:$C$72,2,FALSE) -> Pesquisa e Inovação | F39: =VLOOKUP(G39,DiretoriaDepart.Coord.!$A$1:$C$72,3,FALSE) -> Pesquisa e Capacitação | G39: Proteção de Plantas (Pesquisa) | I39: 50º Congresso Brasileiro de Pesquisas Cafeeiras | J39: Congresso | K39: 1 | L39: Dhalton Shiguer Ito | M39: Procafé | N39: 0 | O39: Minas Gerais | P39: Poços de Caldas | Q39: 45935.333 | R39: 45938.708 | S39: Não | T39: Presencial | U39: Pesquisa em Cafeicultura | V39: Este é principal evento relacionado à pesquisa em cafeicultura. Reúne os maiores especialistas da área para discutir atualidades e apresentar resultados de pesquisa. Serão apresentados resultados de pesquisas com nematoides no cafeeiro, provenientes de projetos financiados pelo Consórcio Pesquisa Café. É uma grande oportunidade para atualização de conhecimentos. | W39: 12 | X39: 5 | Y39: 200 | Z39: 0 | AA39: 0 | AB39: 0 | AC39: 0 | AD39: 300 | AE39: 0 | AF39: Não | AG39: 1200 | AH39: Não | AI39: =IF(AF39="Sim",INT((R39-Q39+1))*K39*VLOOKUP(P39,'Tabelas Auxiliares'!$A$1:$C$400,3,FALSE),0) -> 0 | AJ39: =(AG39/10)*7 -> 840 | AK39: =IFS( O39="Acre",((W39*0.15)+(X39*0.7))*VLOOKUP(P39,'MunicípiosEstados'!$A$2:$B$23,2,FALSE), O39="Alagoas",((W39*0.15)+(X39*0.7))*VLOOKUP(P39,'MunicípiosEstados'!$C$2:$D$103,2,FALSE), O39="Amapá",((W39*0.15)+(X39*0.7))*VLOOKUP(P39,'MunicípiosEstados'!$E$2:$F$17,2,FALSE), O39="Amazonas",((W39*0.15)+(X39*0.7))*VLOOKUP(P39,'MunicípiosEstados'!$G$2:$H$63,2,FALSE), O39="Bahia",((W39*0.15)+(X39*0.7))*VLOOKUP(P39,'MunicípiosEstados'!$I$2:$J$418,2,FALSE), O39="Ceará",((W39*0.15)+(X39*0.7))*VLOOKUP(P39,'MunicípiosEstados'!$K$2:$L$185,2,FALSE), O39="Distrito Federal",((W39*0.15)+(X39*0.7))*VLOOKUP(P39,'MunicípiosEstados'!$M$2:$N$2,2,FALSE), O39="Espírito Santo",((W39*0.15)+(X39*0.7))*VLOOKUP(P39,'MunicípiosEstados'!$O$2:$P$79,2,FALSE), O39="Goiás",((W39*0.15)+(X39*0.7))*VLOOKUP(P39,'MunicípiosEstados'!$Q$2:$R$247,2,FALSE), O39="Maranhão",((W39*0.15)+(X39*0.7))*VLOOKUP(P39,'MunicípiosEstados'!$S$2:$T$218,2,FALSE), O39="Mato Grosso",((W39*0.15)+(X39*0.7))*VLOOKUP(P39,'MunicípiosEstados'!$U$2:$V$143,2,FALSE), O39="Mato Grosso do Sul",((W39*0.15)+(X39*0.7))*VLOOKUP(P39,'MunicípiosEstados'!$W$2:$X$80,2,FALSE), O39="Minas Gerais",((W39*0.15)+(X39*0.7))*VLOOKUP(P39,'MunicípiosEstados'!$Y$2:$Z$854,2,FALSE), O39="Pará",((W39*0.15)+(X39*0.7))*VLOOKUP(P39,'MunicípiosEstados'!$AA$2:$AB$145,2,FALSE), O39="Paraíba",((W39*0.15)+(X39*0.7))*VLOOKUP(P39,'MunicípiosEstados'!$AC$2:$AD$224,2,FALSE), O39="Paraná",((W39*0.15)+(X39*0.7))*VLOOKUP(P39,'MunicípiosEstados'!$AE$2:$AF$400,2,FALSE), O39="Pernambuco",((W39*0.15)+(X39*0.7))*VLOOKUP(P39,'MunicípiosEstados'!$AG$2:$AH$186,2,FALSE), O39="Piauí",((W39*0.15)+(X39*0.7))*VLOOKUP(P39,'MunicípiosEstados'!$AI$2:$AJ$225,2,FALSE), O39="Rio Grande do Norte",((W39*0.15)+(X39*0.7))*VLOOKUP(P39,'MunicípiosEstados'!$AK$2:$AL$168,2,FALSE), O39="Rio Grande do Sul",((W39*0.15)+(X39*0.7))*VLOOKUP(P39,'MunicípiosEstados'!$AM$2:$AN$498,2,FALSE), O39="Rio de Janeiro",((W39*0.15)+(X39*0.7))*VLOOKUP(P39,'MunicípiosEstados'!$AO$2:$AP$93,2,FALSE), O39="Rondônia",((W39*0.15)+(X39*0.7))*VLOOKUP(P39,'MunicípiosEstados'!$AQ$2:$AR$53,2,FALSE), O39="Roraima",((W39*0.15)+(X39*0.7))*VLOOKUP(P39,'MunicípiosEstados'!$AS$2:$AT$16,2,FALSE), O39="Santa Catarina",((W39*0.15)+(X39*0.7))*VLOOKUP(P39,'MunicípiosEstados'!$AU$2:$AV$296,2,FALSE), O39="São Paulo",((W39*0.15)+(X39*0.7))*VLOOKUP(P39,'MunicípiosEstados'!$AW$2:$AX$646,2,FALSE), O39="Sergipe",((W39*0.15)+(X39*0.7))*VLOOKUP(P39,'MunicípiosEstados'!$AY$2:$AZ$76,2,FALSE), O39="Tocantins",((W39*0.15)+(X39*0.7))*VLOOKUP(P39,'MunicípiosEstados'!$BA$2:$BB$140,2,FALSE), O39="Exterior",((W39*0.15)+(X39*0.7))*VLOOKUP(P39,'MunicípiosEstados'!$BC$2:$BE$221,3,FALSE),TRUE,0 ) -> 1539.915 | AL39: =AK39+AJ39+AI39+AE39+AD39+AC39+AB39+AA39+Z39+Y39 -> 2879.915
A40: =ROW(A40)-1 -> 39 | B40: 45989.722 | C40: patriciasantoro@idr.pr.gov.br | D40: A aprovar | E40: =VLOOKUP(G40,DiretoriaDepart.Coord.!$A$1:$C$72,2,FALSE) -> Pesquisa e Inovação | F40: =VLOOKUP(G40,DiretoriaDepart.Coord.!$A$1:$C$72,3,FALSE) -> Pesquisa e Capacitação | G40: Programa de Café e Cultivos Industriais (Pesquisa) | I40: Semana Internacional do Café | J40: Feira | K40: 1 | L40: Patricia Helena Santoro | M40: Não há | N40: 1 | O40: Minas Gerais | P40: Belo Horizonte | Q40: 45972.333 | R40: 45974.708 | S40: Não | T40: Presencial | U40: Na feira são apresentadas inovações tecnológicas sobre qualidade do café. | V40: A participação na Semana Internacional do Café 2026 é fundamental para o fortalecimento das ações de pesquisa e articulação institucional relacionadas à cafeicultura paranaense. O evento reúne os principais pesquisadores, instituições e lideranças do setor, permitindo acesso direto às inovações científicas, tecnológicas que orientam as tendências de cafés especiais no Brasil e no mundo. Estar presente na SIC possibilitará atualizar conhecimentos técnicos, ampliar o repertório metodológico para análises sensoriais e físico-químicas — especialmente relevantes para os projetos em andamento e estabelecer parcerias estratégicas com universidades e centros de pesquisa, além de fortalecer a representação institucional e identificar oportunidades para futuros projetos, capacitações e cooperações técnicas. | W40: 10 | X40: 5 | Y40: 200 | Z40: 0 | AA40: 2000 | AB40: 0 | AC40: 400 | AD40: 0 | AE40: 0 | AF40: Não | AG40: 00 | AH40: Não | AI40: =IF(AF40="Sim",INT((R40-Q40+1))*K40*VLOOKUP(P40,'Tabelas Auxiliares'!$A$1:$C$400,3,FALSE),0) -> 0 | AJ40: =(AG40/10)*7 -> 0 | AK40: =IFS( O40="Acre",((W40*0.15)+(X40*0.7))*VLOOKUP(P40,'MunicípiosEstados'!$A$2:$B$23,2,FALSE), O40="Alagoas",((W40*0.15)+(X40*0.7))*VLOOKUP(P40,'MunicípiosEstados'!$C$2:$D$103,2,FALSE), O40="Amapá",((W40*0.15)+(X40*0.7))*VLOOKUP(P40,'MunicípiosEstados'!$E$2:$F$17,2,FALSE), O40="Amazonas",((W40*0.15)+(X40*0.7))*VLOOKUP(P40,'MunicípiosEstados'!$G$2:$H$63,2,FALSE), O40="Bahia",((W40*0.15)+(X40*0.7))*VLOOKUP(P40,'MunicípiosEstados'!$I$2:$J$418,2,FALSE), O40="Ceará",((W40*0.15)+(X40*0.7))*VLOOKUP(P40,'MunicípiosEstados'!$K$2:$L$185,2,FALSE), O40="Distrito Federal",((W40*0.15)+(X40*0.7))*VLOOKUP(P40,'MunicípiosEstados'!$M$2:$N$2,2,FALSE), O40="Espírito Santo",((W40*0.15)+(X40*0.7))*VLOOKUP(P40,'MunicípiosEstados'!$O$2:$P$79,2,FALSE), O40="Goiás",((W40*0.15)+(X40*0.7))*VLOOKUP(P40,'MunicípiosEstados'!$Q$2:$R$247,2,FALSE), O40="Maranhão",((W40*0.15)+(X40*0.7))*VLOOKUP(P40,'MunicípiosEstados'!$S$2:$T$218,2,FALSE), O40="Mato Grosso",((W40*0.15)+(X40*0.7))*VLOOKUP(P40,'MunicípiosEstados'!$U$2:$V$143,2,FALSE), O40="Mato Grosso do Sul",((W40*0.15)+(X40*0.7))*VLOOKUP(P40,'MunicípiosEstados'!$W$2:$X$80,2,FALSE), O40="Minas Gerais",((W40*0.15)+(X40*0.7))*VLOOKUP(P40,'MunicípiosEstados'!$Y$2:$Z$854,2,FALSE), O40="Pará",((W40*0.15)+(X40*0.7))*VLOOKUP(P40,'MunicípiosEstados'!$AA$2:$AB$145,2,FALSE), O40="Paraíba",((W40*0.15)+(X40*0.7))*VLOOKUP(P40,'MunicípiosEstados'!$AC$2:$AD$224,2,FALSE), O40="Paraná",((W40*0.15)+(X40*0.7))*VLOOKUP(P40,'MunicípiosEstados'!$AE$2:$AF$400,2,FALSE), O40="Pernambuco",((W40*0.15)+(X40*0.7))*VLOOKUP(P40,'MunicípiosEstados'!$AG$2:$AH$186,2,FALSE), O40="Piauí",((W40*0.15)+(X40*0.7))*VLOOKUP(P40,'MunicípiosEstados'!$AI$2:$AJ$225,2,FALSE), O40="Rio Grande do Norte",((W40*0.15)+(X40*0.7))*VLOOKUP(P40,'MunicípiosEstados'!$AK$2:$AL$168,2,FALSE), O40="Rio Grande do Sul",((W40*0.15)+(X40*0.7))*VLOOKUP(P40,'MunicípiosEstados'!$AM$2:$AN$498,2,FALSE), O40="Rio de Janeiro",((W40*0.15)+(X40*0.7))*VLOOKUP(P40,'MunicípiosEstados'!$AO$2:$AP$93,2,FALSE), O40="Rondônia",((W40*0.15)+(X40*0.7))*VLOOKUP(P40,'MunicípiosEstados'!$AQ$2:$AR$53,2,FALSE), O40="Roraima",((W40*0.15)+(X40*0.7))*VLOOKUP(P40,'MunicípiosEstados'!$AS$2:$AT$16,2,FALSE), O40="Santa Catarina",((W40*0.15)+(X40*0.7))*VLOOKUP(P40,'MunicípiosEstados'!$AU$2:$AV$296,2,FALSE), O40="São Paulo",((W40*0.15)+(X40*0.7))*VLOOKUP(P40,'MunicípiosEstados'!$AW$2:$AX$646,2,FALSE), O40="Sergipe",((W40*0.15)+(X40*0.7))*VLOOKUP(P40,'MunicípiosEstados'!$AY$2:$AZ$76,2,FALSE), O40="Tocantins",((W40*0.15)+(X40*0.7))*VLOOKUP(P40,'MunicípiosEstados'!$BA$2:$BB$140,2,FALSE), O40="Exterior",((W40*0.15)+(X40*0.7))*VLOOKUP(P40,'MunicípiosEstados'!$BC$2:$BE$221,3,FALSE),TRUE,0 ) -> 1856.3 | AL40: =AK40+AJ40+AI40+AE40+AD40+AC40+AB40+AA40+Z40+Y40 -> 4456.3
A41: =ROW(A41)-1 -> 40 | B41: 45992.688 | C41: ito@idr.pr.gov.br | D41: A aprovar | E41: =VLOOKUP(G41,DiretoriaDepart.Coord.!$A$1:$C$72,2,FALSE) -> Pesquisa e Inovação | F41: =VLOOKUP(G41,DiretoriaDepart.Coord.!$A$1:$C$72,3,FALSE) -> Pesquisa e Capacitação | G41: Proteção de Plantas (Pesquisa) | I41: Semana Internacional do Café | J41: Feira | K41: 1 | M41: Governo de Minas Gerais | N41: 0 | O41: Minas Gerais | P41: Belo Horizonte | Q41: 45972.417 | R41: 45974.75 | S41: Sim | T41: Presencial | U41: Cafeicultura | V41: É o maior evento direcionado à informação sobre toda a cadeia do café, com diversos conteúdos em nível internacional. É uma grande oportunidade na atualização do conhecimento, principalmente em temas relacionados à cafeicultura sustentável. A presença de diversas empresas e instituições públicas no evento também possibilita o contato e a formação de possíveis novas parcerias de trabalho. As informações adquiridas serão aplicadas diretamente visando melhorar o conhecimento, proporcionando melhores resultados na pesquisa. | W41: 10 | X41: 4 | Y41: 0 | Z41: 0 | AA41: 2000 | AB41: 0 | AC41: 400 | AD41: 0 | AE41: 0 | AF41: Não | AG41: 0 | AH41: Não | AI41: =IF(AF41="Sim",INT((R41-Q41+1))*K41*VLOOKUP(P41,'Tabelas Auxiliares'!$A$1:$C$400,3,FALSE),0) -> 0 | AJ41: =(AG41/10)*7 -> 0 | AK41: =IFS( O41="Acre",((W41*0.15)+(X41*0.7))*VLOOKUP(P41,'MunicípiosEstados'!$A$2:$B$23,2,FALSE), O41="Alagoas",((W41*0.15)+(X41*0.7))*VLOOKUP(P41,'MunicípiosEstados'!$C$2:$D$103,2,FALSE), O41="Amapá",((W41*0.15)+(X41*0.7))*VLOOKUP(P41,'MunicípiosEstados'!$E$2:$F$17,2,FALSE), O41="Amazonas",((W41*0.15)+(X41*0.7))*VLOOKUP(P41,'MunicípiosEstados'!$G$2:$H$63,2,FALSE), O41="Bahia",((W41*0.15)+(X41*0.7))*VLOOKUP(P41,'MunicípiosEstados'!$I$2:$J$418,2,FALSE), O41="Ceará",((W41*0.15)+(X41*0.7))*VLOOKUP(P41,'MunicípiosEstados'!$K$2:$L$185,2,FALSE), O41="Distrito Federal",((W41*0.15)+(X41*0.7))*VLOOKUP(P41,'MunicípiosEstados'!$M$2:$N$2,2,FALSE), O41="Espírito Santo",((W41*0.15)+(X41*0.7))*VLOOKUP(P41,'MunicípiosEstados'!$O$2:$P$79,2,FALSE), O41="Goiás",((W41*0.15)+(X41*0.7))*VLOOKUP(P41,'MunicípiosEstados'!$Q$2:$R$247,2,FALSE), O41="Maranhão",((W41*0.15)+(X41*0.7))*VLOOKUP(P41,'MunicípiosEstados'!$S$2:$T$218,2,FALSE), O41="Mato Grosso",((W41*0.15)+(X41*0.7))*VLOOKUP(P41,'MunicípiosEstados'!$U$2:$V$143,2,FALSE), O41="Mato Grosso do Sul",((W41*0.15)+(X41*0.7))*VLOOKUP(P41,'MunicípiosEstados'!$W$2:$X$80,2,FALSE), O41="Minas Gerais",((W41*0.15)+(X41*0.7))*VLOOKUP(P41,'MunicípiosEstados'!$Y$2:$Z$854,2,FALSE), O41="Pará",((W41*0.15)+(X41*0.7))*VLOOKUP(P41,'MunicípiosEstados'!$AA$2:$AB$145,2,FALSE), O41="Paraíba",((W41*0.15)+(X41*0.7))*VLOOKUP(P41,'MunicípiosEstados'!$AC$2:$AD$224,2,FALSE), O41="Paraná",((W41*0.15)+(X41*0.7))*VLOOKUP(P41,'MunicípiosEstados'!$AE$2:$AF$400,2,FALSE), O41="Pernambuco",((W41*0.15)+(X41*0.7))*VLOOKUP(P41,'MunicípiosEstados'!$AG$2:$AH$186,2,FALSE), O41="Piauí",((W41*0.15)+(X41*0.7))*VLOOKUP(P41,'MunicípiosEstados'!$AI$2:$AJ$225,2,FALSE), O41="Rio Grande do Norte",((W41*0.15)+(X41*0.7))*VLOOKUP(P41,'MunicípiosEstados'!$AK$2:$AL$168,2,FALSE), O41="Rio Grande do Sul",((W41*0.15)+(X41*0.7))*VLOOKUP(P41,'MunicípiosEstados'!$AM$2:$AN$498,2,FALSE), O41="Rio de Janeiro",((W41*0.15)+(X41*0.7))*VLOOKUP(P41,'MunicípiosEstados'!$AO$2:$AP$93,2,FALSE), O41="Rondônia",((W41*0.15)+(X41*0.7))*VLOOKUP(P41,'MunicípiosEstados'!$AQ$2:$AR$53,2,FALSE), O41="Roraima",((W41*0.15)+(X41*0.7))*VLOOKUP(P41,'MunicípiosEstados'!$AS$2:$AT$16,2,FALSE), O41="Santa Catarina",((W41*0.15)+(X41*0.7))*VLOOKUP(P41,'MunicípiosEstados'!$AU$2:$AV$296,2,FALSE), O41="São Paulo",((W41*0.15)+(X41*0.7))*VLOOKUP(P41,'MunicípiosEstados'!$AW$2:$AX$646,2,FALSE), O41="Sergipe",((W41*0.15)+(X41*0.7))*VLOOKUP(P41,'MunicípiosEstados'!$AY$2:$AZ$76,2,FALSE), O41="Tocantins",((W41*0.15)+(X41*0.7))*VLOOKUP(P41,'MunicípiosEstados'!$BA$2:$BB$140,2,FALSE), O41="Exterior",((W41*0.15)+(X41*0.7))*VLOOKUP(P41,'MunicípiosEstados'!$BC$2:$BE$221,3,FALSE),TRUE,0 ) -> 1596.418 | AL41: =AK41+AJ41+AI41+AE41+AD41+AC41+AB41+AA41+Z41+Y41 -> 3996.418
A42: =ROW(A42)-1 -> 41 | B42: 45998.82 | C42: eduardosantos@idr.pr.gov.br | D42: A aprovar | E42: =VLOOKUP(G42,DiretoriaDepart.Coord.!$A$1:$C$72,2,FALSE) -> Extensão Rural | F42: =VLOOKUP(G42,DiretoriaDepart.Coord.!$A$1:$C$72,3,FALSE) -> Projetos e Cadeias Produtivas | G42: Fruticultura (Extensão Rural) | I42: frutas vermelhas (amora preta, framboesa, morango e mirtilo)) | J42: Visita Técnica | K42: 09 | M42: Emater MG | N42: 03 | O42: Minas Gerais | P42: Senador Amaral | Q42: 45915.354 | R42: 45917.708 | S42: Não | T42: Presencial | U42: Produção a comercialização de frutas vermelhas (Mirtilo, morango, amora preta e framboesa) | V42: Estas frutas vermelhas estão em expansão, porem com problemas de organização da cadeia produtiva. Há fomentos de forma integrada com agroindústria e de forma independente. Porem faltando estrutura de armazenagem e recebimento. Como ainda desconhecimento da frutas como negocio. Ir num dos principais polos de produção do país, com a visita principais compradores busca alianças estratégicas para desenvolvimento da atividade, aproveitando o conhecimento acumulado. | W42: 90 | X42: 45 | Y42: 0 | Z42: 0 | AA42: 0 | AB42: 0 | AC42: 0 | AD42: 0 | AE42: 0 | AF42: Não | AG42: 5000 | AH42: Sim | AI42: =IF(AF42="Sim",INT((R42-Q42+1))*K42*VLOOKUP(P42,'Tabelas Auxiliares'!$A$1:$C$400,3,FALSE),0) -> 0 | AJ42: =(AG42/10)*7 -> 3500 | AK42: =IFS( O42="Acre",((W42*0.15)+(X42*0.7))*VLOOKUP(P42,'MunicípiosEstados'!$A$2:$B$23,2,FALSE), O42="Alagoas",((W42*0.15)+(X42*0.7))*VLOOKUP(P42,'MunicípiosEstados'!$C$2:$D$103,2,FALSE), O42="Amapá",((W42*0.15)+(X42*0.7))*VLOOKUP(P42,'MunicípiosEstados'!$E$2:$F$17,2,FALSE), O42="Amazonas",((W42*0.15)+(X42*0.7))*VLOOKUP(P42,'MunicípiosEstados'!$G$2:$H$63,2,FALSE), O42="Bahia",((W42*0.15)+(X42*0.7))*VLOOKUP(P42,'MunicípiosEstados'!$I$2:$J$418,2,FALSE), O42="Ceará",((W42*0.15)+(X42*0.7))*VLOOKUP(P42,'MunicípiosEstados'!$K$2:$L$185,2,FALSE), O42="Distrito Federal",((W42*0.15)+(X42*0.7))*VLOOKUP(P42,'MunicípiosEstados'!$M$2:$N$2,2,FALSE), O42="Espírito Santo",((W42*0.15)+(X42*0.7))*VLOOKUP(P42,'MunicípiosEstados'!$O$2:$P$79,2,FALSE), O42="Goiás",((W42*0.15)+(X42*0.7))*VLOOKUP(P42,'MunicípiosEstados'!$Q$2:$R$247,2,FALSE), O42="Maranhão",((W42*0.15)+(X42*0.7))*VLOOKUP(P42,'MunicípiosEstados'!$S$2:$T$218,2,FALSE), O42="Mato Grosso",((W42*0.15)+(X42*0.7))*VLOOKUP(P42,'MunicípiosEstados'!$U$2:$V$143,2,FALSE), O42="Mato Grosso do Sul",((W42*0.15)+(X42*0.7))*VLOOKUP(P42,'MunicípiosEstados'!$W$2:$X$80,2,FALSE), O42="Minas Gerais",((W42*0.15)+(X42*0.7))*VLOOKUP(P42,'MunicípiosEstados'!$Y$2:$Z$854,2,FALSE), O42="Pará",((W42*0.15)+(X42*0.7))*VLOOKUP(P42,'MunicípiosEstados'!$AA$2:$AB$145,2,FALSE), O42="Paraíba",((W42*0.15)+(X42*0.7))*VLOOKUP(P42,'MunicípiosEstados'!$AC$2:$AD$224,2,FALSE), O42="Paraná",((W42*0.15)+(X42*0.7))*VLOOKUP(P42,'MunicípiosEstados'!$AE$2:$AF$400,2,FALSE), O42="Pernambuco",((W42*0.15)+(X42*0.7))*VLOOKUP(P42,'MunicípiosEstados'!$AG$2:$AH$186,2,FALSE), O42="Piauí",((W42*0.15)+(X42*0.7))*VLOOKUP(P42,'MunicípiosEstados'!$AI$2:$AJ$225,2,FALSE), O42="Rio Grande do Norte",((W42*0.15)+(X42*0.7))*VLOOKUP(P42,'MunicípiosEstados'!$AK$2:$AL$168,2,FALSE), O42="Rio Grande do Sul",((W42*0.15)+(X42*0.7))*VLOOKUP(P42,'MunicípiosEstados'!$AM$2:$AN$498,2,FALSE), O42="Rio de Janeiro",((W42*0.15)+(X42*0.7))*VLOOKUP(P42,'MunicípiosEstados'!$AO$2:$AP$93,2,FALSE), O42="Rondônia",((W42*0.15)+(X42*0.7))*VLOOKUP(P42,'MunicípiosEstados'!$AQ$2:$AR$53,2,FALSE), O42="Roraima",((W42*0.15)+(X42*0.7))*VLOOKUP(P42,'MunicípiosEstados'!$AS$2:$AT$16,2,FALSE), O42="Santa Catarina",((W42*0.15)+(X42*0.7))*VLOOKUP(P42,'MunicípiosEstados'!$AU$2:$AV$296,2,FALSE), O42="São Paulo",((W42*0.15)+(X42*0.7))*VLOOKUP(P42,'MunicípiosEstados'!$AW$2:$AX$646,2,FALSE), O42="Sergipe",((W42*0.15)+(X42*0.7))*VLOOKUP(P42,'MunicípiosEstados'!$AY$2:$AZ$76,2,FALSE), O42="Tocantins",((W42*0.15)+(X42*0.7))*VLOOKUP(P42,'MunicípiosEstados'!$BA$2:$BB$140,2,FALSE), O42="Exterior",((W42*0.15)+(X42*0.7))*VLOOKUP(P42,'MunicípiosEstados'!$BC$2:$BE$221,3,FALSE),TRUE,0 ) -> 13074.75 | AL42: =AK42+AJ42+AI42+AE42+AD42+AC42+AB42+AA42+Z42+Y42 -> 16574.75
A43: =ROW(A43)-1 -> 42 | B43: 45999.776 | C43: sramos@idr.pr.gov.br | D43: A aprovar | E43: =VLOOKUP(G43,DiretoriaDepart.Coord.!$A$1:$C$72,2,FALSE) -> Extensão Rural | F43: =VLOOKUP(G43,DiretoriaDepart.Coord.!$A$1:$C$72,3,FALSE) -> Políticas Públicas | G43: Turismo Rural (Extensão Rural) | I43: II ENCONTRO NACIONAL DE TÉCNICOS EM TURISMO RURAL DA EXTENSÃO RURAL OFICIAL | J43: Encontro | K43: 10 | L43: NÃO DEFINIDO | M43: EMATER-MG | N43: 150 | O43: Minas Gerais | P43: Belo Horizonte | Q43: 45733.333 | R43: 45735.708 | S43: Sim | T43: Presencial | U43: Turismo Rural | V43: O turismo rural tem se consolidado como uma importante estratégia de desenvolvimento territorial, fortalecimento da agricultura familiar e diversificação das fontes de renda no meio rural. Nesse cenário, a atuação qualificada dos técnicos da extensão rural oficial é fundamental para orientar produtores, estimular boas práticas de gestão, promover a valorização cultural e ambiental e ampliar oportunidades econômicas de forma sustentável. Diante dos desafios emergentes — como a necessidade de qualificação contínua, adequação a normativas sanitárias e ambientais, inovação em produtos e serviços turísticos, uso de tecnologias digitais, e fortalecimento de redes de cooperação — torna-se imprescindível promover espaços de atualização, integração e troca de experiências entre profissionais que atuam diretamente na promoção do turismo rural. O II Encontro Nacional de Técnicos em Turismo Rural da Extensão Rural Oficial visa atender a essa demanda, proporcionando um ambiente de aprendizagem coletiva, alinhamento metodológico e consolidação de estratégias para o fortalecimento das políticas públicas voltadas ao desenvolvimento rural. O evento contribuirá para aprimorar a capacidade dos técnicos em apoiar iniciativas locais, qualificar empreendimentos turísticos, fomentar o empreendedorismo rural e ampliar o impacto social e econômico das ações de extensão | W43: 90 | X43: 40 | Y43: 0 | Z43: 0 | AA43: 12000 | AB43: 0 | AC43: 1200 | AD43: 0 | AE43: 0 | AF43: Não | AG43: 0 | AH43: Não | AI43: =IF(AF43="Sim",INT((R43-Q43+1))*K43*VLOOKUP(P43,'Tabelas Auxiliares'!$A$1:$C$400,3,FALSE),0) -> 0 | AJ43: =(AG43/10)*7 -> 0 | AK43: =IFS( O43="Acre",((W43*0.15)+(X43*0.7))*VLOOKUP(P43,'MunicípiosEstados'!$A$2:$B$23,2,FALSE), O43="Alagoas",((W43*0.15)+(X43*0.7))*VLOOKUP(P43,'MunicípiosEstados'!$C$2:$D$103,2,FALSE), O43="Amapá",((W43*0.15)+(X43*0.7))*VLOOKUP(P43,'MunicípiosEstados'!$E$2:$F$17,2,FALSE), O43="Amazonas",((W43*0.15)+(X43*0.7))*VLOOKUP(P43,'MunicípiosEstados'!$G$2:$H$63,2,FALSE), O43="Bahia",((W43*0.15)+(X43*0.7))*VLOOKUP(P43,'MunicípiosEstados'!$I$2:$J$418,2,FALSE), O43="Ceará",((W43*0.15)+(X43*0.7))*VLOOKUP(P43,'MunicípiosEstados'!$K$2:$L$185,2,FALSE), O43="Distrito Federal",((W43*0.15)+(X43*0.7))*VLOOKUP(P43,'MunicípiosEstados'!$M$2:$N$2,2,FALSE), O43="Espírito Santo",((W43*0.15)+(X43*0.7))*VLOOKUP(P43,'MunicípiosEstados'!$O$2:$P$79,2,FALSE), O43="Goiás",((W43*0.15)+(X43*0.7))*VLOOKUP(P43,'MunicípiosEstados'!$Q$2:$R$247,2,FALSE), O43="Maranhão",((W43*0.15)+(X43*0.7))*VLOOKUP(P43,'MunicípiosEstados'!$S$2:$T$218,2,FALSE), O43="Mato Grosso",((W43*0.15)+(X43*0.7))*VLOOKUP(P43,'MunicípiosEstados'!$U$2:$V$143,2,FALSE), O43="Mato Grosso do Sul",((W43*0.15)+(X43*0.7))*VLOOKUP(P43,'MunicípiosEstados'!$W$2:$X$80,2,FALSE), O43="Minas Gerais",((W43*0.15)+(X43*0.7))*VLOOKUP(P43,'MunicípiosEstados'!$Y$2:$Z$854,2,FALSE), O43="Pará",((W43*0.15)+(X43*0.7))*VLOOKUP(P43,'MunicípiosEstados'!$AA$2:$AB$145,2,FALSE), O43="Paraíba",((W43*0.15)+(X43*0.7))*VLOOKUP(P43,'MunicípiosEstados'!$AC$2:$AD$224,2,FALSE), O43="Paraná",((W43*0.15)+(X43*0.7))*VLOOKUP(P43,'MunicípiosEstados'!$AE$2:$AF$400,2,FALSE), O43="Pernambuco",((W43*0.15)+(X43*0.7))*VLOOKUP(P43,'MunicípiosEstados'!$AG$2:$AH$186,2,FALSE), O43="Piauí",((W43*0.15)+(X43*0.7))*VLOOKUP(P43,'MunicípiosEstados'!$AI$2:$AJ$225,2,FALSE), O43="Rio Grande do Norte",((W43*0.15)+(X43*0.7))*VLOOKUP(P43,'MunicípiosEstados'!$AK$2:$AL$168,2,FALSE), O43="Rio Grande do Sul",((W43*0.15)+(X43*0.7))*VLOOKUP(P43,'MunicípiosEstados'!$AM$2:$AN$498,2,FALSE), O43="Rio de Janeiro",((W43*0.15)+(X43*0.7))*VLOOKUP(P43,'MunicípiosEstados'!$AO$2:$AP$93,2,FALSE), O43="Rondônia",((W43*0.15)+(X43*0.7))*VLOOKUP(P43,'MunicípiosEstados'!$AQ$2:$AR$53,2,FALSE), O43="Roraima",((W43*0.15)+(X43*0.7))*VLOOKUP(P43,'MunicípiosEstados'!$AS$2:$AT$16,2,FALSE), O43="Santa Catarina",((W43*0.15)+(X43*0.7))*VLOOKUP(P43,'MunicípiosEstados'!$AU$2:$AV$296,2,FALSE), O43="São Paulo",((W43*0.15)+(X43*0.7))*VLOOKUP(P43,'MunicípiosEstados'!$AW$2:$AX$646,2,FALSE), O43="Sergipe",((W43*0.15)+(X43*0.7))*VLOOKUP(P43,'MunicípiosEstados'!$AY$2:$AZ$76,2,FALSE), O43="Tocantins",((W43*0.15)+(X43*0.7))*VLOOKUP(P43,'MunicípiosEstados'!$BA$2:$BB$140,2,FALSE), O43="Exterior",((W43*0.15)+(X43*0.7))*VLOOKUP(P43,'MunicípiosEstados'!$BC$2:$BE$221,3,FALSE),TRUE,0 ) -> 15407.29 | AL43: =AK43+AJ43+AI43+AE43+AD43+AC43+AB43+AA43+Z43+Y43 -> 28607.29
A44: =ROW(A44)-1 -> 43 | B44: 45964.681 | C44: pablo.nitsche@idr.pr.gov.br | D44: A aprovar | E44: =VLOOKUP(G44,DiretoriaDepart.Coord.!$A$1:$C$72,2,FALSE) -> Pesquisa e Inovação | F44: =VLOOKUP(G44,DiretoriaDepart.Coord.!$A$1:$C$72,3,FALSE) -> Inovação e Comunicação Científica | G44: Agrometereologia (Pesquisa) | I44: Congresso Brasileiro de Engenharia Agrícola (CONBEA) 2026 | J44: Congresso | K44: 1 | L44: PABLO RICARDO NITSCHE | M44: NÃO SE APLICA | N44: 0 | O44: Paraná | P44: FOZ DO IGUAÇU | Q44: 45873.333 | R44: 45875.75 | S44: Sim | T44: Presencial | U44: A Engenharia Agrícola no Contexto das Mudanças Climáticas | V44: A participação no Congresso Brasileiro de Engenharia Agrícola (CONBEA) 2026 é de grande relevância para minha atuação como pesquisador em Agrometeorologia, pois o evento abordará o tema central “A Engenharia Agrícola no Contexto das Mudanças Climáticas”, diretamente relacionado às minhas atividades de pesquisa e extensão voltadas ao monitoramento climático e à sustentabilidade hídrica da produção agropecuária. O congresso representará uma oportunidade estratégica para atualização científica, troca de experiências com especialistas nacionais e internacionais, e fortalecimento de parcerias institucionais que poderão subsidiar o desenvolvimento de novas abordagens e tecnologias aplicadas à mitigação e adaptação das atividades agrícolas frente às mudanças do clima, contribuindo para aprimorar as ações de pesquisa e inovação no âmbito do IDR-Paraná. | W44: 10 | X44: 4 | Y44: 1000 | Z44: 300 | AA44: 0 | AB44: 0 | AC44: 100 | AD44: 0 | AE44: 0 | AF44: Não | AG44: 1200 | AH44: Não | AI44: =IF(AF44="Sim",INT((R44-Q44+1))*K44*VLOOKUP(P44,'Tabelas Auxiliares'!$A$1:$C$400,3,FALSE),0) -> 0 | AJ44: =(AG44/10)*7 -> 840 | AK44: =IFS( O44="Acre",((W44*0.15)+(X44*0.7))*VLOOKUP(P44,'MunicípiosEstados'!$A$2:$B$23,2,FALSE), O44="Alagoas",((W44*0.15)+(X44*0.7))*VLOOKUP(P44,'MunicípiosEstados'!$C$2:$D$103,2,FALSE), O44="Amapá",((W44*0.15)+(X44*0.7))*VLOOKUP(P44,'MunicípiosEstados'!$E$2:$F$17,2,FALSE), O44="Amazonas",((W44*0.15)+(X44*0.7))*VLOOKUP(P44,'MunicípiosEstados'!$G$2:$H$63,2,FALSE), O44="Bahia",((W44*0.15)+(X44*0.7))*VLOOKUP(P44,'MunicípiosEstados'!$I$2:$J$418,2,FALSE), O44="Ceará",((W44*0.15)+(X44*0.7))*VLOOKUP(P44,'MunicípiosEstados'!$K$2:$L$185,2,FALSE), O44="Distrito Federal",((W44*0.15)+(X44*0.7))*VLOOKUP(P44,'MunicípiosEstados'!$M$2:$N$2,2,FALSE), O44="Espírito Santo",((W44*0.15)+(X44*0.7))*VLOOKUP(P44,'MunicípiosEstados'!$O$2:$P$79,2,FALSE), O44="Goiás",((W44*0.15)+(X44*0.7))*VLOOKUP(P44,'MunicípiosEstados'!$Q$2:$R$247,2,FALSE), O44="Maranhão",((W44*0.15)+(X44*0.7))*VLOOKUP(P44,'MunicípiosEstados'!$S$2:$T$218,2,FALSE), O44="Mato Grosso",((W44*0.15)+(X44*0.7))*VLOOKUP(P44,'MunicípiosEstados'!$U$2:$V$143,2,FALSE), O44="Mato Grosso do Sul",((W44*0.15)+(X44*0.7))*VLOOKUP(P44,'MunicípiosEstados'!$W$2:$X$80,2,FALSE), O44="Minas Gerais",((W44*0.15)+(X44*0.7))*VLOOKUP(P44,'MunicípiosEstados'!$Y$2:$Z$854,2,FALSE), O44="Pará",((W44*0.15)+(X44*0.7))*VLOOKUP(P44,'MunicípiosEstados'!$AA$2:$AB$145,2,FALSE), O44="Paraíba",((W44*0.15)+(X44*0.7))*VLOOKUP(P44,'MunicípiosEstados'!$AC$2:$AD$224,2,FALSE), O44="Paraná",((W44*0.15)+(X44*0.7))*VLOOKUP(P44,'MunicípiosEstados'!$AE$2:$AF$400,2,FALSE), O44="Pernambuco",((W44*0.15)+(X44*0.7))*VLOOKUP(P44,'MunicípiosEstados'!$AG$2:$AH$186,2,FALSE), O44="Piauí",((W44*0.15)+(X44*0.7))*VLOOKUP(P44,'MunicípiosEstados'!$AI$2:$AJ$225,2,FALSE), O44="Rio Grande do Norte",((W44*0.15)+(X44*0.7))*VLOOKUP(P44,'MunicípiosEstados'!$AK$2:$AL$168,2,FALSE), O44="Rio Grande do Sul",((W44*0.15)+(X44*0.7))*VLOOKUP(P44,'MunicípiosEstados'!$AM$2:$AN$498,2,FALSE), O44="Rio de Janeiro",((W44*0.15)+(X44*0.7))*VLOOKUP(P44,'MunicípiosEstados'!$AO$2:$AP$93,2,FALSE), O44="Rondônia",((W44*0.15)+(X44*0.7))*VLOOKUP(P44,'MunicípiosEstados'!$AQ$2:$AR$53,2,FALSE), O44="Roraima",((W44*0.15)+(X44*0.7))*VLOOKUP(P44,'MunicípiosEstados'!$AS$2:$AT$16,2,FALSE), O44="Santa Catarina",((W44*0.15)+(X44*0.7))*VLOOKUP(P44,'MunicípiosEstados'!$AU$2:$AV$296,2,FALSE), O44="São Paulo",((W44*0.15)+(X44*0.7))*VLOOKUP(P44,'MunicípiosEstados'!$AW$2:$AX$646,2,FALSE), O44="Sergipe",((W44*0.15)+(X44*0.7))*VLOOKUP(P44,'MunicípiosEstados'!$AY$2:$AZ$76,2,FALSE), O44="Tocantins",((W44*0.15)+(X44*0.7))*VLOOKUP(P44,'MunicípiosEstados'!$BA$2:$BB$140,2,FALSE), O44="Exterior",((W44*0.15)+(X44*0.7))*VLOOKUP(P44,'MunicípiosEstados'!$BC$2:$BE$221,3,FALSE),TRUE,0 ) -> 1249.365 | AL44: =AK44+AJ44+AI44+AE44+AD44+AC44+AB44+AA44+Z44+Y44 -> 3489.365
A45: =ROW(A45)-1 -> 44 | B45: 45973.437 | C45: rafaelpiovezan@idr.pr.gov.br | D45: A aprovar | E45: =VLOOKUP(G45,DiretoriaDepart.Coord.!$A$1:$C$72,2,FALSE) -> Extensão Rural | F45: =VLOOKUP(G45,DiretoriaDepart.Coord.!$A$1:$C$72,3,FALSE) -> Projetos e Cadeias Produtivas | G45: Pecuária de Leite (Extensão Rural) | I45: Preparação Entrevistadores Diagnóstico Carecterização Leite 2026 | J45: Oficina | K45: 100 | M45: SENAR | N45: 5 | O45: Paraná | P45: Londrina | Q45: 45721.333 | R45: 45721.75 | S45: Não | T45: Presencial | U45: Orientação e treinamento voltado ao teste e aplicação do questionário, foco no suporte da coordenação do projeto durante a realização do trabalho de campo. | V45: Necessário para realizar levantamento de campo e visitas dos extensionistas aos estabelecimentos leiteiros selecionados para realização de entrevista voluntária, utilizando um questionário estruturado | W45: 400 | X45: 200 | Y45: 0 | Z45: 1000 | AA45: 0 | AB45: 0 | AC45: 0 | AD45: 0 | AE45: 0 | AF45: Sim | AG45: 12000 | AH45: Sim | AI45: =IF(AF45="Sim",INT((R45-Q45+1))*K45*VLOOKUP(P45,'Tabelas Auxiliares'!$A$1:$C$400,3,FALSE),0) -> 2264 | AJ45: =(AG45/10)*7 -> 8400 | AK45: =IFS( O45="Acre",((W45*0.15)+(X45*0.7))*VLOOKUP(P45,'MunicípiosEstados'!$A$2:$B$23,2,FALSE), O45="Alagoas",((W45*0.15)+(X45*0.7))*VLOOKUP(P45,'MunicípiosEstados'!$C$2:$D$103,2,FALSE), O45="Amapá",((W45*0.15)+(X45*0.7))*VLOOKUP(P45,'MunicípiosEstados'!$E$2:$F$17,2,FALSE), O45="Amazonas",((W45*0.15)+(X45*0.7))*VLOOKUP(P45,'MunicípiosEstados'!$G$2:$H$63,2,FALSE), O45="Bahia",((W45*0.15)+(X45*0.7))*VLOOKUP(P45,'MunicípiosEstados'!$I$2:$J$418,2,FALSE), O45="Ceará",((W45*0.15)+(X45*0.7))*VLOOKUP(P45,'MunicípiosEstados'!$K$2:$L$185,2,FALSE), O45="Distrito Federal",((W45*0.15)+(X45*0.7))*VLOOKUP(P45,'MunicípiosEstados'!$M$2:$N$2,2,FALSE), O45="Espírito Santo",((W45*0.15)+(X45*0.7))*VLOOKUP(P45,'MunicípiosEstados'!$O$2:$P$79,2,FALSE), O45="Goiás",((W45*0.15)+(X45*0.7))*VLOOKUP(P45,'MunicípiosEstados'!$Q$2:$R$247,2,FALSE), O45="Maranhão",((W45*0.15)+(X45*0.7))*VLOOKUP(P45,'MunicípiosEstados'!$S$2:$T$218,2,FALSE), O45="Mato Grosso",((W45*0.15)+(X45*0.7))*VLOOKUP(P45,'MunicípiosEstados'!$U$2:$V$143,2,FALSE), O45="Mato Grosso do Sul",((W45*0.15)+(X45*0.7))*VLOOKUP(P45,'MunicípiosEstados'!$W$2:$X$80,2,FALSE), O45="Minas Gerais",((W45*0.15)+(X45*0.7))*VLOOKUP(P45,'MunicípiosEstados'!$Y$2:$Z$854,2,FALSE), O45="Pará",((W45*0.15)+(X45*0.7))*VLOOKUP(P45,'MunicípiosEstados'!$AA$2:$AB$145,2,FALSE), O45="Paraíba",((W45*0.15)+(X45*0.7))*VLOOKUP(P45,'MunicípiosEstados'!$AC$2:$AD$224,2,FALSE), O45="Paraná",((W45*0.15)+(X45*0.7))*VLOOKUP(P45,'MunicípiosEstados'!$AE$2:$AF$400,2,FALSE), O45="Pernambuco",((W45*0.15)+(X45*0.7))*VLOOKUP(P45,'MunicípiosEstados'!$AG$2:$AH$186,2,FALSE), O45="Piauí",((W45*0.15)+(X45*0.7))*VLOOKUP(P45,'MunicípiosEstados'!$AI$2:$AJ$225,2,FALSE), O45="Rio Grande do Norte",((W45*0.15)+(X45*0.7))*VLOOKUP(P45,'MunicípiosEstados'!$AK$2:$AL$168,2,FALSE), O45="Rio Grande do Sul",((W45*0.15)+(X45*0.7))*VLOOKUP(P45,'MunicípiosEstados'!$AM$2:$AN$498,2,FALSE), O45="Rio de Janeiro",((W45*0.15)+(X45*0.7))*VLOOKUP(P45,'MunicípiosEstados'!$AO$2:$AP$93,2,FALSE), O45="Rondônia",((W45*0.15)+(X45*0.7))*VLOOKUP(P45,'MunicípiosEstados'!$AQ$2:$AR$53,2,FALSE), O45="Roraima",((W45*0.15)+(X45*0.7))*VLOOKUP(P45,'MunicípiosEstados'!$AS$2:$AT$16,2,FALSE), O45="Santa Catarina",((W45*0.15)+(X45*0.7))*VLOOKUP(P45,'MunicípiosEstados'!$AU$2:$AV$296,2,FALSE), O45="São Paulo",((W45*0.15)+(X45*0.7))*VLOOKUP(P45,'MunicípiosEstados'!$AW$2:$AX$646,2,FALSE), O45="Sergipe",((W45*0.15)+(X45*0.7))*VLOOKUP(P45,'MunicípiosEstados'!$AY$2:$AZ$76,2,FALSE), O45="Tocantins",((W45*0.15)+(X45*0.7))*VLOOKUP(P45,'MunicípiosEstados'!$BA$2:$BB$140,2,FALSE), O45="Exterior",((W45*0.15)+(X45*0.7))*VLOOKUP(P45,'MunicípiosEstados'!$BC$2:$BE$221,3,FALSE),TRUE,0 ) -> 58110 | AL45: =AK45+AJ45+AI45+AE45+AD45+AC45+AB45+AA45+Z45+Y45 -> 69774
A46: =ROW(A46)-1 -> 45 | B46: 45973.449 | C46: rafaelpiovezan@idr.pr.gov.br | D46: A aprovar | E46: =VLOOKUP(G46,DiretoriaDepart.Coord.!$A$1:$C$72,2,FALSE) -> Extensão Rural | F46: =VLOOKUP(G46,DiretoriaDepart.Coord.!$A$1:$C$72,3,FALSE) -> Projetos e Cadeias Produtivas | G46: Pecuária de Leite (Extensão Rural) | I46: Sistemas de Produção das Propriedade Leiteira | J46: Oficina | K46: 80 | M46: APCBRH / SENAR | N46: 10 | O46: Paraná | P46: Curitiba | Q46: 45818.333 | R46: 45819.75 | S46: Não | T46: Presencial | U46: Capacitação, Discussão e Realinhamento dos Trabalhos de Campo Programa Leite IDR-Paraná | V46: Necessário para a gestão do Programa e Redirecionamento das Diretrizes Institucionais | W46: 560 | X46: 240 | Y46: 0 | Z46: 2000 | AA46: 0 | AB46: 0 | AC46: 0 | AD46: 0 | AE46: 0 | AF46: Sim | AG46: 15000 | AH46: Sim | AI46: =IF(AF46="Sim",INT((R46-Q46+1))*K46*VLOOKUP(P46,'Tabelas Auxiliares'!$A$1:$C$400,3,FALSE),0) -> 3622.4 | AJ46: =(AG46/10)*7 -> 10500 | AK46: =IFS( O46="Acre",((W46*0.15)+(X46*0.7))*VLOOKUP(P46,'MunicípiosEstados'!$A$2:$B$23,2,FALSE), O46="Alagoas",((W46*0.15)+(X46*0.7))*VLOOKUP(P46,'MunicípiosEstados'!$C$2:$D$103,2,FALSE), O46="Amapá",((W46*0.15)+(X46*0.7))*VLOOKUP(P46,'MunicípiosEstados'!$E$2:$F$17,2,FALSE), O46="Amazonas",((W46*0.15)+(X46*0.7))*VLOOKUP(P46,'MunicípiosEstados'!$G$2:$H$63,2,FALSE), O46="Bahia",((W46*0.15)+(X46*0.7))*VLOOKUP(P46,'MunicípiosEstados'!$I$2:$J$418,2,FALSE), O46="Ceará",((W46*0.15)+(X46*0.7))*VLOOKUP(P46,'MunicípiosEstados'!$K$2:$L$185,2,FALSE), O46="Distrito Federal",((W46*0.15)+(X46*0.7))*VLOOKUP(P46,'MunicípiosEstados'!$M$2:$N$2,2,FALSE), O46="Espírito Santo",((W46*0.15)+(X46*0.7))*VLOOKUP(P46,'MunicípiosEstados'!$O$2:$P$79,2,FALSE), O46="Goiás",((W46*0.15)+(X46*0.7))*VLOOKUP(P46,'MunicípiosEstados'!$Q$2:$R$247,2,FALSE), O46="Maranhão",((W46*0.15)+(X46*0.7))*VLOOKUP(P46,'MunicípiosEstados'!$S$2:$T$218,2,FALSE), O46="Mato Grosso",((W46*0.15)+(X46*0.7))*VLOOKUP(P46,'MunicípiosEstados'!$U$2:$V$143,2,FALSE), O46="Mato Grosso do Sul",((W46*0.15)+(X46*0.7))*VLOOKUP(P46,'MunicípiosEstados'!$W$2:$X$80,2,FALSE), O46="Minas Gerais",((W46*0.15)+(X46*0.7))*VLOOKUP(P46,'MunicípiosEstados'!$Y$2:$Z$854,2,FALSE), O46="Pará",((W46*0.15)+(X46*0.7))*VLOOKUP(P46,'MunicípiosEstados'!$AA$2:$AB$145,2,FALSE), O46="Paraíba",((W46*0.15)+(X46*0.7))*VLOOKUP(P46,'MunicípiosEstados'!$AC$2:$AD$224,2,FALSE), O46="Paraná",((W46*0.15)+(X46*0.7))*VLOOKUP(P46,'MunicípiosEstados'!$AE$2:$AF$400,2,FALSE), O46="Pernambuco",((W46*0.15)+(X46*0.7))*VLOOKUP(P46,'MunicípiosEstados'!$AG$2:$AH$186,2,FALSE), O46="Piauí",((W46*0.15)+(X46*0.7))*VLOOKUP(P46,'MunicípiosEstados'!$AI$2:$AJ$225,2,FALSE), O46="Rio Grande do Norte",((W46*0.15)+(X46*0.7))*VLOOKUP(P46,'MunicípiosEstados'!$AK$2:$AL$168,2,FALSE), O46="Rio Grande do Sul",((W46*0.15)+(X46*0.7))*VLOOKUP(P46,'MunicípiosEstados'!$AM$2:$AN$498,2,FALSE), O46="Rio de Janeiro",((W46*0.15)+(X46*0.7))*VLOOKUP(P46,'MunicípiosEstados'!$AO$2:$AP$93,2,FALSE), O46="Rondônia",((W46*0.15)+(X46*0.7))*VLOOKUP(P46,'MunicípiosEstados'!$AQ$2:$AR$53,2,FALSE), O46="Roraima",((W46*0.15)+(X46*0.7))*VLOOKUP(P46,'MunicípiosEstados'!$AS$2:$AT$16,2,FALSE), O46="Santa Catarina",((W46*0.15)+(X46*0.7))*VLOOKUP(P46,'MunicípiosEstados'!$AU$2:$AV$296,2,FALSE), O46="São Paulo",((W46*0.15)+(X46*0.7))*VLOOKUP(P46,'MunicípiosEstados'!$AW$2:$AX$646,2,FALSE), O46="Sergipe",((W46*0.15)+(X46*0.7))*VLOOKUP(P46,'MunicípiosEstados'!$AY$2:$AZ$76,2,FALSE), O46="Tocantins",((W46*0.15)+(X46*0.7))*VLOOKUP(P46,'MunicípiosEstados'!$BA$2:$BB$140,2,FALSE), O46="Exterior",((W46*0.15)+(X46*0.7))*VLOOKUP(P46,'MunicípiosEstados'!$BC$2:$BE$221,3,FALSE),TRUE,0 ) -> 93557.52 | AL46: =AK46+AJ46+AI46+AE46+AD46+AC46+AB46+AA46+Z46+Y46 -> 109679.92
